{"document_tone": {"tone_categories": [{"category_id": "emotion_tone", "tones": [{"tone_name": "Anger", "score": 0.833047, "tone_id": "anger"}, {"tone_name": "Disgust", "score": 0.170412, "tone_id": "disgust"}, {"tone_name": "Fear", "score": 0.004349, "tone_id": "fear"}, {"tone_name": "Joy", "score": 0.000394, "tone_id": "joy"}, {"tone_name": "Sadness", "score": 0.100405, "tone_id": "sadness"}], "category_name": "Emotion Tone"}, {"category_id": "language_tone", "tones": [{"tone_name": "Analytical", "score": 0.0, "tone_id": "analytical"}, {"tone_name": "Confident", "score": 0.0, "tone_id": "confident"}, {"tone_name": "Tentative", "score": 0.200829, "tone_id": "tentative"}], "category_name": "Language Tone"}, {"category_id": "social_tone", "tones": [{"tone_name": "Openness", "score": 0.643885, "tone_id": "openness_big5"}, {"tone_name": "Conscientiousness", "score": 0.153805, "tone_id": "conscientiousness_big5"}, {"tone_name": "Extraversion", "score": 0.665932, "tone_id": "extraversion_big5"}, {"tone_name": "Agreeableness", "score": 0.393539, "tone_id": "agreeableness_big5"}, {"tone_name": "Emotional Range", "score": 0.480164, "tone_id": "emotional_range_big5"}], "category_name": "Social Tone"}]}, "sentences_tone": [{"input_to": 38, "text": "Ain't no telling what I'm finna be on.", "sentence_id": 0, "tone_categories": [{"category_id": "emotion_tone", "tones": [{"tone_name": "Anger", "score": 0.335818, "tone_id": "anger"}, {"tone_name": "Disgust", "score": 0.046236, "tone_id": "disgust"}, {"tone_name": "Fear", "score": 0.07308, "tone_id": "fear"}, {"tone_name": "Joy", "score": 0.199678, "tone_id": "joy"}, {"tone_name": "Sadness", "score": 0.432339, "tone_id": "sadness"}], "category_name": "Emotion Tone"}, {"category_id": "language_tone", "tones": [{"tone_name": "Analytical", "score": 0.0, "tone_id": "analytical"}, {"tone_name": "Confident", "score": 0.0, "tone_id": "confident"}, {"tone_name": "Tentative", "score": 0.0, "tone_id": "tentative"}], "category_name": "Language Tone"}, {"category_id": "social_tone", "tones": [{"tone_name": "Openness", "score": 0.264562, "tone_id": "openness_big5"}, {"tone_name": "Conscientiousness", "score": 0.384154, "tone_id": "conscientiousness_big5"}, {"tone_name": "Extraversion", "score": 0.440042, "tone_id": "extraversion_big5"}, {"tone_name": "Agreeableness", "score": 0.415722, "tone_id": "agreeableness_big5"}, {"tone_name": "Emotional Range", "score": 0.32161, "tone_id": "emotional_range_big5"}], "category_name": "Social Tone"}], "input_from": 0}, {"input_to": 69, "text": "I'm beyond all that fuck shit.", "sentence_id": 1, "tone_categories": [{"category_id": "emotion_tone", "tones": [{"tone_name": "Anger", "score": 0.431579, "tone_id": "anger"}, {"tone_name": "Disgust", "score": 0.354997, "tone_id": "disgust"}, {"tone_name": "Fear", "score": 0.132085, "tone_id": "fear"}, {"tone_name": "Joy", "score": 0.040611, "tone_id": "joy"}, {"tone_name": "Sadness", "score": 0.110384, "tone_id": "sadness"}], "category_name": "Emotion Tone"}, {"category_id": "language_tone", "tones": [{"tone_name": "Analytical", "score": 0.0, "tone_id": "analytical"}, {"tone_name": "Confident", "score": 0.942582, "tone_id": "confident"}, {"tone_name": "Tentative", "score": 0.0, "tone_id": "tentative"}], "category_name": "Language Tone"}, {"category_id": "social_tone", "tones": [{"tone_name": "Openness", "score": 0.617437, "tone_id": "openness_big5"}, {"tone_name": "Conscientiousness", "score": 0.342315, "tone_id": "conscientiousness_big5"}, {"tone_name": "Extraversion", "score": 0.408939, "tone_id": "extraversion_big5"}, {"tone_name": "Agreeableness", "score": 0.336641, "tone_id": "agreeableness_big5"}, {"tone_name": "Emotional Range", "score": 0.022584, "tone_id": "emotional_range_big5"}], "category_name": "Social Tone"}], "input_from": 39}, {"input_to": 117, "text": "Hey lil mama would you like to be my sunshine?.", "sentence_id": 2, "tone_categories": [{"category_id": "emotion_tone", "tones": [{"tone_name": "Anger", "score": 0.062118, "tone_id": "anger"}, {"tone_name": "Disgust", "score": 0.046766, "tone_id": "disgust"}, {"tone_name": "Fear", "score": 0.077087, "tone_id": "fear"}, {"tone_name": "Joy", "score": 0.677399, "tone_id": "joy"}, {"tone_name": "Sadness", "score": 0.201687, "tone_id": "sadness"}], "category_name": "Emotion Tone"}, {"category_id": "language_tone", "tones": [{"tone_name": "Analytical", "score": 0.0, "tone_id": "analytical"}, {"tone_name": "Confident", "score": 0.0, "tone_id": "confident"}, {"tone_name": "Tentative", "score": 0.497569, "tone_id": "tentative"}], "category_name": "Language Tone"}, {"category_id": "social_tone", "tones": [{"tone_name": "Openness", "score": 0.251068, "tone_id": "openness_big5"}, {"tone_name": "Conscientiousness", "score": 0.789862, "tone_id": "conscientiousness_big5"}, {"tone_name": "Extraversion", "score": 0.958007, "tone_id": "extraversion_big5"}, {"tone_name": "Agreeableness", "score": 0.970775, "tone_id": "agreeableness_big5"}, {"tone_name": "Emotional Range", "score": 0.76472, "tone_id": "emotional_range_big5"}], "category_name": "Social Tone"}], "input_from": 70}, {"input_to": 173, "text": "Nigga touch my gang we gon turn this shit to Columbine.", "sentence_id": 3, "tone_categories": [{"category_id": "emotion_tone", "tones": [{"tone_name": "Anger", "score": 0.193937, "tone_id": "anger"}, {"tone_name": "Disgust", "score": 0.114575, "tone_id": "disgust"}, {"tone_name": "Fear", "score": 0.138218, "tone_id": "fear"}, {"tone_name": "Joy", "score": 0.034154, "tone_id": "joy"}, {"tone_name": "Sadness", "score": 0.599247, "tone_id": "sadness"}], "category_name": "Emotion Tone"}, {"category_id": "language_tone", "tones": [{"tone_name": "Analytical", "score": 0.0, "tone_id": "analytical"}, {"tone_name": "Confident", "score": 0.0, "tone_id": "confident"}, {"tone_name": "Tentative", "score": 0.0, "tone_id": "tentative"}], "category_name": "Language Tone"}, {"category_id": "social_tone", "tones": [{"tone_name": "Openness", "score": 0.319726, "tone_id": "openness_big5"}, {"tone_name": "Conscientiousness", "score": 0.365578, "tone_id": "conscientiousness_big5"}, {"tone_name": "Extraversion", "score": 0.552517, "tone_id": "extraversion_big5"}, {"tone_name": "Agreeableness", "score": 0.269186, "tone_id": "agreeableness_big5"}, {"tone_name": "Emotional Range", "score": 0.743889, "tone_id": "emotional_range_big5"}], "category_name": "Social Tone"}], "input_from": 118}, {"input_to": 249, "text": "Ice on my neck cost me 10 times 3.\n30, 000 dollars for a nigga to get flee.", "sentence_id": 4, "tone_categories": [{"category_id": "emotion_tone", "tones": [{"tone_name": "Anger", "score": 0.090453, "tone_id": "anger"}, {"tone_name": "Disgust", "score": 0.066079, "tone_id": "disgust"}, {"tone_name": "Fear", "score": 0.04868, "tone_id": "fear"}, {"tone_name": "Joy", "score": 0.031633, "tone_id": "joy"}, {"tone_name": "Sadness", "score": 0.845859, "tone_id": "sadness"}], "category_name": "Emotion Tone"}, {"category_id": "language_tone", "tones": [{"tone_name": "Analytical", "score": 0.0, "tone_id": "analytical"}, {"tone_name": "Confident", "score": 0.0, "tone_id": "confident"}, {"tone_name": "Tentative", "score": 0.0, "tone_id": "tentative"}], "category_name": "Language Tone"}, {"category_id": "social_tone", "tones": [{"tone_name": "Openness", "score": 0.189103, "tone_id": "openness_big5"}, {"tone_name": "Conscientiousness", "score": 0.419947, "tone_id": "conscientiousness_big5"}, {"tone_name": "Extraversion", "score": 0.727666, "tone_id": "extraversion_big5"}, {"tone_name": "Agreeableness", "score": 0.642872, "tone_id": "agreeableness_big5"}, {"tone_name": "Emotional Range", "score": 0.790043, "tone_id": "emotional_range_big5"}], "category_name": "Social Tone"}], "input_from": 174}, {"input_to": 290, "text": "I just hit Rodeo and I spent like 10 Gs.", "sentence_id": 5, "tone_categories": [{"category_id": "emotion_tone", "tones": [{"tone_name": "Anger", "score": 0.123241, "tone_id": "anger"}, {"tone_name": "Disgust", "score": 0.073811, "tone_id": "disgust"}, {"tone_name": "Fear", "score": 0.04125, "tone_id": "fear"}, {"tone_name": "Joy", "score": 0.433532, "tone_id": "joy"}, {"tone_name": "Sadness", "score": 0.380378, "tone_id": "sadness"}], "category_name": "Emotion Tone"}, {"category_id": "language_tone", "tones": [{"tone_name": "Analytical", "score": 0.0, "tone_id": "analytical"}, {"tone_name": "Confident", "score": 0.0, "tone_id": "confident"}, {"tone_name": "Tentative", "score": 0.928936, "tone_id": "tentative"}], "category_name": "Language Tone"}, {"category_id": "social_tone", "tones": [{"tone_name": "Openness", "score": 0.27886, "tone_id": "openness_big5"}, {"tone_name": "Conscientiousness", "score": 0.242046, "tone_id": "conscientiousness_big5"}, {"tone_name": "Extraversion", "score": 0.28191, "tone_id": "extraversion_big5"}, {"tone_name": "Agreeableness", "score": 0.488619, "tone_id": "agreeableness_big5"}, {"tone_name": "Emotional Range", "score": 0.562268, "tone_id": "emotional_range_big5"}], "category_name": "Social Tone"}], "input_from": 250}, {"input_to": 340, "text": "I just did a show and spent the check on my mama.", "sentence_id": 6, "tone_categories": [{"category_id": "emotion_tone", "tones": [{"tone_name": "Anger", "score": 0.130648, "tone_id": "anger"}, {"tone_name": "Disgust", "score": 0.12282, "tone_id": "disgust"}, {"tone_name": "Fear", "score": 0.050602, "tone_id": "fear"}, {"tone_name": "Joy", "score": 0.548018, "tone_id": "joy"}, {"tone_name": "Sadness", "score": 0.251031, "tone_id": "sadness"}], "category_name": "Emotion Tone"}, {"category_id": "language_tone", "tones": [{"tone_name": "Analytical", "score": 0.620279, "tone_id": "analytical"}, {"tone_name": "Confident", "score": 0.0, "tone_id": "confident"}, {"tone_name": "Tentative", "score": 0.75152, "tone_id": "tentative"}], "category_name": "Language Tone"}, {"category_id": "social_tone", "tones": [{"tone_name": "Openness", "score": 0.130878, "tone_id": "openness_big5"}, {"tone_name": "Conscientiousness", "score": 0.90346, "tone_id": "conscientiousness_big5"}, {"tone_name": "Extraversion", "score": 0.745553, "tone_id": "extraversion_big5"}, {"tone_name": "Agreeableness", "score": 0.766979, "tone_id": "agreeableness_big5"}, {"tone_name": "Emotional Range", "score": 0.841734, "tone_id": "emotional_range_big5"}], "category_name": "Social Tone"}], "input_from": 291}, {"input_to": 389, "text": "When I go on vacay I might rent out the Bahamas.", "sentence_id": 7, "tone_categories": [{"category_id": "emotion_tone", "tones": [{"tone_name": "Anger", "score": 0.119279, "tone_id": "anger"}, {"tone_name": "Disgust", "score": 0.143685, "tone_id": "disgust"}, {"tone_name": "Fear", "score": 0.468654, "tone_id": "fear"}, {"tone_name": "Joy", "score": 0.136726, "tone_id": "joy"}, {"tone_name": "Sadness", "score": 0.241949, "tone_id": "sadness"}], "category_name": "Emotion Tone"}, {"category_id": "language_tone", "tones": [{"tone_name": "Analytical", "score": 0.0, "tone_id": "analytical"}, {"tone_name": "Confident", "score": 0.0, "tone_id": "confident"}, {"tone_name": "Tentative", "score": 0.786991, "tone_id": "tentative"}], "category_name": "Language Tone"}, {"category_id": "social_tone", "tones": [{"tone_name": "Openness", "score": 0.041003, "tone_id": "openness_big5"}, {"tone_name": "Conscientiousness", "score": 0.421763, "tone_id": "conscientiousness_big5"}, {"tone_name": "Extraversion", "score": 0.522536, "tone_id": "extraversion_big5"}, {"tone_name": "Agreeableness", "score": 0.402388, "tone_id": "agreeableness_big5"}, {"tone_name": "Emotional Range", "score": 0.693172, "tone_id": "emotional_range_big5"}], "category_name": "Social Tone"}], "input_from": 341}, {"input_to": 444, "text": "And I keep like 10 phones, damn I'm really never home.", "sentence_id": 8, "tone_categories": [{"category_id": "emotion_tone", "tones": [{"tone_name": "Anger", "score": 0.358553, "tone_id": "anger"}, {"tone_name": "Disgust", "score": 0.021684, "tone_id": "disgust"}, {"tone_name": "Fear", "score": 0.026683, "tone_id": "fear"}, {"tone_name": "Joy", "score": 0.156876, "tone_id": "joy"}, {"tone_name": "Sadness", "score": 0.509737, "tone_id": "sadness"}], "category_name": "Emotion Tone"}, {"category_id": "language_tone", "tones": [{"tone_name": "Analytical", "score": 0.0, "tone_id": "analytical"}, {"tone_name": "Confident", "score": 0.0, "tone_id": "confident"}, {"tone_name": "Tentative", "score": 0.0, "tone_id": "tentative"}], "category_name": "Language Tone"}, {"category_id": "social_tone", "tones": [{"tone_name": "Openness", "score": 0.006642, "tone_id": "openness_big5"}, {"tone_name": "Conscientiousness", "score": 0.533911, "tone_id": "conscientiousness_big5"}, {"tone_name": "Extraversion", "score": 0.059439, "tone_id": "extraversion_big5"}, {"tone_name": "Agreeableness", "score": 0.299107, "tone_id": "agreeableness_big5"}, {"tone_name": "Emotional Range", "score": 0.015551, "tone_id": "emotional_range_big5"}], "category_name": "Social Tone"}], "input_from": 390}, {"input_to": 492, "text": "All these niggas clones tryna copy what I'm on.", "sentence_id": 9, "tone_categories": [{"category_id": "emotion_tone", "tones": [{"tone_name": "Anger", "score": 0.046553, "tone_id": "anger"}, {"tone_name": "Disgust", "score": 0.199008, "tone_id": "disgust"}, {"tone_name": "Fear", "score": 0.074557, "tone_id": "fear"}, {"tone_name": "Joy", "score": 0.045065, "tone_id": "joy"}, {"tone_name": "Sadness", "score": 0.721526, "tone_id": "sadness"}], "category_name": "Emotion Tone"}, {"category_id": "language_tone", "tones": [{"tone_name": "Analytical", "score": 0.0, "tone_id": "analytical"}, {"tone_name": "Confident", "score": 0.874372, "tone_id": "confident"}, {"tone_name": "Tentative", "score": 0.0, "tone_id": "tentative"}], "category_name": "Language Tone"}, {"category_id": "social_tone", "tones": [{"tone_name": "Openness", "score": 0.835077, "tone_id": "openness_big5"}, {"tone_name": "Conscientiousness", "score": 0.433654, "tone_id": "conscientiousness_big5"}, {"tone_name": "Extraversion", "score": 0.454725, "tone_id": "extraversion_big5"}, {"tone_name": "Agreeableness", "score": 0.242899, "tone_id": "agreeableness_big5"}, {"tone_name": "Emotional Range", "score": 0.344515, "tone_id": "emotional_range_big5"}], "category_name": "Social Tone"}], "input_from": 445}, {"input_to": 537, "text": "Nigga get your own, tryna pick a nigga bone.", "sentence_id": 10, "tone_categories": [{"category_id": "emotion_tone", "tones": [{"tone_name": "Anger", "score": 0.021216, "tone_id": "anger"}, {"tone_name": "Disgust", "score": 0.073079, "tone_id": "disgust"}, {"tone_name": "Fear", "score": 0.042344, "tone_id": "fear"}, {"tone_name": "Joy", "score": 0.181591, "tone_id": "joy"}, {"tone_name": "Sadness", "score": 0.754955, "tone_id": "sadness"}], "category_name": "Emotion Tone"}, {"category_id": "language_tone", "tones": [{"tone_name": "Analytical", "score": 0.0, "tone_id": "analytical"}, {"tone_name": "Confident", "score": 0.0, "tone_id": "confident"}, {"tone_name": "Tentative", "score": 0.0, "tone_id": "tentative"}], "category_name": "Language Tone"}, {"category_id": "social_tone", "tones": [{"tone_name": "Openness", "score": 0.689871, "tone_id": "openness_big5"}, {"tone_name": "Conscientiousness", "score": 0.291673, "tone_id": "conscientiousness_big5"}, {"tone_name": "Extraversion", "score": 0.54838, "tone_id": "extraversion_big5"}, {"tone_name": "Agreeableness", "score": 0.508982, "tone_id": "agreeableness_big5"}, {"tone_name": "Emotional Range", "score": 0.780819, "tone_id": "emotional_range_big5"}], "category_name": "Social Tone"}], "input_from": 493}, {"input_to": 580, "text": "Way to Brother Skip, boy I had a good day.", "sentence_id": 11, "tone_categories": [{"category_id": "emotion_tone", "tones": [{"tone_name": "Anger", "score": 0.065594, "tone_id": "anger"}, {"tone_name": "Disgust", "score": 0.019085, "tone_id": "disgust"}, {"tone_name": "Fear", "score": 0.052019, "tone_id": "fear"}, {"tone_name": "Joy", "score": 0.812911, "tone_id": "joy"}, {"tone_name": "Sadness", "score": 0.103489, "tone_id": "sadness"}], "category_name": "Emotion Tone"}, {"category_id": "language_tone", "tones": [{"tone_name": "Analytical", "score": 0.235443, "tone_id": "analytical"}, {"tone_name": "Confident", "score": 0.0, "tone_id": "confident"}, {"tone_name": "Tentative", "score": 0.0, "tone_id": "tentative"}], "category_name": "Language Tone"}, {"category_id": "social_tone", "tones": [{"tone_name": "Openness", "score": 0.000132, "tone_id": "openness_big5"}, {"tone_name": "Conscientiousness", "score": 0.171432, "tone_id": "conscientiousness_big5"}, {"tone_name": "Extraversion", "score": 0.497196, "tone_id": "extraversion_big5"}, {"tone_name": "Agreeableness", "score": 0.767164, "tone_id": "agreeableness_big5"}, {"tone_name": "Emotional Range", "score": 0.805337, "tone_id": "emotional_range_big5"}], "category_name": "Social Tone"}], "input_from": 538}, {"input_to": 621, "text": "Metro PCS trapping boy I'm making plays.", "sentence_id": 12, "tone_categories": [{"category_id": "emotion_tone", "tones": [{"tone_name": "Anger", "score": 0.150819, "tone_id": "anger"}, {"tone_name": "Disgust", "score": 0.093829, "tone_id": "disgust"}, {"tone_name": "Fear", "score": 0.139923, "tone_id": "fear"}, {"tone_name": "Joy", "score": 0.552004, "tone_id": "joy"}, {"tone_name": "Sadness", "score": 0.123281, "tone_id": "sadness"}], "category_name": "Emotion Tone"}, {"category_id": "language_tone", "tones": [{"tone_name": "Analytical", "score": 0.801827, "tone_id": "analytical"}, {"tone_name": "Confident", "score": 0.0, "tone_id": "confident"}, {"tone_name": "Tentative", "score": 0.0, "tone_id": "tentative"}], "category_name": "Language Tone"}, {"category_id": "social_tone", "tones": [{"tone_name": "Openness", "score": 0.670882, "tone_id": "openness_big5"}, {"tone_name": "Conscientiousness", "score": 0.155463, "tone_id": "conscientiousness_big5"}, {"tone_name": "Extraversion", "score": 0.59959, "tone_id": "extraversion_big5"}, {"tone_name": "Agreeableness", "score": 0.418969, "tone_id": "agreeableness_big5"}, {"tone_name": "Emotional Range", "score": 0.186694, "tone_id": "emotional_range_big5"}], "category_name": "Social Tone"}], "input_from": 581}, {"input_to": 673, "text": "50 shades of grey, beat that pussy like Hulk Hogan.", "sentence_id": 13, "tone_categories": [{"category_id": "emotion_tone", "tones": [{"tone_name": "Anger", "score": 0.340055, "tone_id": "anger"}, {"tone_name": "Disgust", "score": 0.252573, "tone_id": "disgust"}, {"tone_name": "Fear", "score": 0.080835, "tone_id": "fear"}, {"tone_name": "Joy", "score": 0.002743, "tone_id": "joy"}, {"tone_name": "Sadness", "score": 0.485573, "tone_id": "sadness"}], "category_name": "Emotion Tone"}, {"category_id": "language_tone", "tones": [{"tone_name": "Analytical", "score": 0.0, "tone_id": "analytical"}, {"tone_name": "Confident", "score": 0.0, "tone_id": "confident"}, {"tone_name": "Tentative", "score": 0.497569, "tone_id": "tentative"}], "category_name": "Language Tone"}, {"category_id": "social_tone", "tones": [{"tone_name": "Openness", "score": 0.959877, "tone_id": "openness_big5"}, {"tone_name": "Conscientiousness", "score": 0.194215, "tone_id": "conscientiousness_big5"}, {"tone_name": "Extraversion", "score": 0.58306, "tone_id": "extraversion_big5"}, {"tone_name": "Agreeableness", "score": 0.544676, "tone_id": "agreeableness_big5"}, {"tone_name": "Emotional Range", "score": 0.543431, "tone_id": "emotional_range_big5"}], "category_name": "Social Tone"}], "input_from": 622}, {"input_to": 731, "text": "I know you know my slogan, if I ain't bout guap I'm gone.", "sentence_id": 14, "tone_categories": [{"category_id": "emotion_tone", "tones": [{"tone_name": "Anger", "score": 0.078729, "tone_id": "anger"}, {"tone_name": "Disgust", "score": 0.021001, "tone_id": "disgust"}, {"tone_name": "Fear", "score": 0.248601, "tone_id": "fear"}, {"tone_name": "Joy", "score": 0.15171, "tone_id": "joy"}, {"tone_name": "Sadness", "score": 0.584752, "tone_id": "sadness"}], "category_name": "Emotion Tone"}, {"category_id": "language_tone", "tones": [{"tone_name": "Analytical", "score": 0.893044, "tone_id": "analytical"}, {"tone_name": "Confident", "score": 0.0, "tone_id": "confident"}, {"tone_name": "Tentative", "score": 0.0, "tone_id": "tentative"}], "category_name": "Language Tone"}, {"category_id": "social_tone", "tones": [{"tone_name": "Openness", "score": 0.373229, "tone_id": "openness_big5"}, {"tone_name": "Conscientiousness", "score": 0.602276, "tone_id": "conscientiousness_big5"}, {"tone_name": "Extraversion", "score": 0.24416, "tone_id": "extraversion_big5"}, {"tone_name": "Agreeableness", "score": 0.379646, "tone_id": "agreeableness_big5"}, {"tone_name": "Emotional Range", "score": 0.444078, "tone_id": "emotional_range_big5"}], "category_name": "Social Tone"}], "input_from": 674}, {"input_to": 793, "text": "Niggas hating cause I'm chosen from the concrete that I rose.", "sentence_id": 15, "tone_categories": [{"category_id": "emotion_tone", "tones": [{"tone_name": "Anger", "score": 0.038771, "tone_id": "anger"}, {"tone_name": "Disgust", "score": 0.036186, "tone_id": "disgust"}, {"tone_name": "Fear", "score": 0.05881, "tone_id": "fear"}, {"tone_name": "Joy", "score": 0.123256, "tone_id": "joy"}, {"tone_name": "Sadness", "score": 0.787735, "tone_id": "sadness"}], "category_name": "Emotion Tone"}, {"category_id": "language_tone", "tones": [{"tone_name": "Analytical", "score": 0.653099, "tone_id": "analytical"}, {"tone_name": "Confident", "score": 0.0, "tone_id": "confident"}, {"tone_name": "Tentative", "score": 0.0, "tone_id": "tentative"}], "category_name": "Language Tone"}, {"category_id": "social_tone", "tones": [{"tone_name": "Openness", "score": 0.990473, "tone_id": "openness_big5"}, {"tone_name": "Conscientiousness", "score": 0.17708, "tone_id": "conscientiousness_big5"}, {"tone_name": "Extraversion", "score": 0.504533, "tone_id": "extraversion_big5"}, {"tone_name": "Agreeableness", "score": 0.339454, "tone_id": "agreeableness_big5"}, {"tone_name": "Emotional Range", "score": 0.161854, "tone_id": "emotional_range_big5"}], "category_name": "Social Tone"}], "input_from": 732}, {"input_to": 855, "text": "Shawty staring at my necklace cause my diamonds really froze.", "sentence_id": 16, "tone_categories": [{"category_id": "emotion_tone", "tones": [{"tone_name": "Anger", "score": 0.31572, "tone_id": "anger"}, {"tone_name": "Disgust", "score": 0.035674, "tone_id": "disgust"}, {"tone_name": "Fear", "score": 0.02181, "tone_id": "fear"}, {"tone_name": "Joy", "score": 0.163854, "tone_id": "joy"}, {"tone_name": "Sadness", "score": 0.516152, "tone_id": "sadness"}], "category_name": "Emotion Tone"}, {"category_id": "language_tone", "tones": [{"tone_name": "Analytical", "score": 0.882284, "tone_id": "analytical"}, {"tone_name": "Confident", "score": 0.0, "tone_id": "confident"}, {"tone_name": "Tentative", "score": 0.0, "tone_id": "tentative"}], "category_name": "Language Tone"}, {"category_id": "social_tone", "tones": [{"tone_name": "Openness", "score": 0.51604, "tone_id": "openness_big5"}, {"tone_name": "Conscientiousness", "score": 0.240262, "tone_id": "conscientiousness_big5"}, {"tone_name": "Extraversion", "score": 0.698294, "tone_id": "extraversion_big5"}, {"tone_name": "Agreeableness", "score": 0.62407, "tone_id": "agreeableness_big5"}, {"tone_name": "Emotional Range", "score": 0.056251, "tone_id": "emotional_range_big5"}], "category_name": "Social Tone"}], "input_from": 794}, {"input_to": 914, "text": "Put that dick up in her pussy bet she feel it in her toes.", "sentence_id": 17, "tone_categories": [{"category_id": "emotion_tone", "tones": [{"tone_name": "Anger", "score": 0.080787, "tone_id": "anger"}, {"tone_name": "Disgust", "score": 0.524601, "tone_id": "disgust"}, {"tone_name": "Fear", "score": 0.18, "tone_id": "fear"}, {"tone_name": "Joy", "score": 0.039566, "tone_id": "joy"}, {"tone_name": "Sadness", "score": 0.282142, "tone_id": "sadness"}], "category_name": "Emotion Tone"}, {"category_id": "language_tone", "tones": [{"tone_name": "Analytical", "score": 0.0, "tone_id": "analytical"}, {"tone_name": "Confident", "score": 0.0, "tone_id": "confident"}, {"tone_name": "Tentative", "score": 0.845297, "tone_id": "tentative"}], "category_name": "Language Tone"}, {"category_id": "social_tone", "tones": [{"tone_name": "Openness", "score": 0.635777, "tone_id": "openness_big5"}, {"tone_name": "Conscientiousness", "score": 0.218041, "tone_id": "conscientiousness_big5"}, {"tone_name": "Extraversion", "score": 0.562303, "tone_id": "extraversion_big5"}, {"tone_name": "Agreeableness", "score": 0.680951, "tone_id": "agreeableness_big5"}, {"tone_name": "Emotional Range", "score": 0.390585, "tone_id": "emotional_range_big5"}], "category_name": "Social Tone"}], "input_from": 856}, {"input_to": 963, "text": "I'm a real young nigga from the 6 throwing bows.", "sentence_id": 18, "tone_categories": [{"category_id": "emotion_tone", "tones": [{"tone_name": "Anger", "score": 0.024035, "tone_id": "anger"}, {"tone_name": "Disgust", "score": 0.086298, "tone_id": "disgust"}, {"tone_name": "Fear", "score": 0.103662, "tone_id": "fear"}, {"tone_name": "Joy", "score": 0.037534, "tone_id": "joy"}, {"tone_name": "Sadness", "score": 0.832278, "tone_id": "sadness"}], "category_name": "Emotion Tone"}, {"category_id": "language_tone", "tones": [{"tone_name": "Analytical", "score": 0.0, "tone_id": "analytical"}, {"tone_name": "Confident", "score": 0.618451, "tone_id": "confident"}, {"tone_name": "Tentative", "score": 0.0, "tone_id": "tentative"}], "category_name": "Language Tone"}, {"category_id": "social_tone", "tones": [{"tone_name": "Openness", "score": 0.89498, "tone_id": "openness_big5"}, {"tone_name": "Conscientiousness", "score": 0.154256, "tone_id": "conscientiousness_big5"}, {"tone_name": "Extraversion", "score": 0.529701, "tone_id": "extraversion_big5"}, {"tone_name": "Agreeableness", "score": 0.480388, "tone_id": "agreeableness_big5"}, {"tone_name": "Emotional Range", "score": 0.507261, "tone_id": "emotional_range_big5"}], "category_name": "Social Tone"}], "input_from": 915}, {"input_to": 1012, "text": "I'm a real young nigga from the 6 throwing bows.", "sentence_id": 19, "tone_categories": [{"category_id": "emotion_tone", "tones": [{"tone_name": "Anger", "score": 0.024035, "tone_id": "anger"}, {"tone_name": "Disgust", "score": 0.086298, "tone_id": "disgust"}, {"tone_name": "Fear", "score": 0.103662, "tone_id": "fear"}, {"tone_name": "Joy", "score": 0.037534, "tone_id": "joy"}, {"tone_name": "Sadness", "score": 0.832278, "tone_id": "sadness"}], "category_name": "Emotion Tone"}, {"category_id": "language_tone", "tones": [{"tone_name": "Analytical", "score": 0.0, "tone_id": "analytical"}, {"tone_name": "Confident", "score": 0.618451, "tone_id": "confident"}, {"tone_name": "Tentative", "score": 0.0, "tone_id": "tentative"}], "category_name": "Language Tone"}, {"category_id": "social_tone", "tones": [{"tone_name": "Openness", "score": 0.89498, "tone_id": "openness_big5"}, {"tone_name": "Conscientiousness", "score": 0.154256, "tone_id": "conscientiousness_big5"}, {"tone_name": "Extraversion", "score": 0.529701, "tone_id": "extraversion_big5"}, {"tone_name": "Agreeableness", "score": 0.480388, "tone_id": "agreeableness_big5"}, {"tone_name": "Emotional Range", "score": 0.507261, "tone_id": "emotional_range_big5"}], "category_name": "Social Tone"}], "input_from": 964}, {"input_to": 1055, "text": "Real young nigga from the 6 throwing bows.", "sentence_id": 20, "tone_categories": [{"category_id": "emotion_tone", "tones": [{"tone_name": "Anger", "score": 0.025469, "tone_id": "anger"}, {"tone_name": "Disgust", "score": 0.069894, "tone_id": "disgust"}, {"tone_name": "Fear", "score": 0.082914, "tone_id": "fear"}, {"tone_name": "Joy", "score": 0.043998, "tone_id": "joy"}, {"tone_name": "Sadness", "score": 0.838626, "tone_id": "sadness"}], "category_name": "Emotion Tone"}, {"category_id": "language_tone", "tones": [{"tone_name": "Analytical", "score": 0.0, "tone_id": "analytical"}, {"tone_name": "Confident", "score": 0.704642, "tone_id": "confident"}, {"tone_name": "Tentative", "score": 0.0, "tone_id": "tentative"}], "category_name": "Language Tone"}, {"category_id": "social_tone", "tones": [{"tone_name": "Openness", "score": 0.856924, "tone_id": "openness_big5"}, {"tone_name": "Conscientiousness", "score": 0.273209, "tone_id": "conscientiousness_big5"}, {"tone_name": "Extraversion", "score": 0.571265, "tone_id": "extraversion_big5"}, {"tone_name": "Agreeableness", "score": 0.573341, "tone_id": "agreeableness_big5"}, {"tone_name": "Emotional Range", "score": 0.665285, "tone_id": "emotional_range_big5"}], "category_name": "Social Tone"}], "input_from": 1013}, {"input_to": 1100, "text": "In the middle of the party bitch get off me.", "sentence_id": 21, "tone_categories": [{"category_id": "emotion_tone", "tones": [{"tone_name": "Anger", "score": 0.163159, "tone_id": "anger"}, {"tone_name": "Disgust", "score": 0.128805, "tone_id": "disgust"}, {"tone_name": "Fear", "score": 0.161715, "tone_id": "fear"}, {"tone_name": "Joy", "score": 0.268506, "tone_id": "joy"}, {"tone_name": "Sadness", "score": 0.339725, "tone_id": "sadness"}], "category_name": "Emotion Tone"}, {"category_id": "language_tone", "tones": [{"tone_name": "Analytical", "score": 0.0, "tone_id": "analytical"}, {"tone_name": "Confident", "score": 0.0, "tone_id": "confident"}, {"tone_name": "Tentative", "score": 0.0, "tone_id": "tentative"}], "category_name": "Language Tone"}, {"category_id": "social_tone", "tones": [{"tone_name": "Openness", "score": 0.499143, "tone_id": "openness_big5"}, {"tone_name": "Conscientiousness", "score": 0.390482, "tone_id": "conscientiousness_big5"}, {"tone_name": "Extraversion", "score": 0.899297, "tone_id": "extraversion_big5"}, {"tone_name": "Agreeableness", "score": 0.199983, "tone_id": "agreeableness_big5"}, {"tone_name": "Emotional Range", "score": 0.666529, "tone_id": "emotional_range_big5"}], "category_name": "Social Tone"}], "input_from": 1056}, {"input_to": 1139, "text": "In the cut I'm rolling up my broccoli.", "sentence_id": 22, "tone_categories": [{"category_id": "emotion_tone", "tones": [{"tone_name": "Anger", "score": 0.084023, "tone_id": "anger"}, {"tone_name": "Disgust", "score": 0.077306, "tone_id": "disgust"}, {"tone_name": "Fear", "score": 0.026908, "tone_id": "fear"}, {"tone_name": "Joy", "score": 0.616656, "tone_id": "joy"}, {"tone_name": "Sadness", "score": 0.259374, "tone_id": "sadness"}], "category_name": "Emotion Tone"}, {"category_id": "language_tone", "tones": [{"tone_name": "Analytical", "score": 0.0, "tone_id": "analytical"}, {"tone_name": "Confident", "score": 0.0, "tone_id": "confident"}, {"tone_name": "Tentative", "score": 0.0, "tone_id": "tentative"}], "category_name": "Language Tone"}, {"category_id": "social_tone", "tones": [{"tone_name": "Openness", "score": 0.638492, "tone_id": "openness_big5"}, {"tone_name": "Conscientiousness", "score": 0.207405, "tone_id": "conscientiousness_big5"}, {"tone_name": "Extraversion", "score": 0.540573, "tone_id": "extraversion_big5"}, {"tone_name": "Agreeableness", "score": 0.418581, "tone_id": "agreeableness_big5"}, {"tone_name": "Emotional Range", "score": 0.113375, "tone_id": "emotional_range_big5"}], "category_name": "Social Tone"}], "input_from": 1101}, {"input_to": 1176, "text": "Ya I know your baby mama fond of me.", "sentence_id": 23, "tone_categories": [{"category_id": "emotion_tone", "tones": [{"tone_name": "Anger", "score": 0.044709, "tone_id": "anger"}, {"tone_name": "Disgust", "score": 0.070487, "tone_id": "disgust"}, {"tone_name": "Fear", "score": 0.117295, "tone_id": "fear"}, {"tone_name": "Joy", "score": 0.403791, "tone_id": "joy"}, {"tone_name": "Sadness", "score": 0.430529, "tone_id": "sadness"}], "category_name": "Emotion Tone"}, {"category_id": "language_tone", "tones": [{"tone_name": "Analytical", "score": 0.0, "tone_id": "analytical"}, {"tone_name": "Confident", "score": 0.0, "tone_id": "confident"}, {"tone_name": "Tentative", "score": 0.0, "tone_id": "tentative"}], "category_name": "Language Tone"}, {"category_id": "social_tone", "tones": [{"tone_name": "Openness", "score": 0.339253, "tone_id": "openness_big5"}, {"tone_name": "Conscientiousness", "score": 0.426328, "tone_id": "conscientiousness_big5"}, {"tone_name": "Extraversion", "score": 0.839192, "tone_id": "extraversion_big5"}, {"tone_name": "Agreeableness", "score": 0.803751, "tone_id": "agreeableness_big5"}, {"tone_name": "Emotional Range", "score": 0.147785, "tone_id": "emotional_range_big5"}], "category_name": "Social Tone"}], "input_from": 1140}, {"input_to": 1219, "text": "All she want to do is smoke that broccoli.", "sentence_id": 24, "tone_categories": [{"category_id": "emotion_tone", "tones": [{"tone_name": "Anger", "score": 0.078693, "tone_id": "anger"}, {"tone_name": "Disgust", "score": 0.372258, "tone_id": "disgust"}, {"tone_name": "Fear", "score": 0.053632, "tone_id": "fear"}, {"tone_name": "Joy", "score": 0.112671, "tone_id": "joy"}, {"tone_name": "Sadness", "score": 0.451613, "tone_id": "sadness"}], "category_name": "Emotion Tone"}, {"category_id": "language_tone", "tones": [{"tone_name": "Analytical", "score": 0.0, "tone_id": "analytical"}, {"tone_name": "Confident", "score": 0.874372, "tone_id": "confident"}, {"tone_name": "Tentative", "score": 0.0, "tone_id": "tentative"}], "category_name": "Language Tone"}, {"category_id": "social_tone", "tones": [{"tone_name": "Openness", "score": 0.80601, "tone_id": "openness_big5"}, {"tone_name": "Conscientiousness", "score": 0.589297, "tone_id": "conscientiousness_big5"}, {"tone_name": "Extraversion", "score": 0.564062, "tone_id": "extraversion_big5"}, {"tone_name": "Agreeableness", "score": 0.591797, "tone_id": "agreeableness_big5"}, {"tone_name": "Emotional Range", "score": 0.539567, "tone_id": "emotional_range_big5"}], "category_name": "Social Tone"}], "input_from": 1177}, {"input_to": 1268, "text": "Whispered in my ear she trying to leave with me.", "sentence_id": 25, "tone_categories": [{"category_id": "emotion_tone", "tones": [{"tone_name": "Anger", "score": 0.060436, "tone_id": "anger"}, {"tone_name": "Disgust", "score": 0.172675, "tone_id": "disgust"}, {"tone_name": "Fear", "score": 0.248697, "tone_id": "fear"}, {"tone_name": "Joy", "score": 0.023458, "tone_id": "joy"}, {"tone_name": "Sadness", "score": 0.621952, "tone_id": "sadness"}], "category_name": "Emotion Tone"}, {"category_id": "language_tone", "tones": [{"tone_name": "Analytical", "score": 0.0, "tone_id": "analytical"}, {"tone_name": "Confident", "score": 0.0, "tone_id": "confident"}, {"tone_name": "Tentative", "score": 0.497569, "tone_id": "tentative"}], "category_name": "Language Tone"}, {"category_id": "social_tone", "tones": [{"tone_name": "Openness", "score": 0.347976, "tone_id": "openness_big5"}, {"tone_name": "Conscientiousness", "score": 0.226509, "tone_id": "conscientiousness_big5"}, {"tone_name": "Extraversion", "score": 0.810184, "tone_id": "extraversion_big5"}, {"tone_name": "Agreeableness", "score": 0.766563, "tone_id": "agreeableness_big5"}, {"tone_name": "Emotional Range", "score": 0.014736, "tone_id": "emotional_range_big5"}], "category_name": "Social Tone"}], "input_from": 1220}, {"input_to": 1307, "text": "Said that I can get that pussy easily.", "sentence_id": 26, "tone_categories": [{"category_id": "emotion_tone", "tones": [{"tone_name": "Anger", "score": 0.151481, "tone_id": "anger"}, {"tone_name": "Disgust", "score": 0.082909, "tone_id": "disgust"}, {"tone_name": "Fear", "score": 0.191965, "tone_id": "fear"}, {"tone_name": "Joy", "score": 0.068459, "tone_id": "joy"}, {"tone_name": "Sadness", "score": 0.60175, "tone_id": "sadness"}], "category_name": "Emotion Tone"}, {"category_id": "language_tone", "tones": [{"tone_name": "Analytical", "score": 0.0, "tone_id": "analytical"}, {"tone_name": "Confident", "score": 0.0, "tone_id": "confident"}, {"tone_name": "Tentative", "score": 0.0, "tone_id": "tentative"}], "category_name": "Language Tone"}, {"category_id": "social_tone", "tones": [{"tone_name": "Openness", "score": 0.659527, "tone_id": "openness_big5"}, {"tone_name": "Conscientiousness", "score": 0.643288, "tone_id": "conscientiousness_big5"}, {"tone_name": "Extraversion", "score": 0.110692, "tone_id": "extraversion_big5"}, {"tone_name": "Agreeableness", "score": 0.804676, "tone_id": "agreeableness_big5"}, {"tone_name": "Emotional Range", "score": 0.768164, "tone_id": "emotional_range_big5"}], "category_name": "Social Tone"}], "input_from": 1269}, {"input_to": 1350, "text": "Said that I can hit that shit so greasily.", "sentence_id": 27, "tone_categories": [{"category_id": "emotion_tone", "tones": [{"tone_name": "Anger", "score": 0.112637, "tone_id": "anger"}, {"tone_name": "Disgust", "score": 0.162601, "tone_id": "disgust"}, {"tone_name": "Fear", "score": 0.045653, "tone_id": "fear"}, {"tone_name": "Joy", "score": 0.303001, "tone_id": "joy"}, {"tone_name": "Sadness", "score": 0.459255, "tone_id": "sadness"}], "category_name": "Emotion Tone"}, {"category_id": "language_tone", "tones": [{"tone_name": "Analytical", "score": 0.0, "tone_id": "analytical"}, {"tone_name": "Confident", "score": 0.0, "tone_id": "confident"}, {"tone_name": "Tentative", "score": 0.0, "tone_id": "tentative"}], "category_name": "Language Tone"}, {"category_id": "social_tone", "tones": [{"tone_name": "Openness", "score": 0.652336, "tone_id": "openness_big5"}, {"tone_name": "Conscientiousness", "score": 0.566966, "tone_id": "conscientiousness_big5"}, {"tone_name": "Extraversion", "score": 0.075422, "tone_id": "extraversion_big5"}, {"tone_name": "Agreeableness", "score": 0.704367, "tone_id": "agreeableness_big5"}, {"tone_name": "Emotional Range", "score": 0.736733, "tone_id": "emotional_range_big5"}], "category_name": "Social Tone"}], "input_from": 1308}, {"input_to": 1385, "text": "I'm a dirty dog I did it sleazily.", "sentence_id": 28, "tone_categories": [{"category_id": "emotion_tone", "tones": [{"tone_name": "Anger", "score": 0.064668, "tone_id": "anger"}, {"tone_name": "Disgust", "score": 0.869805, "tone_id": "disgust"}, {"tone_name": "Fear", "score": 0.038333, "tone_id": "fear"}, {"tone_name": "Joy", "score": 0.063066, "tone_id": "joy"}, {"tone_name": "Sadness", "score": 0.025545, "tone_id": "sadness"}], "category_name": "Emotion Tone"}, {"category_id": "language_tone", "tones": [{"tone_name": "Analytical", "score": 0.0, "tone_id": "analytical"}, {"tone_name": "Confident", "score": 0.0, "tone_id": "confident"}, {"tone_name": "Tentative", "score": 0.0, "tone_id": "tentative"}], "category_name": "Language Tone"}, {"category_id": "social_tone", "tones": [{"tone_name": "Openness", "score": 0.307799, "tone_id": "openness_big5"}, {"tone_name": "Conscientiousness", "score": 0.001663, "tone_id": "conscientiousness_big5"}, {"tone_name": "Extraversion", "score": 0.017888, "tone_id": "extraversion_big5"}, {"tone_name": "Agreeableness", "score": 0.215365, "tone_id": "agreeableness_big5"}, {"tone_name": "Emotional Range", "score": 0.093894, "tone_id": "emotional_range_big5"}], "category_name": "Social Tone"}], "input_from": 1351}, {"input_to": 1424, "text": "Ain't no telling what I'm finna be on.", "sentence_id": 29, "tone_categories": [{"category_id": "emotion_tone", "tones": [{"tone_name": "Anger", "score": 0.335818, "tone_id": "anger"}, {"tone_name": "Disgust", "score": 0.046236, "tone_id": "disgust"}, {"tone_name": "Fear", "score": 0.07308, "tone_id": "fear"}, {"tone_name": "Joy", "score": 0.199678, "tone_id": "joy"}, {"tone_name": "Sadness", "score": 0.432339, "tone_id": "sadness"}], "category_name": "Emotion Tone"}, {"category_id": "language_tone", "tones": [{"tone_name": "Analytical", "score": 0.0, "tone_id": "analytical"}, {"tone_name": "Confident", "score": 0.0, "tone_id": "confident"}, {"tone_name": "Tentative", "score": 0.0, "tone_id": "tentative"}], "category_name": "Language Tone"}, {"category_id": "social_tone", "tones": [{"tone_name": "Openness", "score": 0.264562, "tone_id": "openness_big5"}, {"tone_name": "Conscientiousness", "score": 0.384154, "tone_id": "conscientiousness_big5"}, {"tone_name": "Extraversion", "score": 0.440042, "tone_id": "extraversion_big5"}, {"tone_name": "Agreeableness", "score": 0.415722, "tone_id": "agreeableness_big5"}, {"tone_name": "Emotional Range", "score": 0.32161, "tone_id": "emotional_range_big5"}], "category_name": "Social Tone"}], "input_from": 1386}, {"input_to": 1455, "text": "I'm beyond all that fuck shit.", "sentence_id": 30, "tone_categories": [{"category_id": "emotion_tone", "tones": [{"tone_name": "Anger", "score": 0.431579, "tone_id": "anger"}, {"tone_name": "Disgust", "score": 0.354997, "tone_id": "disgust"}, {"tone_name": "Fear", "score": 0.132085, "tone_id": "fear"}, {"tone_name": "Joy", "score": 0.040611, "tone_id": "joy"}, {"tone_name": "Sadness", "score": 0.110384, "tone_id": "sadness"}], "category_name": "Emotion Tone"}, {"category_id": "language_tone", "tones": [{"tone_name": "Analytical", "score": 0.0, "tone_id": "analytical"}, {"tone_name": "Confident", "score": 0.942582, "tone_id": "confident"}, {"tone_name": "Tentative", "score": 0.0, "tone_id": "tentative"}], "category_name": "Language Tone"}, {"category_id": "social_tone", "tones": [{"tone_name": "Openness", "score": 0.617437, "tone_id": "openness_big5"}, {"tone_name": "Conscientiousness", "score": 0.342315, "tone_id": "conscientiousness_big5"}, {"tone_name": "Extraversion", "score": 0.408939, "tone_id": "extraversion_big5"}, {"tone_name": "Agreeableness", "score": 0.336641, "tone_id": "agreeableness_big5"}, {"tone_name": "Emotional Range", "score": 0.022584, "tone_id": "emotional_range_big5"}], "category_name": "Social Tone"}], "input_from": 1425}, {"input_to": 1494, "text": "Ain't no telling what I'm finna be on.", "sentence_id": 31, "tone_categories": [{"category_id": "emotion_tone", "tones": [{"tone_name": "Anger", "score": 0.335818, "tone_id": "anger"}, {"tone_name": "Disgust", "score": 0.046236, "tone_id": "disgust"}, {"tone_name": "Fear", "score": 0.07308, "tone_id": "fear"}, {"tone_name": "Joy", "score": 0.199678, "tone_id": "joy"}, {"tone_name": "Sadness", "score": 0.432339, "tone_id": "sadness"}], "category_name": "Emotion Tone"}, {"category_id": "language_tone", "tones": [{"tone_name": "Analytical", "score": 0.0, "tone_id": "analytical"}, {"tone_name": "Confident", "score": 0.0, "tone_id": "confident"}, {"tone_name": "Tentative", "score": 0.0, "tone_id": "tentative"}], "category_name": "Language Tone"}, {"category_id": "social_tone", "tones": [{"tone_name": "Openness", "score": 0.264562, "tone_id": "openness_big5"}, {"tone_name": "Conscientiousness", "score": 0.384154, "tone_id": "conscientiousness_big5"}, {"tone_name": "Extraversion", "score": 0.440042, "tone_id": "extraversion_big5"}, {"tone_name": "Agreeableness", "score": 0.415722, "tone_id": "agreeableness_big5"}, {"tone_name": "Emotional Range", "score": 0.32161, "tone_id": "emotional_range_big5"}], "category_name": "Social Tone"}], "input_from": 1456}, {"input_to": 1525, "text": "I'm beyond all that fuck shit.", "sentence_id": 32, "tone_categories": [{"category_id": "emotion_tone", "tones": [{"tone_name": "Anger", "score": 0.431579, "tone_id": "anger"}, {"tone_name": "Disgust", "score": 0.354997, "tone_id": "disgust"}, {"tone_name": "Fear", "score": 0.132085, "tone_id": "fear"}, {"tone_name": "Joy", "score": 0.040611, "tone_id": "joy"}, {"tone_name": "Sadness", "score": 0.110384, "tone_id": "sadness"}], "category_name": "Emotion Tone"}, {"category_id": "language_tone", "tones": [{"tone_name": "Analytical", "score": 0.0, "tone_id": "analytical"}, {"tone_name": "Confident", "score": 0.942582, "tone_id": "confident"}, {"tone_name": "Tentative", "score": 0.0, "tone_id": "tentative"}], "category_name": "Language Tone"}, {"category_id": "social_tone", "tones": [{"tone_name": "Openness", "score": 0.617437, "tone_id": "openness_big5"}, {"tone_name": "Conscientiousness", "score": 0.342315, "tone_id": "conscientiousness_big5"}, {"tone_name": "Extraversion", "score": 0.408939, "tone_id": "extraversion_big5"}, {"tone_name": "Agreeableness", "score": 0.336641, "tone_id": "agreeableness_big5"}, {"tone_name": "Emotional Range", "score": 0.022584, "tone_id": "emotional_range_big5"}], "category_name": "Social Tone"}], "input_from": 1495}, {"input_to": 1552, "text": "I got companies and Pesos.", "sentence_id": 33, "tone_categories": [{"category_id": "emotion_tone", "tones": [{"tone_name": "Anger", "score": 0.080253, "tone_id": "anger"}, {"tone_name": "Disgust", "score": 0.100827, "tone_id": "disgust"}, {"tone_name": "Fear", "score": 0.055994, "tone_id": "fear"}, {"tone_name": "Joy", "score": 0.61493, "tone_id": "joy"}, {"tone_name": "Sadness", "score": 0.220873, "tone_id": "sadness"}], "category_name": "Emotion Tone"}, {"category_id": "language_tone", "tones": [{"tone_name": "Analytical", "score": 0.0, "tone_id": "analytical"}, {"tone_name": "Confident", "score": 0.0, "tone_id": "confident"}, {"tone_name": "Tentative", "score": 0.0, "tone_id": "tentative"}], "category_name": "Language Tone"}, {"category_id": "social_tone", "tones": [{"tone_name": "Openness", "score": 0.180814, "tone_id": "openness_big5"}, {"tone_name": "Conscientiousness", "score": 0.304708, "tone_id": "conscientiousness_big5"}, {"tone_name": "Extraversion", "score": 0.612432, "tone_id": "extraversion_big5"}, {"tone_name": "Agreeableness", "score": 0.558244, "tone_id": "agreeableness_big5"}, {"tone_name": "Emotional Range", "score": 0.39179, "tone_id": "emotional_range_big5"}], "category_name": "Social Tone"}], "input_from": 1526}, {"input_to": 1580, "text": "I got people on my payroll.", "sentence_id": 34, "tone_categories": [{"category_id": "emotion_tone", "tones": [{"tone_name": "Anger", "score": 0.161863, "tone_id": "anger"}, {"tone_name": "Disgust", "score": 0.04436, "tone_id": "disgust"}, {"tone_name": "Fear", "score": 0.063667, "tone_id": "fear"}, {"tone_name": "Joy", "score": 0.186337, "tone_id": "joy"}, {"tone_name": "Sadness", "score": 0.614841, "tone_id": "sadness"}], "category_name": "Emotion Tone"}, {"category_id": "language_tone", "tones": [{"tone_name": "Analytical", "score": 0.0, "tone_id": "analytical"}, {"tone_name": "Confident", "score": 0.0, "tone_id": "confident"}, {"tone_name": "Tentative", "score": 0.0, "tone_id": "tentative"}], "category_name": "Language Tone"}, {"category_id": "social_tone", "tones": [{"tone_name": "Openness", "score": 0.078535, "tone_id": "openness_big5"}, {"tone_name": "Conscientiousness", "score": 0.374597, "tone_id": "conscientiousness_big5"}, {"tone_name": "Extraversion", "score": 0.663561, "tone_id": "extraversion_big5"}, {"tone_name": "Agreeableness", "score": 0.247398, "tone_id": "agreeableness_big5"}, {"tone_name": "Emotional Range", "score": 0.402799, "tone_id": "emotional_range_big5"}], "category_name": "Social Tone"}], "input_from": 1553}, {"input_to": 1611, "text": "She don't do it less I say so.", "sentence_id": 35, "tone_categories": [{"category_id": "emotion_tone", "tones": [{"tone_name": "Anger", "score": 0.116289, "tone_id": "anger"}, {"tone_name": "Disgust", "score": 0.106227, "tone_id": "disgust"}, {"tone_name": "Fear", "score": 0.255763, "tone_id": "fear"}, {"tone_name": "Joy", "score": 0.128637, "tone_id": "joy"}, {"tone_name": "Sadness", "score": 0.499605, "tone_id": "sadness"}], "category_name": "Emotion Tone"}, {"category_id": "language_tone", "tones": [{"tone_name": "Analytical", "score": 0.0, "tone_id": "analytical"}, {"tone_name": "Confident", "score": 0.0, "tone_id": "confident"}, {"tone_name": "Tentative", "score": 0.0, "tone_id": "tentative"}], "category_name": "Language Tone"}, {"category_id": "social_tone", "tones": [{"tone_name": "Openness", "score": 0.033451, "tone_id": "openness_big5"}, {"tone_name": "Conscientiousness", "score": 0.292486, "tone_id": "conscientiousness_big5"}, {"tone_name": "Extraversion", "score": 0.047099, "tone_id": "extraversion_big5"}, {"tone_name": "Agreeableness", "score": 0.587954, "tone_id": "agreeableness_big5"}, {"tone_name": "Emotional Range", "score": 0.106696, "tone_id": "emotional_range_big5"}], "category_name": "Social Tone"}], "input_from": 1581}, {"input_to": 1644, "text": "I don't smoke if it ain't fuego.", "sentence_id": 36, "tone_categories": [{"category_id": "emotion_tone", "tones": [{"tone_name": "Anger", "score": 0.075968, "tone_id": "anger"}, {"tone_name": "Disgust", "score": 0.462563, "tone_id": "disgust"}, {"tone_name": "Fear", "score": 0.105911, "tone_id": "fear"}, {"tone_name": "Joy", "score": 0.125544, "tone_id": "joy"}, {"tone_name": "Sadness", "score": 0.318595, "tone_id": "sadness"}], "category_name": "Emotion Tone"}, {"category_id": "language_tone", "tones": [{"tone_name": "Analytical", "score": 0.801827, "tone_id": "analytical"}, {"tone_name": "Confident", "score": 0.0, "tone_id": "confident"}, {"tone_name": "Tentative", "score": 0.0, "tone_id": "tentative"}], "category_name": "Language Tone"}, {"category_id": "social_tone", "tones": [{"tone_name": "Openness", "score": 0.584377, "tone_id": "openness_big5"}, {"tone_name": "Conscientiousness", "score": 0.344952, "tone_id": "conscientiousness_big5"}, {"tone_name": "Extraversion", "score": 0.286132, "tone_id": "extraversion_big5"}, {"tone_name": "Agreeableness", "score": 0.412922, "tone_id": "agreeableness_big5"}, {"tone_name": "Emotional Range", "score": 0.47243, "tone_id": "emotional_range_big5"}], "category_name": "Social Tone"}], "input_from": 1612}, {"input_to": 1675, "text": "I just sauce em up like Prego.", "sentence_id": 37, "tone_categories": [{"category_id": "emotion_tone", "tones": [{"tone_name": "Anger", "score": 0.217381, "tone_id": "anger"}, {"tone_name": "Disgust", "score": 0.089231, "tone_id": "disgust"}, {"tone_name": "Fear", "score": 0.074745, "tone_id": "fear"}, {"tone_name": "Joy", "score": 0.145821, "tone_id": "joy"}, {"tone_name": "Sadness", "score": 0.546321, "tone_id": "sadness"}], "category_name": "Emotion Tone"}, {"category_id": "language_tone", "tones": [{"tone_name": "Analytical", "score": 0.0, "tone_id": "analytical"}, {"tone_name": "Confident", "score": 0.0, "tone_id": "confident"}, {"tone_name": "Tentative", "score": 0.974201, "tone_id": "tentative"}], "category_name": "Language Tone"}, {"category_id": "social_tone", "tones": [{"tone_name": "Openness", "score": 0.406952, "tone_id": "openness_big5"}, {"tone_name": "Conscientiousness", "score": 0.306721, "tone_id": "conscientiousness_big5"}, {"tone_name": "Extraversion", "score": 0.662497, "tone_id": "extraversion_big5"}, {"tone_name": "Agreeableness", "score": 0.602688, "tone_id": "agreeableness_big5"}, {"tone_name": "Emotional Range", "score": 0.280983, "tone_id": "emotional_range_big5"}], "category_name": "Social Tone"}], "input_from": 1645}, {"input_to": 1700, "text": "Fettuchini with Alfredo.", "sentence_id": 38, "tone_categories": [], "input_from": 1676}, {"input_to": 1760, "text": "All I wanted was the fame and every game they made on Sega.", "sentence_id": 39, "tone_categories": [{"category_id": "emotion_tone", "tones": [{"tone_name": "Anger", "score": 0.214348, "tone_id": "anger"}, {"tone_name": "Disgust", "score": 0.14976, "tone_id": "disgust"}, {"tone_name": "Fear", "score": 0.079976, "tone_id": "fear"}, {"tone_name": "Joy", "score": 0.111816, "tone_id": "joy"}, {"tone_name": "Sadness", "score": 0.515176, "tone_id": "sadness"}], "category_name": "Emotion Tone"}, {"category_id": "language_tone", "tones": [{"tone_name": "Analytical", "score": 0.0, "tone_id": "analytical"}, {"tone_name": "Confident", "score": 0.932155, "tone_id": "confident"}, {"tone_name": "Tentative", "score": 0.0, "tone_id": "tentative"}], "category_name": "Language Tone"}, {"category_id": "social_tone", "tones": [{"tone_name": "Openness", "score": 0.853103, "tone_id": "openness_big5"}, {"tone_name": "Conscientiousness", "score": 0.48315, "tone_id": "conscientiousness_big5"}, {"tone_name": "Extraversion", "score": 0.307223, "tone_id": "extraversion_big5"}, {"tone_name": "Agreeableness", "score": 0.121744, "tone_id": "agreeableness_big5"}, {"tone_name": "Emotional Range", "score": 0.948404, "tone_id": "emotional_range_big5"}], "category_name": "Social Tone"}], "input_from": 1701}, {"input_to": 1825, "text": "I was 5 or 6 years old when I had told myself ok you're special.", "sentence_id": 40, "tone_categories": [{"category_id": "emotion_tone", "tones": [{"tone_name": "Anger", "score": 0.060087, "tone_id": "anger"}, {"tone_name": "Disgust", "score": 0.179146, "tone_id": "disgust"}, {"tone_name": "Fear", "score": 0.131886, "tone_id": "fear"}, {"tone_name": "Joy", "score": 0.318315, "tone_id": "joy"}, {"tone_name": "Sadness", "score": 0.405284, "tone_id": "sadness"}], "category_name": "Emotion Tone"}, {"category_id": "language_tone", "tones": [{"tone_name": "Analytical", "score": 0.0, "tone_id": "analytical"}, {"tone_name": "Confident", "score": 0.0, "tone_id": "confident"}, {"tone_name": "Tentative", "score": 0.647986, "tone_id": "tentative"}], "category_name": "Language Tone"}, {"category_id": "social_tone", "tones": [{"tone_name": "Openness", "score": 0.140361, "tone_id": "openness_big5"}, {"tone_name": "Conscientiousness", "score": 0.005711, "tone_id": "conscientiousness_big5"}, {"tone_name": "Extraversion", "score": 0.159713, "tone_id": "extraversion_big5"}, {"tone_name": "Agreeableness", "score": 0.933935, "tone_id": "agreeableness_big5"}, {"tone_name": "Emotional Range", "score": 0.188979, "tone_id": "emotional_range_big5"}], "category_name": "Social Tone"}], "input_from": 1761}, {"input_to": 1869, "text": "But I treat you like my equal never lesser.", "sentence_id": 41, "tone_categories": [{"category_id": "emotion_tone", "tones": [{"tone_name": "Anger", "score": 0.230131, "tone_id": "anger"}, {"tone_name": "Disgust", "score": 0.043384, "tone_id": "disgust"}, {"tone_name": "Fear", "score": 0.122071, "tone_id": "fear"}, {"tone_name": "Joy", "score": 0.228295, "tone_id": "joy"}, {"tone_name": "Sadness", "score": 0.456611, "tone_id": "sadness"}], "category_name": "Emotion Tone"}, {"category_id": "language_tone", "tones": [{"tone_name": "Analytical", "score": 0.0, "tone_id": "analytical"}, {"tone_name": "Confident", "score": 0.0, "tone_id": "confident"}, {"tone_name": "Tentative", "score": 0.0, "tone_id": "tentative"}], "category_name": "Language Tone"}, {"category_id": "social_tone", "tones": [{"tone_name": "Openness", "score": 0.692572, "tone_id": "openness_big5"}, {"tone_name": "Conscientiousness", "score": 0.42987, "tone_id": "conscientiousness_big5"}, {"tone_name": "Extraversion", "score": 0.152977, "tone_id": "extraversion_big5"}, {"tone_name": "Agreeableness", "score": 0.565035, "tone_id": "agreeableness_big5"}, {"tone_name": "Emotional Range", "score": 0.272182, "tone_id": "emotional_range_big5"}], "category_name": "Social Tone"}], "input_from": 1826}, {"input_to": 1933, "text": "I was 26 years old when we had dropped this one amazing record.", "sentence_id": 42, "tone_categories": [{"category_id": "emotion_tone", "tones": [{"tone_name": "Anger", "score": 0.035291, "tone_id": "anger"}, {"tone_name": "Disgust", "score": 0.101527, "tone_id": "disgust"}, {"tone_name": "Fear", "score": 0.102327, "tone_id": "fear"}, {"tone_name": "Joy", "score": 0.714977, "tone_id": "joy"}, {"tone_name": "Sadness", "score": 0.106273, "tone_id": "sadness"}], "category_name": "Emotion Tone"}, {"category_id": "language_tone", "tones": [{"tone_name": "Analytical", "score": 0.0, "tone_id": "analytical"}, {"tone_name": "Confident", "score": 0.0, "tone_id": "confident"}, {"tone_name": "Tentative", "score": 0.0, "tone_id": "tentative"}], "category_name": "Language Tone"}, {"category_id": "social_tone", "tones": [{"tone_name": "Openness", "score": 0.041574, "tone_id": "openness_big5"}, {"tone_name": "Conscientiousness", "score": 0.230124, "tone_id": "conscientiousness_big5"}, {"tone_name": "Extraversion", "score": 0.22947, "tone_id": "extraversion_big5"}, {"tone_name": "Agreeableness", "score": 0.553856, "tone_id": "agreeableness_big5"}, {"tone_name": "Emotional Range", "score": 0.478727, "tone_id": "emotional_range_big5"}], "category_name": "Social Tone"}], "input_from": 1870}, {"input_to": 1957, "text": "Had the world stepping.", "sentence_id": 43, "tone_categories": [{"category_id": "emotion_tone", "tones": [{"tone_name": "Anger", "score": 0.043924, "tone_id": "anger"}, {"tone_name": "Disgust", "score": 0.061871, "tone_id": "disgust"}, {"tone_name": "Fear", "score": 0.112402, "tone_id": "fear"}, {"tone_name": "Joy", "score": 0.421682, "tone_id": "joy"}, {"tone_name": "Sadness", "score": 0.409911, "tone_id": "sadness"}], "category_name": "Emotion Tone"}, {"category_id": "language_tone", "tones": [{"tone_name": "Analytical", "score": 0.0, "tone_id": "analytical"}, {"tone_name": "Confident", "score": 0.0, "tone_id": "confident"}, {"tone_name": "Tentative", "score": 0.0, "tone_id": "tentative"}], "category_name": "Language Tone"}, {"category_id": "social_tone", "tones": [{"tone_name": "Openness", "score": 0.445621, "tone_id": "openness_big5"}, {"tone_name": "Conscientiousness", "score": 0.279604, "tone_id": "conscientiousness_big5"}, {"tone_name": "Extraversion", "score": 0.483114, "tone_id": "extraversion_big5"}, {"tone_name": "Agreeableness", "score": 0.545248, "tone_id": "agreeableness_big5"}, {"tone_name": "Emotional Range", "score": 0.522767, "tone_id": "emotional_range_big5"}], "category_name": "Social Tone"}], "input_from": 1934}, {"input_to": 1982, "text": "That's what I call epic.", "sentence_id": 44, "tone_categories": [{"category_id": "emotion_tone", "tones": [{"tone_name": "Anger", "score": 0.135703, "tone_id": "anger"}, {"tone_name": "Disgust", "score": 0.126066, "tone_id": "disgust"}, {"tone_name": "Fear", "score": 0.119195, "tone_id": "fear"}, {"tone_name": "Joy", "score": 0.214374, "tone_id": "joy"}, {"tone_name": "Sadness", "score": 0.530414, "tone_id": "sadness"}], "category_name": "Emotion Tone"}, {"category_id": "language_tone", "tones": [{"tone_name": "Analytical", "score": 0.0, "tone_id": "analytical"}, {"tone_name": "Confident", "score": 0.0, "tone_id": "confident"}, {"tone_name": "Tentative", "score": 0.0, "tone_id": "tentative"}], "category_name": "Language Tone"}, {"category_id": "social_tone", "tones": [{"tone_name": "Openness", "score": 0.699069, "tone_id": "openness_big5"}, {"tone_name": "Conscientiousness", "score": 0.335398, "tone_id": "conscientiousness_big5"}, {"tone_name": "Extraversion", "score": 0.470448, "tone_id": "extraversion_big5"}, {"tone_name": "Agreeableness", "score": 0.666444, "tone_id": "agreeableness_big5"}, {"tone_name": "Emotional Range", "score": 0.825088, "tone_id": "emotional_range_big5"}], "category_name": "Social Tone"}], "input_from": 1958}, {"input_to": 2016, "text": "Couple summers later I got paper.", "sentence_id": 45, "tone_categories": [{"category_id": "emotion_tone", "tones": [{"tone_name": "Anger", "score": 0.091229, "tone_id": "anger"}, {"tone_name": "Disgust", "score": 0.024943, "tone_id": "disgust"}, {"tone_name": "Fear", "score": 0.006565, "tone_id": "fear"}, {"tone_name": "Joy", "score": 0.718526, "tone_id": "joy"}, {"tone_name": "Sadness", "score": 0.218142, "tone_id": "sadness"}], "category_name": "Emotion Tone"}, {"category_id": "language_tone", "tones": [{"tone_name": "Analytical", "score": 0.0, "tone_id": "analytical"}, {"tone_name": "Confident", "score": 0.0, "tone_id": "confident"}, {"tone_name": "Tentative", "score": 0.0, "tone_id": "tentative"}], "category_name": "Language Tone"}, {"category_id": "social_tone", "tones": [{"tone_name": "Openness", "score": 0.107993, "tone_id": "openness_big5"}, {"tone_name": "Conscientiousness", "score": 0.420171, "tone_id": "conscientiousness_big5"}, {"tone_name": "Extraversion", "score": 0.301035, "tone_id": "extraversion_big5"}, {"tone_name": "Agreeableness", "score": 0.536146, "tone_id": "agreeableness_big5"}, {"tone_name": "Emotional Range", "score": 0.155448, "tone_id": "emotional_range_big5"}], "category_name": "Social Tone"}], "input_from": 1983}, {"input_to": 2056, "text": "I acquired taste for salmon on a bagel.", "sentence_id": 46, "tone_categories": [{"category_id": "emotion_tone", "tones": [{"tone_name": "Anger", "score": 0.081826, "tone_id": "anger"}, {"tone_name": "Disgust", "score": 0.380237, "tone_id": "disgust"}, {"tone_name": "Fear", "score": 0.070072, "tone_id": "fear"}, {"tone_name": "Joy", "score": 0.355477, "tone_id": "joy"}, {"tone_name": "Sadness", "score": 0.198486, "tone_id": "sadness"}], "category_name": "Emotion Tone"}, {"category_id": "language_tone", "tones": [{"tone_name": "Analytical", "score": 0.0, "tone_id": "analytical"}, {"tone_name": "Confident", "score": 0.0, "tone_id": "confident"}, {"tone_name": "Tentative", "score": 0.0, "tone_id": "tentative"}], "category_name": "Language Tone"}, {"category_id": "social_tone", "tones": [{"tone_name": "Openness", "score": 0.758051, "tone_id": "openness_big5"}, {"tone_name": "Conscientiousness", "score": 0.365844, "tone_id": "conscientiousness_big5"}, {"tone_name": "Extraversion", "score": 0.541915, "tone_id": "extraversion_big5"}, {"tone_name": "Agreeableness", "score": 0.443325, "tone_id": "agreeableness_big5"}, {"tone_name": "Emotional Range", "score": 0.604033, "tone_id": "emotional_range_big5"}], "category_name": "Social Tone"}], "input_from": 2017}, {"input_to": 2091, "text": "With the capers on a square plate.", "sentence_id": 47, "tone_categories": [{"category_id": "emotion_tone", "tones": [{"tone_name": "Anger", "score": 0.268681, "tone_id": "anger"}, {"tone_name": "Disgust", "score": 0.243632, "tone_id": "disgust"}, {"tone_name": "Fear", "score": 0.058196, "tone_id": "fear"}, {"tone_name": "Joy", "score": 0.440436, "tone_id": "joy"}, {"tone_name": "Sadness", "score": 0.081403, "tone_id": "sadness"}], "category_name": "Emotion Tone"}, {"category_id": "language_tone", "tones": [{"tone_name": "Analytical", "score": 0.0, "tone_id": "analytical"}, {"tone_name": "Confident", "score": 0.0, "tone_id": "confident"}, {"tone_name": "Tentative", "score": 0.0, "tone_id": "tentative"}], "category_name": "Language Tone"}, {"category_id": "social_tone", "tones": [{"tone_name": "Openness", "score": 0.716953, "tone_id": "openness_big5"}, {"tone_name": "Conscientiousness", "score": 0.353807, "tone_id": "conscientiousness_big5"}, {"tone_name": "Extraversion", "score": 0.789261, "tone_id": "extraversion_big5"}, {"tone_name": "Agreeableness", "score": 0.364868, "tone_id": "agreeableness_big5"}, {"tone_name": "Emotional Range", "score": 0.8102, "tone_id": "emotional_range_big5"}], "category_name": "Social Tone"}], "input_from": 2057}, {"input_to": 2145, "text": "At the restaurant with the why you got to stare face.", "sentence_id": 48, "tone_categories": [{"category_id": "emotion_tone", "tones": [{"tone_name": "Anger", "score": 0.155363, "tone_id": "anger"}, {"tone_name": "Disgust", "score": 0.144221, "tone_id": "disgust"}, {"tone_name": "Fear", "score": 0.314549, "tone_id": "fear"}, {"tone_name": "Joy", "score": 0.217428, "tone_id": "joy"}, {"tone_name": "Sadness", "score": 0.232364, "tone_id": "sadness"}], "category_name": "Emotion Tone"}, {"category_id": "language_tone", "tones": [{"tone_name": "Analytical", "score": 0.0, "tone_id": "analytical"}, {"tone_name": "Confident", "score": 0.0, "tone_id": "confident"}, {"tone_name": "Tentative", "score": 0.0, "tone_id": "tentative"}], "category_name": "Language Tone"}, {"category_id": "social_tone", "tones": [{"tone_name": "Openness", "score": 0.251228, "tone_id": "openness_big5"}, {"tone_name": "Conscientiousness", "score": 0.56466, "tone_id": "conscientiousness_big5"}, {"tone_name": "Extraversion", "score": 0.970536, "tone_id": "extraversion_big5"}, {"tone_name": "Agreeableness", "score": 0.665968, "tone_id": "agreeableness_big5"}, {"tone_name": "Emotional Range", "score": 0.841203, "tone_id": "emotional_range_big5"}], "category_name": "Social Tone"}], "input_from": 2092}, {"input_to": 2204, "text": "To know I either ball or I record over the snare and bass.", "sentence_id": 49, "tone_categories": [{"category_id": "emotion_tone", "tones": [{"tone_name": "Anger", "score": 0.45727, "tone_id": "anger"}, {"tone_name": "Disgust", "score": 0.079975, "tone_id": "disgust"}, {"tone_name": "Fear", "score": 0.208476, "tone_id": "fear"}, {"tone_name": "Joy", "score": 0.133768, "tone_id": "joy"}, {"tone_name": "Sadness", "score": 0.194986, "tone_id": "sadness"}], "category_name": "Emotion Tone"}, {"category_id": "language_tone", "tones": [{"tone_name": "Analytical", "score": 0.821913, "tone_id": "analytical"}, {"tone_name": "Confident", "score": 0.0, "tone_id": "confident"}, {"tone_name": "Tentative", "score": 0.716301, "tone_id": "tentative"}], "category_name": "Language Tone"}, {"category_id": "social_tone", "tones": [{"tone_name": "Openness", "score": 0.828986, "tone_id": "openness_big5"}, {"tone_name": "Conscientiousness", "score": 0.034377, "tone_id": "conscientiousness_big5"}, {"tone_name": "Extraversion", "score": 0.585871, "tone_id": "extraversion_big5"}, {"tone_name": "Agreeableness", "score": 0.070133, "tone_id": "agreeableness_big5"}, {"tone_name": "Emotional Range", "score": 0.700001, "tone_id": "emotional_range_big5"}], "category_name": "Social Tone"}], "input_from": 2146}, {"input_to": 2231, "text": "Rapper face, dread headed.", "sentence_id": 50, "tone_categories": [{"category_id": "emotion_tone", "tones": [{"tone_name": "Anger", "score": 0.047218, "tone_id": "anger"}, {"tone_name": "Disgust", "score": 0.057615, "tone_id": "disgust"}, {"tone_name": "Fear", "score": 0.754128, "tone_id": "fear"}, {"tone_name": "Joy", "score": 0.020596, "tone_id": "joy"}, {"tone_name": "Sadness", "score": 0.181634, "tone_id": "sadness"}], "category_name": "Emotion Tone"}, {"category_id": "language_tone", "tones": [{"tone_name": "Analytical", "score": 0.0, "tone_id": "analytical"}, {"tone_name": "Confident", "score": 0.0, "tone_id": "confident"}, {"tone_name": "Tentative", "score": 0.0, "tone_id": "tentative"}], "category_name": "Language Tone"}, {"category_id": "social_tone", "tones": [{"tone_name": "Openness", "score": 0.605501, "tone_id": "openness_big5"}, {"tone_name": "Conscientiousness", "score": 0.265536, "tone_id": "conscientiousness_big5"}, {"tone_name": "Extraversion", "score": 0.562708, "tone_id": "extraversion_big5"}, {"tone_name": "Agreeableness", "score": 0.592659, "tone_id": "agreeableness_big5"}, {"tone_name": "Emotional Range", "score": 0.290781, "tone_id": "emotional_range_big5"}], "category_name": "Social Tone"}], "input_from": 2205}, {"input_to": 2261, "text": "Golden diamond teeth wearing.", "sentence_id": 51, "tone_categories": [{"category_id": "emotion_tone", "tones": [{"tone_name": "Anger", "score": 0.0386, "tone_id": "anger"}, {"tone_name": "Disgust", "score": 0.312523, "tone_id": "disgust"}, {"tone_name": "Fear", "score": 0.032973, "tone_id": "fear"}, {"tone_name": "Joy", "score": 0.669398, "tone_id": "joy"}, {"tone_name": "Sadness", "score": 0.031319, "tone_id": "sadness"}], "category_name": "Emotion Tone"}, {"category_id": "language_tone", "tones": [{"tone_name": "Analytical", "score": 0.0, "tone_id": "analytical"}, {"tone_name": "Confident", "score": 0.0, "tone_id": "confident"}, {"tone_name": "Tentative", "score": 0.0, "tone_id": "tentative"}], "category_name": "Language Tone"}, {"category_id": "social_tone", "tones": [{"tone_name": "Openness", "score": 0.446912, "tone_id": "openness_big5"}, {"tone_name": "Conscientiousness", "score": 0.273998, "tone_id": "conscientiousness_big5"}, {"tone_name": "Extraversion", "score": 0.549942, "tone_id": "extraversion_big5"}, {"tone_name": "Agreeableness", "score": 0.601055, "tone_id": "agreeableness_big5"}, {"tone_name": "Emotional Range", "score": 0.313736, "tone_id": "emotional_range_big5"}], "category_name": "Social Tone"}], "input_from": 2232}, {"input_to": 2319, "text": "They just mad cause I got that cheese bitch I keep dairy.", "sentence_id": 52, "tone_categories": [{"category_id": "emotion_tone", "tones": [{"tone_name": "Anger", "score": 0.315988, "tone_id": "anger"}, {"tone_name": "Disgust", "score": 0.020227, "tone_id": "disgust"}, {"tone_name": "Fear", "score": 0.008938, "tone_id": "fear"}, {"tone_name": "Joy", "score": 0.015078, "tone_id": "joy"}, {"tone_name": "Sadness", "score": 0.726326, "tone_id": "sadness"}], "category_name": "Emotion Tone"}, {"category_id": "language_tone", "tones": [{"tone_name": "Analytical", "score": 0.0, "tone_id": "analytical"}, {"tone_name": "Confident", "score": 0.0, "tone_id": "confident"}, {"tone_name": "Tentative", "score": 0.75152, "tone_id": "tentative"}], "category_name": "Language Tone"}, {"category_id": "social_tone", "tones": [{"tone_name": "Openness", "score": 0.798847, "tone_id": "openness_big5"}, {"tone_name": "Conscientiousness", "score": 0.721977, "tone_id": "conscientiousness_big5"}, {"tone_name": "Extraversion", "score": 0.155266, "tone_id": "extraversion_big5"}, {"tone_name": "Agreeableness", "score": 0.564593, "tone_id": "agreeableness_big5"}, {"tone_name": "Emotional Range", "score": 0.263836, "tone_id": "emotional_range_big5"}], "category_name": "Social Tone"}], "input_from": 2262}, {"input_to": 2364, "text": "Turnt up in the party getting lit to Yachty.", "sentence_id": 53, "tone_categories": [{"category_id": "emotion_tone", "tones": [{"tone_name": "Anger", "score": 0.089946, "tone_id": "anger"}, {"tone_name": "Disgust", "score": 0.095117, "tone_id": "disgust"}, {"tone_name": "Fear", "score": 0.093576, "tone_id": "fear"}, {"tone_name": "Joy", "score": 0.388521, "tone_id": "joy"}, {"tone_name": "Sadness", "score": 0.391543, "tone_id": "sadness"}], "category_name": "Emotion Tone"}, {"category_id": "language_tone", "tones": [{"tone_name": "Analytical", "score": 0.0, "tone_id": "analytical"}, {"tone_name": "Confident", "score": 0.0, "tone_id": "confident"}, {"tone_name": "Tentative", "score": 0.0, "tone_id": "tentative"}], "category_name": "Language Tone"}, {"category_id": "social_tone", "tones": [{"tone_name": "Openness", "score": 0.046515, "tone_id": "openness_big5"}, {"tone_name": "Conscientiousness", "score": 0.223786, "tone_id": "conscientiousness_big5"}, {"tone_name": "Extraversion", "score": 0.896963, "tone_id": "extraversion_big5"}, {"tone_name": "Agreeableness", "score": 0.167178, "tone_id": "agreeableness_big5"}, {"tone_name": "Emotional Range", "score": 0.273348, "tone_id": "emotional_range_big5"}], "category_name": "Social Tone"}], "input_from": 2320}, {"input_to": 2404, "text": "With a Spanish Barbie word to my mommy.", "sentence_id": 54, "tone_categories": [{"category_id": "emotion_tone", "tones": [{"tone_name": "Anger", "score": 0.054923, "tone_id": "anger"}, {"tone_name": "Disgust", "score": 0.087683, "tone_id": "disgust"}, {"tone_name": "Fear", "score": 0.032716, "tone_id": "fear"}, {"tone_name": "Joy", "score": 0.628111, "tone_id": "joy"}, {"tone_name": "Sadness", "score": 0.263146, "tone_id": "sadness"}], "category_name": "Emotion Tone"}, {"category_id": "language_tone", "tones": [{"tone_name": "Analytical", "score": 0.0, "tone_id": "analytical"}, {"tone_name": "Confident", "score": 0.0, "tone_id": "confident"}, {"tone_name": "Tentative", "score": 0.0, "tone_id": "tentative"}], "category_name": "Language Tone"}, {"category_id": "social_tone", "tones": [{"tone_name": "Openness", "score": 0.228848, "tone_id": "openness_big5"}, {"tone_name": "Conscientiousness", "score": 0.261246, "tone_id": "conscientiousness_big5"}, {"tone_name": "Extraversion", "score": 0.824596, "tone_id": "extraversion_big5"}, {"tone_name": "Agreeableness", "score": 0.681312, "tone_id": "agreeableness_big5"}, {"tone_name": "Emotional Range", "score": 0.530154, "tone_id": "emotional_range_big5"}], "category_name": "Social Tone"}], "input_from": 2365}, {"input_to": 2449, "text": "In the middle of the party bitch get off me.", "sentence_id": 55, "tone_categories": [{"category_id": "emotion_tone", "tones": [{"tone_name": "Anger", "score": 0.163159, "tone_id": "anger"}, {"tone_name": "Disgust", "score": 0.128805, "tone_id": "disgust"}, {"tone_name": "Fear", "score": 0.161715, "tone_id": "fear"}, {"tone_name": "Joy", "score": 0.268506, "tone_id": "joy"}, {"tone_name": "Sadness", "score": 0.339725, "tone_id": "sadness"}], "category_name": "Emotion Tone"}, {"category_id": "language_tone", "tones": [{"tone_name": "Analytical", "score": 0.0, "tone_id": "analytical"}, {"tone_name": "Confident", "score": 0.0, "tone_id": "confident"}, {"tone_name": "Tentative", "score": 0.0, "tone_id": "tentative"}], "category_name": "Language Tone"}, {"category_id": "social_tone", "tones": [{"tone_name": "Openness", "score": 0.499143, "tone_id": "openness_big5"}, {"tone_name": "Conscientiousness", "score": 0.390482, "tone_id": "conscientiousness_big5"}, {"tone_name": "Extraversion", "score": 0.899297, "tone_id": "extraversion_big5"}, {"tone_name": "Agreeableness", "score": 0.199983, "tone_id": "agreeableness_big5"}, {"tone_name": "Emotional Range", "score": 0.666529, "tone_id": "emotional_range_big5"}], "category_name": "Social Tone"}], "input_from": 2405}, {"input_to": 2488, "text": "In the cut I'm rolling up my broccoli.", "sentence_id": 56, "tone_categories": [{"category_id": "emotion_tone", "tones": [{"tone_name": "Anger", "score": 0.084023, "tone_id": "anger"}, {"tone_name": "Disgust", "score": 0.077306, "tone_id": "disgust"}, {"tone_name": "Fear", "score": 0.026908, "tone_id": "fear"}, {"tone_name": "Joy", "score": 0.616656, "tone_id": "joy"}, {"tone_name": "Sadness", "score": 0.259374, "tone_id": "sadness"}], "category_name": "Emotion Tone"}, {"category_id": "language_tone", "tones": [{"tone_name": "Analytical", "score": 0.0, "tone_id": "analytical"}, {"tone_name": "Confident", "score": 0.0, "tone_id": "confident"}, {"tone_name": "Tentative", "score": 0.0, "tone_id": "tentative"}], "category_name": "Language Tone"}, {"category_id": "social_tone", "tones": [{"tone_name": "Openness", "score": 0.638492, "tone_id": "openness_big5"}, {"tone_name": "Conscientiousness", "score": 0.207405, "tone_id": "conscientiousness_big5"}, {"tone_name": "Extraversion", "score": 0.540573, "tone_id": "extraversion_big5"}, {"tone_name": "Agreeableness", "score": 0.418581, "tone_id": "agreeableness_big5"}, {"tone_name": "Emotional Range", "score": 0.113375, "tone_id": "emotional_range_big5"}], "category_name": "Social Tone"}], "input_from": 2450}, {"input_to": 2525, "text": "Ya I know your baby mama fond of me.", "sentence_id": 57, "tone_categories": [{"category_id": "emotion_tone", "tones": [{"tone_name": "Anger", "score": 0.044709, "tone_id": "anger"}, {"tone_name": "Disgust", "score": 0.070487, "tone_id": "disgust"}, {"tone_name": "Fear", "score": 0.117295, "tone_id": "fear"}, {"tone_name": "Joy", "score": 0.403791, "tone_id": "joy"}, {"tone_name": "Sadness", "score": 0.430529, "tone_id": "sadness"}], "category_name": "Emotion Tone"}, {"category_id": "language_tone", "tones": [{"tone_name": "Analytical", "score": 0.0, "tone_id": "analytical"}, {"tone_name": "Confident", "score": 0.0, "tone_id": "confident"}, {"tone_name": "Tentative", "score": 0.0, "tone_id": "tentative"}], "category_name": "Language Tone"}, {"category_id": "social_tone", "tones": [{"tone_name": "Openness", "score": 0.339253, "tone_id": "openness_big5"}, {"tone_name": "Conscientiousness", "score": 0.426328, "tone_id": "conscientiousness_big5"}, {"tone_name": "Extraversion", "score": 0.839192, "tone_id": "extraversion_big5"}, {"tone_name": "Agreeableness", "score": 0.803751, "tone_id": "agreeableness_big5"}, {"tone_name": "Emotional Range", "score": 0.147785, "tone_id": "emotional_range_big5"}], "category_name": "Social Tone"}], "input_from": 2489}, {"input_to": 2568, "text": "All she want to do is smoke that broccoli.", "sentence_id": 58, "tone_categories": [{"category_id": "emotion_tone", "tones": [{"tone_name": "Anger", "score": 0.078693, "tone_id": "anger"}, {"tone_name": "Disgust", "score": 0.372258, "tone_id": "disgust"}, {"tone_name": "Fear", "score": 0.053632, "tone_id": "fear"}, {"tone_name": "Joy", "score": 0.112671, "tone_id": "joy"}, {"tone_name": "Sadness", "score": 0.451613, "tone_id": "sadness"}], "category_name": "Emotion Tone"}, {"category_id": "language_tone", "tones": [{"tone_name": "Analytical", "score": 0.0, "tone_id": "analytical"}, {"tone_name": "Confident", "score": 0.874372, "tone_id": "confident"}, {"tone_name": "Tentative", "score": 0.0, "tone_id": "tentative"}], "category_name": "Language Tone"}, {"category_id": "social_tone", "tones": [{"tone_name": "Openness", "score": 0.80601, "tone_id": "openness_big5"}, {"tone_name": "Conscientiousness", "score": 0.589297, "tone_id": "conscientiousness_big5"}, {"tone_name": "Extraversion", "score": 0.564062, "tone_id": "extraversion_big5"}, {"tone_name": "Agreeableness", "score": 0.591797, "tone_id": "agreeableness_big5"}, {"tone_name": "Emotional Range", "score": 0.539567, "tone_id": "emotional_range_big5"}], "category_name": "Social Tone"}], "input_from": 2526}, {"input_to": 2617, "text": "Whispered in my ear she trying to leave with me.", "sentence_id": 59, "tone_categories": [{"category_id": "emotion_tone", "tones": [{"tone_name": "Anger", "score": 0.060436, "tone_id": "anger"}, {"tone_name": "Disgust", "score": 0.172675, "tone_id": "disgust"}, {"tone_name": "Fear", "score": 0.248697, "tone_id": "fear"}, {"tone_name": "Joy", "score": 0.023458, "tone_id": "joy"}, {"tone_name": "Sadness", "score": 0.621952, "tone_id": "sadness"}], "category_name": "Emotion Tone"}, {"category_id": "language_tone", "tones": [{"tone_name": "Analytical", "score": 0.0, "tone_id": "analytical"}, {"tone_name": "Confident", "score": 0.0, "tone_id": "confident"}, {"tone_name": "Tentative", "score": 0.497569, "tone_id": "tentative"}], "category_name": "Language Tone"}, {"category_id": "social_tone", "tones": [{"tone_name": "Openness", "score": 0.347976, "tone_id": "openness_big5"}, {"tone_name": "Conscientiousness", "score": 0.226509, "tone_id": "conscientiousness_big5"}, {"tone_name": "Extraversion", "score": 0.810184, "tone_id": "extraversion_big5"}, {"tone_name": "Agreeableness", "score": 0.766563, "tone_id": "agreeableness_big5"}, {"tone_name": "Emotional Range", "score": 0.014736, "tone_id": "emotional_range_big5"}], "category_name": "Social Tone"}], "input_from": 2569}, {"input_to": 2656, "text": "Said that I can get that pussy easily.", "sentence_id": 60, "tone_categories": [{"category_id": "emotion_tone", "tones": [{"tone_name": "Anger", "score": 0.151481, "tone_id": "anger"}, {"tone_name": "Disgust", "score": 0.082909, "tone_id": "disgust"}, {"tone_name": "Fear", "score": 0.191965, "tone_id": "fear"}, {"tone_name": "Joy", "score": 0.068459, "tone_id": "joy"}, {"tone_name": "Sadness", "score": 0.60175, "tone_id": "sadness"}], "category_name": "Emotion Tone"}, {"category_id": "language_tone", "tones": [{"tone_name": "Analytical", "score": 0.0, "tone_id": "analytical"}, {"tone_name": "Confident", "score": 0.0, "tone_id": "confident"}, {"tone_name": "Tentative", "score": 0.0, "tone_id": "tentative"}], "category_name": "Language Tone"}, {"category_id": "social_tone", "tones": [{"tone_name": "Openness", "score": 0.659527, "tone_id": "openness_big5"}, {"tone_name": "Conscientiousness", "score": 0.643288, "tone_id": "conscientiousness_big5"}, {"tone_name": "Extraversion", "score": 0.110692, "tone_id": "extraversion_big5"}, {"tone_name": "Agreeableness", "score": 0.804676, "tone_id": "agreeableness_big5"}, {"tone_name": "Emotional Range", "score": 0.768164, "tone_id": "emotional_range_big5"}], "category_name": "Social Tone"}], "input_from": 2618}, {"input_to": 2699, "text": "Said that I can hit that shit so greasily.", "sentence_id": 61, "tone_categories": [{"category_id": "emotion_tone", "tones": [{"tone_name": "Anger", "score": 0.112637, "tone_id": "anger"}, {"tone_name": "Disgust", "score": 0.162601, "tone_id": "disgust"}, {"tone_name": "Fear", "score": 0.045653, "tone_id": "fear"}, {"tone_name": "Joy", "score": 0.303001, "tone_id": "joy"}, {"tone_name": "Sadness", "score": 0.459255, "tone_id": "sadness"}], "category_name": "Emotion Tone"}, {"category_id": "language_tone", "tones": [{"tone_name": "Analytical", "score": 0.0, "tone_id": "analytical"}, {"tone_name": "Confident", "score": 0.0, "tone_id": "confident"}, {"tone_name": "Tentative", "score": 0.0, "tone_id": "tentative"}], "category_name": "Language Tone"}, {"category_id": "social_tone", "tones": [{"tone_name": "Openness", "score": 0.652336, "tone_id": "openness_big5"}, {"tone_name": "Conscientiousness", "score": 0.566966, "tone_id": "conscientiousness_big5"}, {"tone_name": "Extraversion", "score": 0.075422, "tone_id": "extraversion_big5"}, {"tone_name": "Agreeableness", "score": 0.704367, "tone_id": "agreeableness_big5"}, {"tone_name": "Emotional Range", "score": 0.736733, "tone_id": "emotional_range_big5"}], "category_name": "Social Tone"}], "input_from": 2657}, {"input_to": 2734, "text": "I'm a dirty dog I did it sleazily.", "sentence_id": 62, "tone_categories": [{"category_id": "emotion_tone", "tones": [{"tone_name": "Anger", "score": 0.064668, "tone_id": "anger"}, {"tone_name": "Disgust", "score": 0.869805, "tone_id": "disgust"}, {"tone_name": "Fear", "score": 0.038333, "tone_id": "fear"}, {"tone_name": "Joy", "score": 0.063066, "tone_id": "joy"}, {"tone_name": "Sadness", "score": 0.025545, "tone_id": "sadness"}], "category_name": "Emotion Tone"}, {"category_id": "language_tone", "tones": [{"tone_name": "Analytical", "score": 0.0, "tone_id": "analytical"}, {"tone_name": "Confident", "score": 0.0, "tone_id": "confident"}, {"tone_name": "Tentative", "score": 0.0, "tone_id": "tentative"}], "category_name": "Language Tone"}, {"category_id": "social_tone", "tones": [{"tone_name": "Openness", "score": 0.307799, "tone_id": "openness_big5"}, {"tone_name": "Conscientiousness", "score": 0.001663, "tone_id": "conscientiousness_big5"}, {"tone_name": "Extraversion", "score": 0.017888, "tone_id": "extraversion_big5"}, {"tone_name": "Agreeableness", "score": 0.215365, "tone_id": "agreeableness_big5"}, {"tone_name": "Emotional Range", "score": 0.093894, "tone_id": "emotional_range_big5"}], "category_name": "Social Tone"}], "input_from": 2700}]}