{"document_tone": {"tone_categories": [{"category_id": "emotion_tone", "tones": [{"tone_name": "Anger", "score": 0.159827, "tone_id": "anger"}, {"tone_name": "Disgust", "score": 0.013651, "tone_id": "disgust"}, {"tone_name": "Fear", "score": 0.006754, "tone_id": "fear"}, {"tone_name": "Joy", "score": 0.688572, "tone_id": "joy"}, {"tone_name": "Sadness", "score": 0.132681, "tone_id": "sadness"}], "category_name": "Emotion Tone"}, {"category_id": "language_tone", "tones": [{"tone_name": "Analytical", "score": 0.0, "tone_id": "analytical"}, {"tone_name": "Confident", "score": 0.0, "tone_id": "confident"}, {"tone_name": "Tentative", "score": 0.551011, "tone_id": "tentative"}], "category_name": "Language Tone"}, {"category_id": "social_tone", "tones": [{"tone_name": "Openness", "score": 0.001153, "tone_id": "openness_big5"}, {"tone_name": "Conscientiousness", "score": 0.933341, "tone_id": "conscientiousness_big5"}, {"tone_name": "Extraversion", "score": 0.517629, "tone_id": "extraversion_big5"}, {"tone_name": "Agreeableness", "score": 0.992082, "tone_id": "agreeableness_big5"}, {"tone_name": "Emotional Range", "score": 0.260405, "tone_id": "emotional_range_big5"}], "category_name": "Social Tone"}]}, "sentences_tone": [{"input_to": 7, "text": "Oh hey.", "sentence_id": 0, "tone_categories": [], "input_from": 0}, {"input_to": 19, "text": "Oh, oh hey.", "sentence_id": 1, "tone_categories": [], "input_from": 8}, {"input_to": 35, "text": "Oh, oh, oh hey.", "sentence_id": 2, "tone_categories": [{"category_id": "emotion_tone", "tones": [{"tone_name": "Anger", "score": 0.097065, "tone_id": "anger"}, {"tone_name": "Disgust", "score": 0.041484, "tone_id": "disgust"}, {"tone_name": "Fear", "score": 0.176703, "tone_id": "fear"}, {"tone_name": "Joy", "score": 0.323319, "tone_id": "joy"}, {"tone_name": "Sadness", "score": 0.410897, "tone_id": "sadness"}], "category_name": "Emotion Tone"}, {"category_id": "language_tone", "tones": [{"tone_name": "Analytical", "score": 0.0, "tone_id": "analytical"}, {"tone_name": "Confident", "score": 0.0, "tone_id": "confident"}, {"tone_name": "Tentative", "score": 0.0, "tone_id": "tentative"}], "category_name": "Language Tone"}, {"category_id": "social_tone", "tones": [{"tone_name": "Openness", "score": 0.259574, "tone_id": "openness_big5"}, {"tone_name": "Conscientiousness", "score": 0.274457, "tone_id": "conscientiousness_big5"}, {"tone_name": "Extraversion", "score": 0.543206, "tone_id": "extraversion_big5"}, {"tone_name": "Agreeableness", "score": 0.59952, "tone_id": "agreeableness_big5"}, {"tone_name": "Emotional Range", "score": 0.299772, "tone_id": "emotional_range_big5"}], "category_name": "Social Tone"}], "input_from": 20}, {"input_to": 49, "text": "Uh oh, uh oh.", "sentence_id": 3, "tone_categories": [{"category_id": "emotion_tone", "tones": [{"tone_name": "Anger", "score": 0.051112, "tone_id": "anger"}, {"tone_name": "Disgust", "score": 0.035952, "tone_id": "disgust"}, {"tone_name": "Fear", "score": 0.577526, "tone_id": "fear"}, {"tone_name": "Joy", "score": 0.347636, "tone_id": "joy"}, {"tone_name": "Sadness", "score": 0.049835, "tone_id": "sadness"}], "category_name": "Emotion Tone"}, {"category_id": "language_tone", "tones": [{"tone_name": "Analytical", "score": 0.0, "tone_id": "analytical"}, {"tone_name": "Confident", "score": 0.0, "tone_id": "confident"}, {"tone_name": "Tentative", "score": 0.0, "tone_id": "tentative"}], "category_name": "Language Tone"}, {"category_id": "social_tone", "tones": [{"tone_name": "Openness", "score": 0.260223, "tone_id": "openness_big5"}, {"tone_name": "Conscientiousness", "score": 0.274457, "tone_id": "conscientiousness_big5"}, {"tone_name": "Extraversion", "score": 0.543033, "tone_id": "extraversion_big5"}, {"tone_name": "Agreeableness", "score": 0.599501, "tone_id": "agreeableness_big5"}, {"tone_name": "Emotional Range", "score": 0.294499, "tone_id": "emotional_range_big5"}], "category_name": "Social Tone"}], "input_from": 36}, {"input_to": 87, "text": "I don't wanna know, know, know, know.", "sentence_id": 4, "tone_categories": [{"category_id": "emotion_tone", "tones": [{"tone_name": "Anger", "score": 0.08893, "tone_id": "anger"}, {"tone_name": "Disgust", "score": 0.029665, "tone_id": "disgust"}, {"tone_name": "Fear", "score": 0.128077, "tone_id": "fear"}, {"tone_name": "Joy", "score": 0.122079, "tone_id": "joy"}, {"tone_name": "Sadness", "score": 0.719966, "tone_id": "sadness"}], "category_name": "Emotion Tone"}, {"category_id": "language_tone", "tones": [{"tone_name": "Analytical", "score": 0.93884, "tone_id": "analytical"}, {"tone_name": "Confident", "score": 0.0, "tone_id": "confident"}, {"tone_name": "Tentative", "score": 0.0, "tone_id": "tentative"}], "category_name": "Language Tone"}, {"category_id": "social_tone", "tones": [{"tone_name": "Openness", "score": 0.110727, "tone_id": "openness_big5"}, {"tone_name": "Conscientiousness", "score": 0.328356, "tone_id": "conscientiousness_big5"}, {"tone_name": "Extraversion", "score": 0.404247, "tone_id": "extraversion_big5"}, {"tone_name": "Agreeableness", "score": 0.568497, "tone_id": "agreeableness_big5"}, {"tone_name": "Emotional Range", "score": 0.276836, "tone_id": "emotional_range_big5"}], "category_name": "Social Tone"}], "input_from": 50}, {"input_to": 128, "text": "Who\u2018s taking you home, home, home, home.", "sentence_id": 5, "tone_categories": [{"category_id": "emotion_tone", "tones": [{"tone_name": "Anger", "score": 0.123141, "tone_id": "anger"}, {"tone_name": "Disgust", "score": 0.056906, "tone_id": "disgust"}, {"tone_name": "Fear", "score": 0.147947, "tone_id": "fear"}, {"tone_name": "Joy", "score": 0.680187, "tone_id": "joy"}, {"tone_name": "Sadness", "score": 0.075893, "tone_id": "sadness"}], "category_name": "Emotion Tone"}, {"category_id": "language_tone", "tones": [{"tone_name": "Analytical", "score": 0.0, "tone_id": "analytical"}, {"tone_name": "Confident", "score": 0.0, "tone_id": "confident"}, {"tone_name": "Tentative", "score": 0.0, "tone_id": "tentative"}], "category_name": "Language Tone"}, {"category_id": "social_tone", "tones": [{"tone_name": "Openness", "score": 0.00211, "tone_id": "openness_big5"}, {"tone_name": "Conscientiousness", "score": 0.327082, "tone_id": "conscientiousness_big5"}, {"tone_name": "Extraversion", "score": 0.531741, "tone_id": "extraversion_big5"}, {"tone_name": "Agreeableness", "score": 0.640351, "tone_id": "agreeableness_big5"}, {"tone_name": "Emotional Range", "score": 0.482435, "tone_id": "emotional_range_big5"}], "category_name": "Social Tone"}], "input_from": 88}, {"input_to": 159, "text": "And loving you so, so, so, so.", "sentence_id": 6, "tone_categories": [{"category_id": "emotion_tone", "tones": [{"tone_name": "Anger", "score": 0.044234, "tone_id": "anger"}, {"tone_name": "Disgust", "score": 0.013642, "tone_id": "disgust"}, {"tone_name": "Fear", "score": 0.025767, "tone_id": "fear"}, {"tone_name": "Joy", "score": 0.723575, "tone_id": "joy"}, {"tone_name": "Sadness", "score": 0.242875, "tone_id": "sadness"}], "category_name": "Emotion Tone"}, {"category_id": "language_tone", "tones": [{"tone_name": "Analytical", "score": 0.0, "tone_id": "analytical"}, {"tone_name": "Confident", "score": 0.0, "tone_id": "confident"}, {"tone_name": "Tentative", "score": 0.0, "tone_id": "tentative"}], "category_name": "Language Tone"}, {"category_id": "social_tone", "tones": [{"tone_name": "Openness", "score": 0.097814, "tone_id": "openness_big5"}, {"tone_name": "Conscientiousness", "score": 0.280442, "tone_id": "conscientiousness_big5"}, {"tone_name": "Extraversion", "score": 0.581671, "tone_id": "extraversion_big5"}, {"tone_name": "Agreeableness", "score": 0.634751, "tone_id": "agreeableness_big5"}, {"tone_name": "Emotional Range", "score": 0.067996, "tone_id": "emotional_range_big5"}], "category_name": "Social Tone"}], "input_from": 129}, {"input_to": 191, "text": "The way I used to love you, no.", "sentence_id": 7, "tone_categories": [{"category_id": "emotion_tone", "tones": [{"tone_name": "Anger", "score": 0.098945, "tone_id": "anger"}, {"tone_name": "Disgust", "score": 0.053495, "tone_id": "disgust"}, {"tone_name": "Fear", "score": 0.077129, "tone_id": "fear"}, {"tone_name": "Joy", "score": 0.097725, "tone_id": "joy"}, {"tone_name": "Sadness", "score": 0.726223, "tone_id": "sadness"}], "category_name": "Emotion Tone"}, {"category_id": "language_tone", "tones": [{"tone_name": "Analytical", "score": 0.116314, "tone_id": "analytical"}, {"tone_name": "Confident", "score": 0.0, "tone_id": "confident"}, {"tone_name": "Tentative", "score": 0.0, "tone_id": "tentative"}], "category_name": "Language Tone"}, {"category_id": "social_tone", "tones": [{"tone_name": "Openness", "score": 0.11046, "tone_id": "openness_big5"}, {"tone_name": "Conscientiousness", "score": 0.550654, "tone_id": "conscientiousness_big5"}, {"tone_name": "Extraversion", "score": 0.616951, "tone_id": "extraversion_big5"}, {"tone_name": "Agreeableness", "score": 0.74965, "tone_id": "agreeableness_big5"}, {"tone_name": "Emotional Range", "score": 0.823096, "tone_id": "emotional_range_big5"}], "category_name": "Social Tone"}], "input_from": 160}, {"input_to": 229, "text": "I don't wanna know, know, know, know.", "sentence_id": 8, "tone_categories": [{"category_id": "emotion_tone", "tones": [{"tone_name": "Anger", "score": 0.08893, "tone_id": "anger"}, {"tone_name": "Disgust", "score": 0.029665, "tone_id": "disgust"}, {"tone_name": "Fear", "score": 0.128077, "tone_id": "fear"}, {"tone_name": "Joy", "score": 0.122079, "tone_id": "joy"}, {"tone_name": "Sadness", "score": 0.719966, "tone_id": "sadness"}], "category_name": "Emotion Tone"}, {"category_id": "language_tone", "tones": [{"tone_name": "Analytical", "score": 0.93884, "tone_id": "analytical"}, {"tone_name": "Confident", "score": 0.0, "tone_id": "confident"}, {"tone_name": "Tentative", "score": 0.0, "tone_id": "tentative"}], "category_name": "Language Tone"}, {"category_id": "social_tone", "tones": [{"tone_name": "Openness", "score": 0.110727, "tone_id": "openness_big5"}, {"tone_name": "Conscientiousness", "score": 0.328356, "tone_id": "conscientiousness_big5"}, {"tone_name": "Extraversion", "score": 0.404247, "tone_id": "extraversion_big5"}, {"tone_name": "Agreeableness", "score": 0.568497, "tone_id": "agreeableness_big5"}, {"tone_name": "Emotional Range", "score": 0.276836, "tone_id": "emotional_range_big5"}], "category_name": "Social Tone"}], "input_from": 192}, {"input_to": 270, "text": "Who's taking you home, home, home, home.", "sentence_id": 9, "tone_categories": [{"category_id": "emotion_tone", "tones": [{"tone_name": "Anger", "score": 0.12746, "tone_id": "anger"}, {"tone_name": "Disgust", "score": 0.073118, "tone_id": "disgust"}, {"tone_name": "Fear", "score": 0.145777, "tone_id": "fear"}, {"tone_name": "Joy", "score": 0.680181, "tone_id": "joy"}, {"tone_name": "Sadness", "score": 0.070942, "tone_id": "sadness"}], "category_name": "Emotion Tone"}, {"category_id": "language_tone", "tones": [{"tone_name": "Analytical", "score": 0.0, "tone_id": "analytical"}, {"tone_name": "Confident", "score": 0.0, "tone_id": "confident"}, {"tone_name": "Tentative", "score": 0.0, "tone_id": "tentative"}], "category_name": "Language Tone"}, {"category_id": "social_tone", "tones": [{"tone_name": "Openness", "score": 0.00805, "tone_id": "openness_big5"}, {"tone_name": "Conscientiousness", "score": 0.286228, "tone_id": "conscientiousness_big5"}, {"tone_name": "Extraversion", "score": 0.553924, "tone_id": "extraversion_big5"}, {"tone_name": "Agreeableness", "score": 0.615368, "tone_id": "agreeableness_big5"}, {"tone_name": "Emotional Range", "score": 0.369658, "tone_id": "emotional_range_big5"}], "category_name": "Social Tone"}], "input_from": 230}, {"input_to": 301, "text": "And loving you so, so, so, so.", "sentence_id": 10, "tone_categories": [{"category_id": "emotion_tone", "tones": [{"tone_name": "Anger", "score": 0.044234, "tone_id": "anger"}, {"tone_name": "Disgust", "score": 0.013642, "tone_id": "disgust"}, {"tone_name": "Fear", "score": 0.025767, "tone_id": "fear"}, {"tone_name": "Joy", "score": 0.723575, "tone_id": "joy"}, {"tone_name": "Sadness", "score": 0.242875, "tone_id": "sadness"}], "category_name": "Emotion Tone"}, {"category_id": "language_tone", "tones": [{"tone_name": "Analytical", "score": 0.0, "tone_id": "analytical"}, {"tone_name": "Confident", "score": 0.0, "tone_id": "confident"}, {"tone_name": "Tentative", "score": 0.0, "tone_id": "tentative"}], "category_name": "Language Tone"}, {"category_id": "social_tone", "tones": [{"tone_name": "Openness", "score": 0.097814, "tone_id": "openness_big5"}, {"tone_name": "Conscientiousness", "score": 0.280442, "tone_id": "conscientiousness_big5"}, {"tone_name": "Extraversion", "score": 0.581671, "tone_id": "extraversion_big5"}, {"tone_name": "Agreeableness", "score": 0.634751, "tone_id": "agreeableness_big5"}, {"tone_name": "Emotional Range", "score": 0.067996, "tone_id": "emotional_range_big5"}], "category_name": "Social Tone"}], "input_from": 271}, {"input_to": 333, "text": "The way I used to love you, oh.", "sentence_id": 11, "tone_categories": [{"category_id": "emotion_tone", "tones": [{"tone_name": "Anger", "score": 0.090054, "tone_id": "anger"}, {"tone_name": "Disgust", "score": 0.037155, "tone_id": "disgust"}, {"tone_name": "Fear", "score": 0.079356, "tone_id": "fear"}, {"tone_name": "Joy", "score": 0.146338, "tone_id": "joy"}, {"tone_name": "Sadness", "score": 0.683564, "tone_id": "sadness"}], "category_name": "Emotion Tone"}, {"category_id": "language_tone", "tones": [{"tone_name": "Analytical", "score": 0.0, "tone_id": "analytical"}, {"tone_name": "Confident", "score": 0.0, "tone_id": "confident"}, {"tone_name": "Tentative", "score": 0.0, "tone_id": "tentative"}], "category_name": "Language Tone"}, {"category_id": "social_tone", "tones": [{"tone_name": "Openness", "score": 0.126115, "tone_id": "openness_big5"}, {"tone_name": "Conscientiousness", "score": 0.671193, "tone_id": "conscientiousness_big5"}, {"tone_name": "Extraversion", "score": 0.617389, "tone_id": "extraversion_big5"}, {"tone_name": "Agreeableness", "score": 0.947059, "tone_id": "agreeableness_big5"}, {"tone_name": "Emotional Range", "score": 0.790395, "tone_id": "emotional_range_big5"}], "category_name": "Social Tone"}], "input_from": 302}, {"input_to": 353, "text": "I don't wanna know.", "sentence_id": 12, "tone_categories": [{"category_id": "emotion_tone", "tones": [{"tone_name": "Anger", "score": 0.112917, "tone_id": "anger"}, {"tone_name": "Disgust", "score": 0.047376, "tone_id": "disgust"}, {"tone_name": "Fear", "score": 0.164002, "tone_id": "fear"}, {"tone_name": "Joy", "score": 0.101987, "tone_id": "joy"}, {"tone_name": "Sadness", "score": 0.662436, "tone_id": "sadness"}], "category_name": "Emotion Tone"}, {"category_id": "language_tone", "tones": [{"tone_name": "Analytical", "score": 0.0, "tone_id": "analytical"}, {"tone_name": "Confident", "score": 0.0, "tone_id": "confident"}, {"tone_name": "Tentative", "score": 0.0, "tone_id": "tentative"}], "category_name": "Language Tone"}, {"category_id": "social_tone", "tones": [{"tone_name": "Openness", "score": 0.075882, "tone_id": "openness_big5"}, {"tone_name": "Conscientiousness", "score": 0.299336, "tone_id": "conscientiousness_big5"}, {"tone_name": "Extraversion", "score": 0.37318, "tone_id": "extraversion_big5"}, {"tone_name": "Agreeableness", "score": 0.547426, "tone_id": "agreeableness_big5"}, {"tone_name": "Emotional Range", "score": 0.117378, "tone_id": "emotional_range_big5"}], "category_name": "Social Tone"}], "input_from": 334}, {"input_to": 370, "text": "Wasted (wasted).", "sentence_id": 13, "tone_categories": [], "input_from": 354}, {"input_to": 419, "text": "And the more I drink the more I think about you.", "sentence_id": 14, "tone_categories": [{"category_id": "emotion_tone", "tones": [{"tone_name": "Anger", "score": 0.079, "tone_id": "anger"}, {"tone_name": "Disgust", "score": 0.555255, "tone_id": "disgust"}, {"tone_name": "Fear", "score": 0.03078, "tone_id": "fear"}, {"tone_name": "Joy", "score": 0.261099, "tone_id": "joy"}, {"tone_name": "Sadness", "score": 0.184609, "tone_id": "sadness"}], "category_name": "Emotion Tone"}, {"category_id": "language_tone", "tones": [{"tone_name": "Analytical", "score": 0.8152, "tone_id": "analytical"}, {"tone_name": "Confident", "score": 0.0, "tone_id": "confident"}, {"tone_name": "Tentative", "score": 0.0, "tone_id": "tentative"}], "category_name": "Language Tone"}, {"category_id": "social_tone", "tones": [{"tone_name": "Openness", "score": 0.744268, "tone_id": "openness_big5"}, {"tone_name": "Conscientiousness", "score": 0.332966, "tone_id": "conscientiousness_big5"}, {"tone_name": "Extraversion", "score": 0.380291, "tone_id": "extraversion_big5"}, {"tone_name": "Agreeableness", "score": 0.610014, "tone_id": "agreeableness_big5"}, {"tone_name": "Emotional Range", "score": 0.28875, "tone_id": "emotional_range_big5"}], "category_name": "Social Tone"}], "input_from": 371}, {"input_to": 447, "text": "Oh no, no, I can't take it.", "sentence_id": 15, "tone_categories": [{"category_id": "emotion_tone", "tones": [{"tone_name": "Anger", "score": 0.065352, "tone_id": "anger"}, {"tone_name": "Disgust", "score": 0.018907, "tone_id": "disgust"}, {"tone_name": "Fear", "score": 0.607152, "tone_id": "fear"}, {"tone_name": "Joy", "score": 0.170239, "tone_id": "joy"}, {"tone_name": "Sadness", "score": 0.244491, "tone_id": "sadness"}], "category_name": "Emotion Tone"}, {"category_id": "language_tone", "tones": [{"tone_name": "Analytical", "score": 0.0, "tone_id": "analytical"}, {"tone_name": "Confident", "score": 0.0, "tone_id": "confident"}, {"tone_name": "Tentative", "score": 0.0, "tone_id": "tentative"}], "category_name": "Language Tone"}, {"category_id": "social_tone", "tones": [{"tone_name": "Openness", "score": 0.012979, "tone_id": "openness_big5"}, {"tone_name": "Conscientiousness", "score": 0.318737, "tone_id": "conscientiousness_big5"}, {"tone_name": "Extraversion", "score": 0.175083, "tone_id": "extraversion_big5"}, {"tone_name": "Agreeableness", "score": 0.478185, "tone_id": "agreeableness_big5"}, {"tone_name": "Emotional Range", "score": 0.221918, "tone_id": "emotional_range_big5"}], "category_name": "Social Tone"}], "input_from": 420}, {"input_to": 488, "text": "Baby every place I go reminds me of you.", "sentence_id": 16, "tone_categories": [{"category_id": "emotion_tone", "tones": [{"tone_name": "Anger", "score": 0.034339, "tone_id": "anger"}, {"tone_name": "Disgust", "score": 0.065489, "tone_id": "disgust"}, {"tone_name": "Fear", "score": 0.160841, "tone_id": "fear"}, {"tone_name": "Joy", "score": 0.354026, "tone_id": "joy"}, {"tone_name": "Sadness", "score": 0.458955, "tone_id": "sadness"}], "category_name": "Emotion Tone"}, {"category_id": "language_tone", "tones": [{"tone_name": "Analytical", "score": 0.0, "tone_id": "analytical"}, {"tone_name": "Confident", "score": 0.874372, "tone_id": "confident"}, {"tone_name": "Tentative", "score": 0.0, "tone_id": "tentative"}], "category_name": "Language Tone"}, {"category_id": "social_tone", "tones": [{"tone_name": "Openness", "score": 0.233331, "tone_id": "openness_big5"}, {"tone_name": "Conscientiousness", "score": 0.727058, "tone_id": "conscientiousness_big5"}, {"tone_name": "Extraversion", "score": 0.922427, "tone_id": "extraversion_big5"}, {"tone_name": "Agreeableness", "score": 0.992817, "tone_id": "agreeableness_big5"}, {"tone_name": "Emotional Range", "score": 0.300015, "tone_id": "emotional_range_big5"}], "category_name": "Social Tone"}], "input_from": 448}, {"input_to": 508, "text": "Do you think of me?", "sentence_id": 17, "tone_categories": [{"category_id": "emotion_tone", "tones": [{"tone_name": "Anger", "score": 0.095417, "tone_id": "anger"}, {"tone_name": "Disgust", "score": 0.072352, "tone_id": "disgust"}, {"tone_name": "Fear", "score": 0.317368, "tone_id": "fear"}, {"tone_name": "Joy", "score": 0.314012, "tone_id": "joy"}, {"tone_name": "Sadness", "score": 0.295947, "tone_id": "sadness"}], "category_name": "Emotion Tone"}, {"category_id": "language_tone", "tones": [{"tone_name": "Analytical", "score": 0.994057, "tone_id": "analytical"}, {"tone_name": "Confident", "score": 0.0, "tone_id": "confident"}, {"tone_name": "Tentative", "score": 0.0, "tone_id": "tentative"}], "category_name": "Language Tone"}, {"category_id": "social_tone", "tones": [{"tone_name": "Openness", "score": 0.453564, "tone_id": "openness_big5"}, {"tone_name": "Conscientiousness", "score": 0.457911, "tone_id": "conscientiousness_big5"}, {"tone_name": "Extraversion", "score": 0.538857, "tone_id": "extraversion_big5"}, {"tone_name": "Agreeableness", "score": 0.666586, "tone_id": "agreeableness_big5"}, {"tone_name": "Emotional Range", "score": 0.139579, "tone_id": "emotional_range_big5"}], "category_name": "Social Tone"}], "input_from": 489}, {"input_to": 532, "text": "Of what we used to be?.", "sentence_id": 18, "tone_categories": [{"category_id": "emotion_tone", "tones": [{"tone_name": "Anger", "score": 0.028724, "tone_id": "anger"}, {"tone_name": "Disgust", "score": 0.108879, "tone_id": "disgust"}, {"tone_name": "Fear", "score": 0.226639, "tone_id": "fear"}, {"tone_name": "Joy", "score": 0.12236, "tone_id": "joy"}, {"tone_name": "Sadness", "score": 0.586047, "tone_id": "sadness"}], "category_name": "Emotion Tone"}, {"category_id": "language_tone", "tones": [{"tone_name": "Analytical", "score": 0.0, "tone_id": "analytical"}, {"tone_name": "Confident", "score": 0.0, "tone_id": "confident"}, {"tone_name": "Tentative", "score": 0.0, "tone_id": "tentative"}], "category_name": "Language Tone"}, {"category_id": "social_tone", "tones": [{"tone_name": "Openness", "score": 0.473529, "tone_id": "openness_big5"}, {"tone_name": "Conscientiousness", "score": 0.650253, "tone_id": "conscientiousness_big5"}, {"tone_name": "Extraversion", "score": 0.204638, "tone_id": "extraversion_big5"}, {"tone_name": "Agreeableness", "score": 0.663215, "tone_id": "agreeableness_big5"}, {"tone_name": "Emotional Range", "score": 0.710573, "tone_id": "emotional_range_big5"}], "category_name": "Social Tone"}], "input_from": 509}, {"input_to": 633, "text": "Is it better now that I'm not around?.\nMy friends are actin' strange, they don't bring up your name.", "sentence_id": 19, "tone_categories": [{"category_id": "emotion_tone", "tones": [{"tone_name": "Anger", "score": 0.111754, "tone_id": "anger"}, {"tone_name": "Disgust", "score": 0.031774, "tone_id": "disgust"}, {"tone_name": "Fear", "score": 0.142577, "tone_id": "fear"}, {"tone_name": "Joy", "score": 0.032844, "tone_id": "joy"}, {"tone_name": "Sadness", "score": 0.74882, "tone_id": "sadness"}], "category_name": "Emotion Tone"}, {"category_id": "language_tone", "tones": [{"tone_name": "Analytical", "score": 0.620279, "tone_id": "analytical"}, {"tone_name": "Confident", "score": 0.0, "tone_id": "confident"}, {"tone_name": "Tentative", "score": 0.5538, "tone_id": "tentative"}], "category_name": "Language Tone"}, {"category_id": "social_tone", "tones": [{"tone_name": "Openness", "score": 0.712453, "tone_id": "openness_big5"}, {"tone_name": "Conscientiousness", "score": 0.548809, "tone_id": "conscientiousness_big5"}, {"tone_name": "Extraversion", "score": 0.522369, "tone_id": "extraversion_big5"}, {"tone_name": "Agreeableness", "score": 0.163408, "tone_id": "agreeableness_big5"}, {"tone_name": "Emotional Range", "score": 0.178076, "tone_id": "emotional_range_big5"}], "category_name": "Social Tone"}], "input_from": 533}, {"input_to": 653, "text": "Are you happy now?.", "sentence_id": 20, "tone_categories": [{"category_id": "emotion_tone", "tones": [{"tone_name": "Anger", "score": 0.011507, "tone_id": "anger"}, {"tone_name": "Disgust", "score": 0.011595, "tone_id": "disgust"}, {"tone_name": "Fear", "score": 0.018799, "tone_id": "fear"}, {"tone_name": "Joy", "score": 0.888221, "tone_id": "joy"}, {"tone_name": "Sadness", "score": 0.078883, "tone_id": "sadness"}], "category_name": "Emotion Tone"}, {"category_id": "language_tone", "tones": [{"tone_name": "Analytical", "score": 0.0, "tone_id": "analytical"}, {"tone_name": "Confident", "score": 0.0, "tone_id": "confident"}, {"tone_name": "Tentative", "score": 0.0, "tone_id": "tentative"}], "category_name": "Language Tone"}, {"category_id": "social_tone", "tones": [{"tone_name": "Openness", "score": 0.18025, "tone_id": "openness_big5"}, {"tone_name": "Conscientiousness", "score": 0.344574, "tone_id": "conscientiousness_big5"}, {"tone_name": "Extraversion", "score": 0.591315, "tone_id": "extraversion_big5"}, {"tone_name": "Agreeableness", "score": 0.637124, "tone_id": "agreeableness_big5"}, {"tone_name": "Emotional Range", "score": 0.4858, "tone_id": "emotional_range_big5"}], "category_name": "Social Tone"}], "input_from": 634}, {"input_to": 673, "text": "Are you happy now?.", "sentence_id": 21, "tone_categories": [{"category_id": "emotion_tone", "tones": [{"tone_name": "Anger", "score": 0.011507, "tone_id": "anger"}, {"tone_name": "Disgust", "score": 0.011595, "tone_id": "disgust"}, {"tone_name": "Fear", "score": 0.018799, "tone_id": "fear"}, {"tone_name": "Joy", "score": 0.888221, "tone_id": "joy"}, {"tone_name": "Sadness", "score": 0.078883, "tone_id": "sadness"}], "category_name": "Emotion Tone"}, {"category_id": "language_tone", "tones": [{"tone_name": "Analytical", "score": 0.0, "tone_id": "analytical"}, {"tone_name": "Confident", "score": 0.0, "tone_id": "confident"}, {"tone_name": "Tentative", "score": 0.0, "tone_id": "tentative"}], "category_name": "Language Tone"}, {"category_id": "social_tone", "tones": [{"tone_name": "Openness", "score": 0.18025, "tone_id": "openness_big5"}, {"tone_name": "Conscientiousness", "score": 0.344574, "tone_id": "conscientiousness_big5"}, {"tone_name": "Extraversion", "score": 0.591315, "tone_id": "extraversion_big5"}, {"tone_name": "Agreeableness", "score": 0.637124, "tone_id": "agreeableness_big5"}, {"tone_name": "Emotional Range", "score": 0.4858, "tone_id": "emotional_range_big5"}], "category_name": "Social Tone"}], "input_from": 654}, {"input_to": 711, "text": "I don't wanna know, know, know, know.", "sentence_id": 22, "tone_categories": [{"category_id": "emotion_tone", "tones": [{"tone_name": "Anger", "score": 0.08893, "tone_id": "anger"}, {"tone_name": "Disgust", "score": 0.029665, "tone_id": "disgust"}, {"tone_name": "Fear", "score": 0.128077, "tone_id": "fear"}, {"tone_name": "Joy", "score": 0.122079, "tone_id": "joy"}, {"tone_name": "Sadness", "score": 0.719966, "tone_id": "sadness"}], "category_name": "Emotion Tone"}, {"category_id": "language_tone", "tones": [{"tone_name": "Analytical", "score": 0.93884, "tone_id": "analytical"}, {"tone_name": "Confident", "score": 0.0, "tone_id": "confident"}, {"tone_name": "Tentative", "score": 0.0, "tone_id": "tentative"}], "category_name": "Language Tone"}, {"category_id": "social_tone", "tones": [{"tone_name": "Openness", "score": 0.110727, "tone_id": "openness_big5"}, {"tone_name": "Conscientiousness", "score": 0.328356, "tone_id": "conscientiousness_big5"}, {"tone_name": "Extraversion", "score": 0.404247, "tone_id": "extraversion_big5"}, {"tone_name": "Agreeableness", "score": 0.568497, "tone_id": "agreeableness_big5"}, {"tone_name": "Emotional Range", "score": 0.276836, "tone_id": "emotional_range_big5"}], "category_name": "Social Tone"}], "input_from": 674}, {"input_to": 752, "text": "Who's taking you home, home, home, home.", "sentence_id": 23, "tone_categories": [{"category_id": "emotion_tone", "tones": [{"tone_name": "Anger", "score": 0.12746, "tone_id": "anger"}, {"tone_name": "Disgust", "score": 0.073118, "tone_id": "disgust"}, {"tone_name": "Fear", "score": 0.145777, "tone_id": "fear"}, {"tone_name": "Joy", "score": 0.680181, "tone_id": "joy"}, {"tone_name": "Sadness", "score": 0.070942, "tone_id": "sadness"}], "category_name": "Emotion Tone"}, {"category_id": "language_tone", "tones": [{"tone_name": "Analytical", "score": 0.0, "tone_id": "analytical"}, {"tone_name": "Confident", "score": 0.0, "tone_id": "confident"}, {"tone_name": "Tentative", "score": 0.0, "tone_id": "tentative"}], "category_name": "Language Tone"}, {"category_id": "social_tone", "tones": [{"tone_name": "Openness", "score": 0.00805, "tone_id": "openness_big5"}, {"tone_name": "Conscientiousness", "score": 0.286228, "tone_id": "conscientiousness_big5"}, {"tone_name": "Extraversion", "score": 0.553924, "tone_id": "extraversion_big5"}, {"tone_name": "Agreeableness", "score": 0.615368, "tone_id": "agreeableness_big5"}, {"tone_name": "Emotional Range", "score": 0.369658, "tone_id": "emotional_range_big5"}], "category_name": "Social Tone"}], "input_from": 712}, {"input_to": 783, "text": "And loving you so, so, so, so.", "sentence_id": 24, "tone_categories": [{"category_id": "emotion_tone", "tones": [{"tone_name": "Anger", "score": 0.044234, "tone_id": "anger"}, {"tone_name": "Disgust", "score": 0.013642, "tone_id": "disgust"}, {"tone_name": "Fear", "score": 0.025767, "tone_id": "fear"}, {"tone_name": "Joy", "score": 0.723575, "tone_id": "joy"}, {"tone_name": "Sadness", "score": 0.242875, "tone_id": "sadness"}], "category_name": "Emotion Tone"}, {"category_id": "language_tone", "tones": [{"tone_name": "Analytical", "score": 0.0, "tone_id": "analytical"}, {"tone_name": "Confident", "score": 0.0, "tone_id": "confident"}, {"tone_name": "Tentative", "score": 0.0, "tone_id": "tentative"}], "category_name": "Language Tone"}, {"category_id": "social_tone", "tones": [{"tone_name": "Openness", "score": 0.097814, "tone_id": "openness_big5"}, {"tone_name": "Conscientiousness", "score": 0.280442, "tone_id": "conscientiousness_big5"}, {"tone_name": "Extraversion", "score": 0.581671, "tone_id": "extraversion_big5"}, {"tone_name": "Agreeableness", "score": 0.634751, "tone_id": "agreeableness_big5"}, {"tone_name": "Emotional Range", "score": 0.067996, "tone_id": "emotional_range_big5"}], "category_name": "Social Tone"}], "input_from": 753}, {"input_to": 815, "text": "The way I used to love you, no.", "sentence_id": 25, "tone_categories": [{"category_id": "emotion_tone", "tones": [{"tone_name": "Anger", "score": 0.098945, "tone_id": "anger"}, {"tone_name": "Disgust", "score": 0.053495, "tone_id": "disgust"}, {"tone_name": "Fear", "score": 0.077129, "tone_id": "fear"}, {"tone_name": "Joy", "score": 0.097725, "tone_id": "joy"}, {"tone_name": "Sadness", "score": 0.726223, "tone_id": "sadness"}], "category_name": "Emotion Tone"}, {"category_id": "language_tone", "tones": [{"tone_name": "Analytical", "score": 0.116314, "tone_id": "analytical"}, {"tone_name": "Confident", "score": 0.0, "tone_id": "confident"}, {"tone_name": "Tentative", "score": 0.0, "tone_id": "tentative"}], "category_name": "Language Tone"}, {"category_id": "social_tone", "tones": [{"tone_name": "Openness", "score": 0.11046, "tone_id": "openness_big5"}, {"tone_name": "Conscientiousness", "score": 0.550654, "tone_id": "conscientiousness_big5"}, {"tone_name": "Extraversion", "score": 0.616951, "tone_id": "extraversion_big5"}, {"tone_name": "Agreeableness", "score": 0.74965, "tone_id": "agreeableness_big5"}, {"tone_name": "Emotional Range", "score": 0.823096, "tone_id": "emotional_range_big5"}], "category_name": "Social Tone"}], "input_from": 784}, {"input_to": 853, "text": "I don't wanna know, know, know, know.", "sentence_id": 26, "tone_categories": [{"category_id": "emotion_tone", "tones": [{"tone_name": "Anger", "score": 0.08893, "tone_id": "anger"}, {"tone_name": "Disgust", "score": 0.029665, "tone_id": "disgust"}, {"tone_name": "Fear", "score": 0.128077, "tone_id": "fear"}, {"tone_name": "Joy", "score": 0.122079, "tone_id": "joy"}, {"tone_name": "Sadness", "score": 0.719966, "tone_id": "sadness"}], "category_name": "Emotion Tone"}, {"category_id": "language_tone", "tones": [{"tone_name": "Analytical", "score": 0.93884, "tone_id": "analytical"}, {"tone_name": "Confident", "score": 0.0, "tone_id": "confident"}, {"tone_name": "Tentative", "score": 0.0, "tone_id": "tentative"}], "category_name": "Language Tone"}, {"category_id": "social_tone", "tones": [{"tone_name": "Openness", "score": 0.110727, "tone_id": "openness_big5"}, {"tone_name": "Conscientiousness", "score": 0.328356, "tone_id": "conscientiousness_big5"}, {"tone_name": "Extraversion", "score": 0.404247, "tone_id": "extraversion_big5"}, {"tone_name": "Agreeableness", "score": 0.568497, "tone_id": "agreeableness_big5"}, {"tone_name": "Emotional Range", "score": 0.276836, "tone_id": "emotional_range_big5"}], "category_name": "Social Tone"}], "input_from": 816}, {"input_to": 894, "text": "Who's taking you home, home, home, home.", "sentence_id": 27, "tone_categories": [{"category_id": "emotion_tone", "tones": [{"tone_name": "Anger", "score": 0.12746, "tone_id": "anger"}, {"tone_name": "Disgust", "score": 0.073118, "tone_id": "disgust"}, {"tone_name": "Fear", "score": 0.145777, "tone_id": "fear"}, {"tone_name": "Joy", "score": 0.680181, "tone_id": "joy"}, {"tone_name": "Sadness", "score": 0.070942, "tone_id": "sadness"}], "category_name": "Emotion Tone"}, {"category_id": "language_tone", "tones": [{"tone_name": "Analytical", "score": 0.0, "tone_id": "analytical"}, {"tone_name": "Confident", "score": 0.0, "tone_id": "confident"}, {"tone_name": "Tentative", "score": 0.0, "tone_id": "tentative"}], "category_name": "Language Tone"}, {"category_id": "social_tone", "tones": [{"tone_name": "Openness", "score": 0.00805, "tone_id": "openness_big5"}, {"tone_name": "Conscientiousness", "score": 0.286228, "tone_id": "conscientiousness_big5"}, {"tone_name": "Extraversion", "score": 0.553924, "tone_id": "extraversion_big5"}, {"tone_name": "Agreeableness", "score": 0.615368, "tone_id": "agreeableness_big5"}, {"tone_name": "Emotional Range", "score": 0.369658, "tone_id": "emotional_range_big5"}], "category_name": "Social Tone"}], "input_from": 854}, {"input_to": 925, "text": "And loving you so, so, so, so.", "sentence_id": 28, "tone_categories": [{"category_id": "emotion_tone", "tones": [{"tone_name": "Anger", "score": 0.044234, "tone_id": "anger"}, {"tone_name": "Disgust", "score": 0.013642, "tone_id": "disgust"}, {"tone_name": "Fear", "score": 0.025767, "tone_id": "fear"}, {"tone_name": "Joy", "score": 0.723575, "tone_id": "joy"}, {"tone_name": "Sadness", "score": 0.242875, "tone_id": "sadness"}], "category_name": "Emotion Tone"}, {"category_id": "language_tone", "tones": [{"tone_name": "Analytical", "score": 0.0, "tone_id": "analytical"}, {"tone_name": "Confident", "score": 0.0, "tone_id": "confident"}, {"tone_name": "Tentative", "score": 0.0, "tone_id": "tentative"}], "category_name": "Language Tone"}, {"category_id": "social_tone", "tones": [{"tone_name": "Openness", "score": 0.097814, "tone_id": "openness_big5"}, {"tone_name": "Conscientiousness", "score": 0.280442, "tone_id": "conscientiousness_big5"}, {"tone_name": "Extraversion", "score": 0.581671, "tone_id": "extraversion_big5"}, {"tone_name": "Agreeableness", "score": 0.634751, "tone_id": "agreeableness_big5"}, {"tone_name": "Emotional Range", "score": 0.067996, "tone_id": "emotional_range_big5"}], "category_name": "Social Tone"}], "input_from": 895}, {"input_to": 957, "text": "The way I used to love you, oh.", "sentence_id": 29, "tone_categories": [{"category_id": "emotion_tone", "tones": [{"tone_name": "Anger", "score": 0.090054, "tone_id": "anger"}, {"tone_name": "Disgust", "score": 0.037155, "tone_id": "disgust"}, {"tone_name": "Fear", "score": 0.079356, "tone_id": "fear"}, {"tone_name": "Joy", "score": 0.146338, "tone_id": "joy"}, {"tone_name": "Sadness", "score": 0.683564, "tone_id": "sadness"}], "category_name": "Emotion Tone"}, {"category_id": "language_tone", "tones": [{"tone_name": "Analytical", "score": 0.0, "tone_id": "analytical"}, {"tone_name": "Confident", "score": 0.0, "tone_id": "confident"}, {"tone_name": "Tentative", "score": 0.0, "tone_id": "tentative"}], "category_name": "Language Tone"}, {"category_id": "social_tone", "tones": [{"tone_name": "Openness", "score": 0.126115, "tone_id": "openness_big5"}, {"tone_name": "Conscientiousness", "score": 0.671193, "tone_id": "conscientiousness_big5"}, {"tone_name": "Extraversion", "score": 0.617389, "tone_id": "extraversion_big5"}, {"tone_name": "Agreeableness", "score": 0.947059, "tone_id": "agreeableness_big5"}, {"tone_name": "Emotional Range", "score": 0.790395, "tone_id": "emotional_range_big5"}], "category_name": "Social Tone"}], "input_from": 926}, {"input_to": 977, "text": "I don't wanna know.", "sentence_id": 30, "tone_categories": [{"category_id": "emotion_tone", "tones": [{"tone_name": "Anger", "score": 0.112917, "tone_id": "anger"}, {"tone_name": "Disgust", "score": 0.047376, "tone_id": "disgust"}, {"tone_name": "Fear", "score": 0.164002, "tone_id": "fear"}, {"tone_name": "Joy", "score": 0.101987, "tone_id": "joy"}, {"tone_name": "Sadness", "score": 0.662436, "tone_id": "sadness"}], "category_name": "Emotion Tone"}, {"category_id": "language_tone", "tones": [{"tone_name": "Analytical", "score": 0.0, "tone_id": "analytical"}, {"tone_name": "Confident", "score": 0.0, "tone_id": "confident"}, {"tone_name": "Tentative", "score": 0.0, "tone_id": "tentative"}], "category_name": "Language Tone"}, {"category_id": "social_tone", "tones": [{"tone_name": "Openness", "score": 0.075882, "tone_id": "openness_big5"}, {"tone_name": "Conscientiousness", "score": 0.299336, "tone_id": "conscientiousness_big5"}, {"tone_name": "Extraversion", "score": 0.37318, "tone_id": "extraversion_big5"}, {"tone_name": "Agreeableness", "score": 0.547426, "tone_id": "agreeableness_big5"}, {"tone_name": "Emotional Range", "score": 0.117378, "tone_id": "emotional_range_big5"}], "category_name": "Social Tone"}], "input_from": 958}, {"input_to": 1008, "text": "And every time I go out, yeah.", "sentence_id": 31, "tone_categories": [{"category_id": "emotion_tone", "tones": [{"tone_name": "Anger", "score": 0.199496, "tone_id": "anger"}, {"tone_name": "Disgust", "score": 0.056808, "tone_id": "disgust"}, {"tone_name": "Fear", "score": 0.21287, "tone_id": "fear"}, {"tone_name": "Joy", "score": 0.169733, "tone_id": "joy"}, {"tone_name": "Sadness", "score": 0.427999, "tone_id": "sadness"}], "category_name": "Emotion Tone"}, {"category_id": "language_tone", "tones": [{"tone_name": "Analytical", "score": 0.0, "tone_id": "analytical"}, {"tone_name": "Confident", "score": 0.92125, "tone_id": "confident"}, {"tone_name": "Tentative", "score": 0.0, "tone_id": "tentative"}], "category_name": "Language Tone"}, {"category_id": "social_tone", "tones": [{"tone_name": "Openness", "score": 0.079224, "tone_id": "openness_big5"}, {"tone_name": "Conscientiousness", "score": 0.830067, "tone_id": "conscientiousness_big5"}, {"tone_name": "Extraversion", "score": 0.567555, "tone_id": "extraversion_big5"}, {"tone_name": "Agreeableness", "score": 0.796972, "tone_id": "agreeableness_big5"}, {"tone_name": "Emotional Range", "score": 0.798638, "tone_id": "emotional_range_big5"}], "category_name": "Social Tone"}], "input_from": 978}, {"input_to": 1058, "text": "I hear it from this one, I hear it from that one.", "sentence_id": 32, "tone_categories": [{"category_id": "emotion_tone", "tones": [{"tone_name": "Anger", "score": 0.067865, "tone_id": "anger"}, {"tone_name": "Disgust", "score": 0.324429, "tone_id": "disgust"}, {"tone_name": "Fear", "score": 0.104914, "tone_id": "fear"}, {"tone_name": "Joy", "score": 0.353441, "tone_id": "joy"}, {"tone_name": "Sadness", "score": 0.234749, "tone_id": "sadness"}], "category_name": "Emotion Tone"}, {"category_id": "language_tone", "tones": [{"tone_name": "Analytical", "score": 0.0, "tone_id": "analytical"}, {"tone_name": "Confident", "score": 0.0, "tone_id": "confident"}, {"tone_name": "Tentative", "score": 0.0, "tone_id": "tentative"}], "category_name": "Language Tone"}, {"category_id": "social_tone", "tones": [{"tone_name": "Openness", "score": 0.549451, "tone_id": "openness_big5"}, {"tone_name": "Conscientiousness", "score": 0.402721, "tone_id": "conscientiousness_big5"}, {"tone_name": "Extraversion", "score": 0.006797, "tone_id": "extraversion_big5"}, {"tone_name": "Agreeableness", "score": 0.90433, "tone_id": "agreeableness_big5"}, {"tone_name": "Emotional Range", "score": 0.200716, "tone_id": "emotional_range_big5"}], "category_name": "Social Tone"}], "input_from": 1009}, {"input_to": 1084, "text": "That you got someone new.", "sentence_id": 33, "tone_categories": [{"category_id": "emotion_tone", "tones": [{"tone_name": "Anger", "score": 0.21823, "tone_id": "anger"}, {"tone_name": "Disgust", "score": 0.069248, "tone_id": "disgust"}, {"tone_name": "Fear", "score": 0.102375, "tone_id": "fear"}, {"tone_name": "Joy", "score": 0.467778, "tone_id": "joy"}, {"tone_name": "Sadness", "score": 0.203416, "tone_id": "sadness"}], "category_name": "Emotion Tone"}, {"category_id": "language_tone", "tones": [{"tone_name": "Analytical", "score": 0.0, "tone_id": "analytical"}, {"tone_name": "Confident", "score": 0.0, "tone_id": "confident"}, {"tone_name": "Tentative", "score": 0.968123, "tone_id": "tentative"}], "category_name": "Language Tone"}, {"category_id": "social_tone", "tones": [{"tone_name": "Openness", "score": 0.558826, "tone_id": "openness_big5"}, {"tone_name": "Conscientiousness", "score": 0.744514, "tone_id": "conscientiousness_big5"}, {"tone_name": "Extraversion", "score": 0.824509, "tone_id": "extraversion_big5"}, {"tone_name": "Agreeableness", "score": 0.841095, "tone_id": "agreeableness_big5"}, {"tone_name": "Emotional Range", "score": 0.710068, "tone_id": "emotional_range_big5"}], "category_name": "Social Tone"}], "input_from": 1059}, {"input_to": 1118, "text": "Yeah, I see but don't believe it.", "sentence_id": 34, "tone_categories": [{"category_id": "emotion_tone", "tones": [{"tone_name": "Anger", "score": 0.04395, "tone_id": "anger"}, {"tone_name": "Disgust", "score": 0.030843, "tone_id": "disgust"}, {"tone_name": "Fear", "score": 0.041128, "tone_id": "fear"}, {"tone_name": "Joy", "score": 0.190328, "tone_id": "joy"}, {"tone_name": "Sadness", "score": 0.769151, "tone_id": "sadness"}], "category_name": "Emotion Tone"}, {"category_id": "language_tone", "tones": [{"tone_name": "Analytical", "score": 0.0, "tone_id": "analytical"}, {"tone_name": "Confident", "score": 0.0, "tone_id": "confident"}, {"tone_name": "Tentative", "score": 0.91961, "tone_id": "tentative"}], "category_name": "Language Tone"}, {"category_id": "social_tone", "tones": [{"tone_name": "Openness", "score": 0.04543, "tone_id": "openness_big5"}, {"tone_name": "Conscientiousness", "score": 0.489269, "tone_id": "conscientiousness_big5"}, {"tone_name": "Extraversion", "score": 0.033299, "tone_id": "extraversion_big5"}, {"tone_name": "Agreeableness", "score": 0.600211, "tone_id": "agreeableness_big5"}, {"tone_name": "Emotional Range", "score": 0.176235, "tone_id": "emotional_range_big5"}], "category_name": "Social Tone"}], "input_from": 1085}, {"input_to": 1158, "text": "Even in my head you're still in my bed.", "sentence_id": 35, "tone_categories": [{"category_id": "emotion_tone", "tones": [{"tone_name": "Anger", "score": 0.177952, "tone_id": "anger"}, {"tone_name": "Disgust", "score": 0.16709, "tone_id": "disgust"}, {"tone_name": "Fear", "score": 0.056298, "tone_id": "fear"}, {"tone_name": "Joy", "score": 0.209507, "tone_id": "joy"}, {"tone_name": "Sadness", "score": 0.463315, "tone_id": "sadness"}], "category_name": "Emotion Tone"}, {"category_id": "language_tone", "tones": [{"tone_name": "Analytical", "score": 0.0, "tone_id": "analytical"}, {"tone_name": "Confident", "score": 0.0, "tone_id": "confident"}, {"tone_name": "Tentative", "score": 0.856622, "tone_id": "tentative"}], "category_name": "Language Tone"}, {"category_id": "social_tone", "tones": [{"tone_name": "Openness", "score": 0.047669, "tone_id": "openness_big5"}, {"tone_name": "Conscientiousness", "score": 0.152982, "tone_id": "conscientiousness_big5"}, {"tone_name": "Extraversion", "score": 0.491853, "tone_id": "extraversion_big5"}, {"tone_name": "Agreeableness", "score": 0.485745, "tone_id": "agreeableness_big5"}, {"tone_name": "Emotional Range", "score": 0.033686, "tone_id": "emotional_range_big5"}], "category_name": "Social Tone"}], "input_from": 1119}, {"input_to": 1181, "text": "Maybe I'm just a fool.", "sentence_id": 36, "tone_categories": [{"category_id": "emotion_tone", "tones": [{"tone_name": "Anger", "score": 0.108155, "tone_id": "anger"}, {"tone_name": "Disgust", "score": 0.154673, "tone_id": "disgust"}, {"tone_name": "Fear", "score": 0.079928, "tone_id": "fear"}, {"tone_name": "Joy", "score": 0.19307, "tone_id": "joy"}, {"tone_name": "Sadness", "score": 0.568393, "tone_id": "sadness"}], "category_name": "Emotion Tone"}, {"category_id": "language_tone", "tones": [{"tone_name": "Analytical", "score": 0.0, "tone_id": "analytical"}, {"tone_name": "Confident", "score": 0.0, "tone_id": "confident"}, {"tone_name": "Tentative", "score": 0.997314, "tone_id": "tentative"}], "category_name": "Language Tone"}, {"category_id": "social_tone", "tones": [{"tone_name": "Openness", "score": 0.395207, "tone_id": "openness_big5"}, {"tone_name": "Conscientiousness", "score": 0.127276, "tone_id": "conscientiousness_big5"}, {"tone_name": "Extraversion", "score": 0.178045, "tone_id": "extraversion_big5"}, {"tone_name": "Agreeableness", "score": 0.511807, "tone_id": "agreeableness_big5"}, {"tone_name": "Emotional Range", "score": 0.095429, "tone_id": "emotional_range_big5"}], "category_name": "Social Tone"}], "input_from": 1159}, {"input_to": 1201, "text": "Do you think of me?", "sentence_id": 37, "tone_categories": [{"category_id": "emotion_tone", "tones": [{"tone_name": "Anger", "score": 0.095417, "tone_id": "anger"}, {"tone_name": "Disgust", "score": 0.072352, "tone_id": "disgust"}, {"tone_name": "Fear", "score": 0.317368, "tone_id": "fear"}, {"tone_name": "Joy", "score": 0.314012, "tone_id": "joy"}, {"tone_name": "Sadness", "score": 0.295947, "tone_id": "sadness"}], "category_name": "Emotion Tone"}, {"category_id": "language_tone", "tones": [{"tone_name": "Analytical", "score": 0.994057, "tone_id": "analytical"}, {"tone_name": "Confident", "score": 0.0, "tone_id": "confident"}, {"tone_name": "Tentative", "score": 0.0, "tone_id": "tentative"}], "category_name": "Language Tone"}, {"category_id": "social_tone", "tones": [{"tone_name": "Openness", "score": 0.453564, "tone_id": "openness_big5"}, {"tone_name": "Conscientiousness", "score": 0.457911, "tone_id": "conscientiousness_big5"}, {"tone_name": "Extraversion", "score": 0.538857, "tone_id": "extraversion_big5"}, {"tone_name": "Agreeableness", "score": 0.666586, "tone_id": "agreeableness_big5"}, {"tone_name": "Emotional Range", "score": 0.139579, "tone_id": "emotional_range_big5"}], "category_name": "Social Tone"}], "input_from": 1182}, {"input_to": 1225, "text": "Of what we used to be?.", "sentence_id": 38, "tone_categories": [{"category_id": "emotion_tone", "tones": [{"tone_name": "Anger", "score": 0.028724, "tone_id": "anger"}, {"tone_name": "Disgust", "score": 0.108879, "tone_id": "disgust"}, {"tone_name": "Fear", "score": 0.226639, "tone_id": "fear"}, {"tone_name": "Joy", "score": 0.12236, "tone_id": "joy"}, {"tone_name": "Sadness", "score": 0.586047, "tone_id": "sadness"}], "category_name": "Emotion Tone"}, {"category_id": "language_tone", "tones": [{"tone_name": "Analytical", "score": 0.0, "tone_id": "analytical"}, {"tone_name": "Confident", "score": 0.0, "tone_id": "confident"}, {"tone_name": "Tentative", "score": 0.0, "tone_id": "tentative"}], "category_name": "Language Tone"}, {"category_id": "social_tone", "tones": [{"tone_name": "Openness", "score": 0.473529, "tone_id": "openness_big5"}, {"tone_name": "Conscientiousness", "score": 0.650253, "tone_id": "conscientiousness_big5"}, {"tone_name": "Extraversion", "score": 0.204638, "tone_id": "extraversion_big5"}, {"tone_name": "Agreeableness", "score": 0.663215, "tone_id": "agreeableness_big5"}, {"tone_name": "Emotional Range", "score": 0.710573, "tone_id": "emotional_range_big5"}], "category_name": "Social Tone"}], "input_from": 1202}, {"input_to": 1326, "text": "Is it better now that I'm not around?.\nMy friends are actin' strange, they don't bring up your name.", "sentence_id": 39, "tone_categories": [{"category_id": "emotion_tone", "tones": [{"tone_name": "Anger", "score": 0.111754, "tone_id": "anger"}, {"tone_name": "Disgust", "score": 0.031774, "tone_id": "disgust"}, {"tone_name": "Fear", "score": 0.142577, "tone_id": "fear"}, {"tone_name": "Joy", "score": 0.032844, "tone_id": "joy"}, {"tone_name": "Sadness", "score": 0.74882, "tone_id": "sadness"}], "category_name": "Emotion Tone"}, {"category_id": "language_tone", "tones": [{"tone_name": "Analytical", "score": 0.620279, "tone_id": "analytical"}, {"tone_name": "Confident", "score": 0.0, "tone_id": "confident"}, {"tone_name": "Tentative", "score": 0.5538, "tone_id": "tentative"}], "category_name": "Language Tone"}, {"category_id": "social_tone", "tones": [{"tone_name": "Openness", "score": 0.712453, "tone_id": "openness_big5"}, {"tone_name": "Conscientiousness", "score": 0.548809, "tone_id": "conscientiousness_big5"}, {"tone_name": "Extraversion", "score": 0.522369, "tone_id": "extraversion_big5"}, {"tone_name": "Agreeableness", "score": 0.163408, "tone_id": "agreeableness_big5"}, {"tone_name": "Emotional Range", "score": 0.178076, "tone_id": "emotional_range_big5"}], "category_name": "Social Tone"}], "input_from": 1226}, {"input_to": 1346, "text": "Are you happy now?.", "sentence_id": 40, "tone_categories": [{"category_id": "emotion_tone", "tones": [{"tone_name": "Anger", "score": 0.011507, "tone_id": "anger"}, {"tone_name": "Disgust", "score": 0.011595, "tone_id": "disgust"}, {"tone_name": "Fear", "score": 0.018799, "tone_id": "fear"}, {"tone_name": "Joy", "score": 0.888221, "tone_id": "joy"}, {"tone_name": "Sadness", "score": 0.078883, "tone_id": "sadness"}], "category_name": "Emotion Tone"}, {"category_id": "language_tone", "tones": [{"tone_name": "Analytical", "score": 0.0, "tone_id": "analytical"}, {"tone_name": "Confident", "score": 0.0, "tone_id": "confident"}, {"tone_name": "Tentative", "score": 0.0, "tone_id": "tentative"}], "category_name": "Language Tone"}, {"category_id": "social_tone", "tones": [{"tone_name": "Openness", "score": 0.18025, "tone_id": "openness_big5"}, {"tone_name": "Conscientiousness", "score": 0.344574, "tone_id": "conscientiousness_big5"}, {"tone_name": "Extraversion", "score": 0.591315, "tone_id": "extraversion_big5"}, {"tone_name": "Agreeableness", "score": 0.637124, "tone_id": "agreeableness_big5"}, {"tone_name": "Emotional Range", "score": 0.4858, "tone_id": "emotional_range_big5"}], "category_name": "Social Tone"}], "input_from": 1327}, {"input_to": 1366, "text": "Are you happy now?.", "sentence_id": 41, "tone_categories": [{"category_id": "emotion_tone", "tones": [{"tone_name": "Anger", "score": 0.011507, "tone_id": "anger"}, {"tone_name": "Disgust", "score": 0.011595, "tone_id": "disgust"}, {"tone_name": "Fear", "score": 0.018799, "tone_id": "fear"}, {"tone_name": "Joy", "score": 0.888221, "tone_id": "joy"}, {"tone_name": "Sadness", "score": 0.078883, "tone_id": "sadness"}], "category_name": "Emotion Tone"}, {"category_id": "language_tone", "tones": [{"tone_name": "Analytical", "score": 0.0, "tone_id": "analytical"}, {"tone_name": "Confident", "score": 0.0, "tone_id": "confident"}, {"tone_name": "Tentative", "score": 0.0, "tone_id": "tentative"}], "category_name": "Language Tone"}, {"category_id": "social_tone", "tones": [{"tone_name": "Openness", "score": 0.18025, "tone_id": "openness_big5"}, {"tone_name": "Conscientiousness", "score": 0.344574, "tone_id": "conscientiousness_big5"}, {"tone_name": "Extraversion", "score": 0.591315, "tone_id": "extraversion_big5"}, {"tone_name": "Agreeableness", "score": 0.637124, "tone_id": "agreeableness_big5"}, {"tone_name": "Emotional Range", "score": 0.4858, "tone_id": "emotional_range_big5"}], "category_name": "Social Tone"}], "input_from": 1347}, {"input_to": 1404, "text": "I don't wanna know, know, know, know.", "sentence_id": 42, "tone_categories": [{"category_id": "emotion_tone", "tones": [{"tone_name": "Anger", "score": 0.08893, "tone_id": "anger"}, {"tone_name": "Disgust", "score": 0.029665, "tone_id": "disgust"}, {"tone_name": "Fear", "score": 0.128077, "tone_id": "fear"}, {"tone_name": "Joy", "score": 0.122079, "tone_id": "joy"}, {"tone_name": "Sadness", "score": 0.719966, "tone_id": "sadness"}], "category_name": "Emotion Tone"}, {"category_id": "language_tone", "tones": [{"tone_name": "Analytical", "score": 0.93884, "tone_id": "analytical"}, {"tone_name": "Confident", "score": 0.0, "tone_id": "confident"}, {"tone_name": "Tentative", "score": 0.0, "tone_id": "tentative"}], "category_name": "Language Tone"}, {"category_id": "social_tone", "tones": [{"tone_name": "Openness", "score": 0.110727, "tone_id": "openness_big5"}, {"tone_name": "Conscientiousness", "score": 0.328356, "tone_id": "conscientiousness_big5"}, {"tone_name": "Extraversion", "score": 0.404247, "tone_id": "extraversion_big5"}, {"tone_name": "Agreeableness", "score": 0.568497, "tone_id": "agreeableness_big5"}, {"tone_name": "Emotional Range", "score": 0.276836, "tone_id": "emotional_range_big5"}], "category_name": "Social Tone"}], "input_from": 1367}, {"input_to": 1445, "text": "Who's taking you home, home, home, home.", "sentence_id": 43, "tone_categories": [{"category_id": "emotion_tone", "tones": [{"tone_name": "Anger", "score": 0.12746, "tone_id": "anger"}, {"tone_name": "Disgust", "score": 0.073118, "tone_id": "disgust"}, {"tone_name": "Fear", "score": 0.145777, "tone_id": "fear"}, {"tone_name": "Joy", "score": 0.680181, "tone_id": "joy"}, {"tone_name": "Sadness", "score": 0.070942, "tone_id": "sadness"}], "category_name": "Emotion Tone"}, {"category_id": "language_tone", "tones": [{"tone_name": "Analytical", "score": 0.0, "tone_id": "analytical"}, {"tone_name": "Confident", "score": 0.0, "tone_id": "confident"}, {"tone_name": "Tentative", "score": 0.0, "tone_id": "tentative"}], "category_name": "Language Tone"}, {"category_id": "social_tone", "tones": [{"tone_name": "Openness", "score": 0.00805, "tone_id": "openness_big5"}, {"tone_name": "Conscientiousness", "score": 0.286228, "tone_id": "conscientiousness_big5"}, {"tone_name": "Extraversion", "score": 0.553924, "tone_id": "extraversion_big5"}, {"tone_name": "Agreeableness", "score": 0.615368, "tone_id": "agreeableness_big5"}, {"tone_name": "Emotional Range", "score": 0.369658, "tone_id": "emotional_range_big5"}], "category_name": "Social Tone"}], "input_from": 1405}, {"input_to": 1476, "text": "And loving you so, so, so, so.", "sentence_id": 44, "tone_categories": [{"category_id": "emotion_tone", "tones": [{"tone_name": "Anger", "score": 0.044234, "tone_id": "anger"}, {"tone_name": "Disgust", "score": 0.013642, "tone_id": "disgust"}, {"tone_name": "Fear", "score": 0.025767, "tone_id": "fear"}, {"tone_name": "Joy", "score": 0.723575, "tone_id": "joy"}, {"tone_name": "Sadness", "score": 0.242875, "tone_id": "sadness"}], "category_name": "Emotion Tone"}, {"category_id": "language_tone", "tones": [{"tone_name": "Analytical", "score": 0.0, "tone_id": "analytical"}, {"tone_name": "Confident", "score": 0.0, "tone_id": "confident"}, {"tone_name": "Tentative", "score": 0.0, "tone_id": "tentative"}], "category_name": "Language Tone"}, {"category_id": "social_tone", "tones": [{"tone_name": "Openness", "score": 0.097814, "tone_id": "openness_big5"}, {"tone_name": "Conscientiousness", "score": 0.280442, "tone_id": "conscientiousness_big5"}, {"tone_name": "Extraversion", "score": 0.581671, "tone_id": "extraversion_big5"}, {"tone_name": "Agreeableness", "score": 0.634751, "tone_id": "agreeableness_big5"}, {"tone_name": "Emotional Range", "score": 0.067996, "tone_id": "emotional_range_big5"}], "category_name": "Social Tone"}], "input_from": 1446}, {"input_to": 1508, "text": "The way I used to love you, no.", "sentence_id": 45, "tone_categories": [{"category_id": "emotion_tone", "tones": [{"tone_name": "Anger", "score": 0.098945, "tone_id": "anger"}, {"tone_name": "Disgust", "score": 0.053495, "tone_id": "disgust"}, {"tone_name": "Fear", "score": 0.077129, "tone_id": "fear"}, {"tone_name": "Joy", "score": 0.097725, "tone_id": "joy"}, {"tone_name": "Sadness", "score": 0.726223, "tone_id": "sadness"}], "category_name": "Emotion Tone"}, {"category_id": "language_tone", "tones": [{"tone_name": "Analytical", "score": 0.116314, "tone_id": "analytical"}, {"tone_name": "Confident", "score": 0.0, "tone_id": "confident"}, {"tone_name": "Tentative", "score": 0.0, "tone_id": "tentative"}], "category_name": "Language Tone"}, {"category_id": "social_tone", "tones": [{"tone_name": "Openness", "score": 0.11046, "tone_id": "openness_big5"}, {"tone_name": "Conscientiousness", "score": 0.550654, "tone_id": "conscientiousness_big5"}, {"tone_name": "Extraversion", "score": 0.616951, "tone_id": "extraversion_big5"}, {"tone_name": "Agreeableness", "score": 0.74965, "tone_id": "agreeableness_big5"}, {"tone_name": "Emotional Range", "score": 0.823096, "tone_id": "emotional_range_big5"}], "category_name": "Social Tone"}], "input_from": 1477}, {"input_to": 1546, "text": "I don't wanna know, know, know, know.", "sentence_id": 46, "tone_categories": [{"category_id": "emotion_tone", "tones": [{"tone_name": "Anger", "score": 0.08893, "tone_id": "anger"}, {"tone_name": "Disgust", "score": 0.029665, "tone_id": "disgust"}, {"tone_name": "Fear", "score": 0.128077, "tone_id": "fear"}, {"tone_name": "Joy", "score": 0.122079, "tone_id": "joy"}, {"tone_name": "Sadness", "score": 0.719966, "tone_id": "sadness"}], "category_name": "Emotion Tone"}, {"category_id": "language_tone", "tones": [{"tone_name": "Analytical", "score": 0.93884, "tone_id": "analytical"}, {"tone_name": "Confident", "score": 0.0, "tone_id": "confident"}, {"tone_name": "Tentative", "score": 0.0, "tone_id": "tentative"}], "category_name": "Language Tone"}, {"category_id": "social_tone", "tones": [{"tone_name": "Openness", "score": 0.110727, "tone_id": "openness_big5"}, {"tone_name": "Conscientiousness", "score": 0.328356, "tone_id": "conscientiousness_big5"}, {"tone_name": "Extraversion", "score": 0.404247, "tone_id": "extraversion_big5"}, {"tone_name": "Agreeableness", "score": 0.568497, "tone_id": "agreeableness_big5"}, {"tone_name": "Emotional Range", "score": 0.276836, "tone_id": "emotional_range_big5"}], "category_name": "Social Tone"}], "input_from": 1509}, {"input_to": 1587, "text": "Who's taking you home, home, home, home.", "sentence_id": 47, "tone_categories": [{"category_id": "emotion_tone", "tones": [{"tone_name": "Anger", "score": 0.12746, "tone_id": "anger"}, {"tone_name": "Disgust", "score": 0.073118, "tone_id": "disgust"}, {"tone_name": "Fear", "score": 0.145777, "tone_id": "fear"}, {"tone_name": "Joy", "score": 0.680181, "tone_id": "joy"}, {"tone_name": "Sadness", "score": 0.070942, "tone_id": "sadness"}], "category_name": "Emotion Tone"}, {"category_id": "language_tone", "tones": [{"tone_name": "Analytical", "score": 0.0, "tone_id": "analytical"}, {"tone_name": "Confident", "score": 0.0, "tone_id": "confident"}, {"tone_name": "Tentative", "score": 0.0, "tone_id": "tentative"}], "category_name": "Language Tone"}, {"category_id": "social_tone", "tones": [{"tone_name": "Openness", "score": 0.00805, "tone_id": "openness_big5"}, {"tone_name": "Conscientiousness", "score": 0.286228, "tone_id": "conscientiousness_big5"}, {"tone_name": "Extraversion", "score": 0.553924, "tone_id": "extraversion_big5"}, {"tone_name": "Agreeableness", "score": 0.615368, "tone_id": "agreeableness_big5"}, {"tone_name": "Emotional Range", "score": 0.369658, "tone_id": "emotional_range_big5"}], "category_name": "Social Tone"}], "input_from": 1547}, {"input_to": 1618, "text": "And loving you so, so, so, so.", "sentence_id": 48, "tone_categories": [{"category_id": "emotion_tone", "tones": [{"tone_name": "Anger", "score": 0.044234, "tone_id": "anger"}, {"tone_name": "Disgust", "score": 0.013642, "tone_id": "disgust"}, {"tone_name": "Fear", "score": 0.025767, "tone_id": "fear"}, {"tone_name": "Joy", "score": 0.723575, "tone_id": "joy"}, {"tone_name": "Sadness", "score": 0.242875, "tone_id": "sadness"}], "category_name": "Emotion Tone"}, {"category_id": "language_tone", "tones": [{"tone_name": "Analytical", "score": 0.0, "tone_id": "analytical"}, {"tone_name": "Confident", "score": 0.0, "tone_id": "confident"}, {"tone_name": "Tentative", "score": 0.0, "tone_id": "tentative"}], "category_name": "Language Tone"}, {"category_id": "social_tone", "tones": [{"tone_name": "Openness", "score": 0.097814, "tone_id": "openness_big5"}, {"tone_name": "Conscientiousness", "score": 0.280442, "tone_id": "conscientiousness_big5"}, {"tone_name": "Extraversion", "score": 0.581671, "tone_id": "extraversion_big5"}, {"tone_name": "Agreeableness", "score": 0.634751, "tone_id": "agreeableness_big5"}, {"tone_name": "Emotional Range", "score": 0.067996, "tone_id": "emotional_range_big5"}], "category_name": "Social Tone"}], "input_from": 1588}, {"input_to": 1650, "text": "The way I used to love you, oh.", "sentence_id": 49, "tone_categories": [{"category_id": "emotion_tone", "tones": [{"tone_name": "Anger", "score": 0.090054, "tone_id": "anger"}, {"tone_name": "Disgust", "score": 0.037155, "tone_id": "disgust"}, {"tone_name": "Fear", "score": 0.079356, "tone_id": "fear"}, {"tone_name": "Joy", "score": 0.146338, "tone_id": "joy"}, {"tone_name": "Sadness", "score": 0.683564, "tone_id": "sadness"}], "category_name": "Emotion Tone"}, {"category_id": "language_tone", "tones": [{"tone_name": "Analytical", "score": 0.0, "tone_id": "analytical"}, {"tone_name": "Confident", "score": 0.0, "tone_id": "confident"}, {"tone_name": "Tentative", "score": 0.0, "tone_id": "tentative"}], "category_name": "Language Tone"}, {"category_id": "social_tone", "tones": [{"tone_name": "Openness", "score": 0.126115, "tone_id": "openness_big5"}, {"tone_name": "Conscientiousness", "score": 0.671193, "tone_id": "conscientiousness_big5"}, {"tone_name": "Extraversion", "score": 0.617389, "tone_id": "extraversion_big5"}, {"tone_name": "Agreeableness", "score": 0.947059, "tone_id": "agreeableness_big5"}, {"tone_name": "Emotional Range", "score": 0.790395, "tone_id": "emotional_range_big5"}], "category_name": "Social Tone"}], "input_from": 1619}, {"input_to": 1670, "text": "I don't wanna know.", "sentence_id": 50, "tone_categories": [{"category_id": "emotion_tone", "tones": [{"tone_name": "Anger", "score": 0.112917, "tone_id": "anger"}, {"tone_name": "Disgust", "score": 0.047376, "tone_id": "disgust"}, {"tone_name": "Fear", "score": 0.164002, "tone_id": "fear"}, {"tone_name": "Joy", "score": 0.101987, "tone_id": "joy"}, {"tone_name": "Sadness", "score": 0.662436, "tone_id": "sadness"}], "category_name": "Emotion Tone"}, {"category_id": "language_tone", "tones": [{"tone_name": "Analytical", "score": 0.0, "tone_id": "analytical"}, {"tone_name": "Confident", "score": 0.0, "tone_id": "confident"}, {"tone_name": "Tentative", "score": 0.0, "tone_id": "tentative"}], "category_name": "Language Tone"}, {"category_id": "social_tone", "tones": [{"tone_name": "Openness", "score": 0.075882, "tone_id": "openness_big5"}, {"tone_name": "Conscientiousness", "score": 0.299336, "tone_id": "conscientiousness_big5"}, {"tone_name": "Extraversion", "score": 0.37318, "tone_id": "extraversion_big5"}, {"tone_name": "Agreeableness", "score": 0.547426, "tone_id": "agreeableness_big5"}, {"tone_name": "Emotional Range", "score": 0.117378, "tone_id": "emotional_range_big5"}], "category_name": "Social Tone"}], "input_from": 1651}, {"input_to": 1680, "text": "(Oh hey).", "sentence_id": 51, "tone_categories": [], "input_from": 1671}, {"input_to": 1703, "text": "No more \u201cplease stop\u201d.", "sentence_id": 52, "tone_categories": [{"category_id": "emotion_tone", "tones": [{"tone_name": "Anger", "score": 0.158643, "tone_id": "anger"}, {"tone_name": "Disgust", "score": 0.098825, "tone_id": "disgust"}, {"tone_name": "Fear", "score": 0.364039, "tone_id": "fear"}, {"tone_name": "Joy", "score": 0.206828, "tone_id": "joy"}, {"tone_name": "Sadness", "score": 0.301385, "tone_id": "sadness"}], "category_name": "Emotion Tone"}, {"category_id": "language_tone", "tones": [{"tone_name": "Analytical", "score": 0.0, "tone_id": "analytical"}, {"tone_name": "Confident", "score": 0.0, "tone_id": "confident"}, {"tone_name": "Tentative", "score": 0.0, "tone_id": "tentative"}], "category_name": "Language Tone"}, {"category_id": "social_tone", "tones": [{"tone_name": "Openness", "score": 0.203728, "tone_id": "openness_big5"}, {"tone_name": "Conscientiousness", "score": 0.290009, "tone_id": "conscientiousness_big5"}, {"tone_name": "Extraversion", "score": 0.544873, "tone_id": "extraversion_big5"}, {"tone_name": "Agreeableness", "score": 0.591646, "tone_id": "agreeableness_big5"}, {"tone_name": "Emotional Range", "score": 0.107912, "tone_id": "emotional_range_big5"}], "category_name": "Social Tone"}], "input_from": 1681}, {"input_to": 1741, "text": "No more hashtag boo'd up screenshots.", "sentence_id": 53, "tone_categories": [{"category_id": "emotion_tone", "tones": [{"tone_name": "Anger", "score": 0.033057, "tone_id": "anger"}, {"tone_name": "Disgust", "score": 0.067841, "tone_id": "disgust"}, {"tone_name": "Fear", "score": 0.137823, "tone_id": "fear"}, {"tone_name": "Joy", "score": 0.138515, "tone_id": "joy"}, {"tone_name": "Sadness", "score": 0.696243, "tone_id": "sadness"}], "category_name": "Emotion Tone"}, {"category_id": "language_tone", "tones": [{"tone_name": "Analytical", "score": 0.0, "tone_id": "analytical"}, {"tone_name": "Confident", "score": 0.0, "tone_id": "confident"}, {"tone_name": "Tentative", "score": 0.0, "tone_id": "tentative"}], "category_name": "Language Tone"}, {"category_id": "social_tone", "tones": [{"tone_name": "Openness", "score": 0.224811, "tone_id": "openness_big5"}, {"tone_name": "Conscientiousness", "score": 0.158453, "tone_id": "conscientiousness_big5"}, {"tone_name": "Extraversion", "score": 0.351706, "tone_id": "extraversion_big5"}, {"tone_name": "Agreeableness", "score": 0.160231, "tone_id": "agreeableness_big5"}, {"tone_name": "Emotional Range", "score": 0.179489, "tone_id": "emotional_range_big5"}], "category_name": "Social Tone"}], "input_from": 1704}, {"input_to": 1790, "text": "No more tryin' make me jealous on your birthday.", "sentence_id": 54, "tone_categories": [{"category_id": "emotion_tone", "tones": [{"tone_name": "Anger", "score": 0.046624, "tone_id": "anger"}, {"tone_name": "Disgust", "score": 0.058887, "tone_id": "disgust"}, {"tone_name": "Fear", "score": 0.008404, "tone_id": "fear"}, {"tone_name": "Joy", "score": 0.730448, "tone_id": "joy"}, {"tone_name": "Sadness", "score": 0.237701, "tone_id": "sadness"}], "category_name": "Emotion Tone"}, {"category_id": "language_tone", "tones": [{"tone_name": "Analytical", "score": 0.0, "tone_id": "analytical"}, {"tone_name": "Confident", "score": 0.0, "tone_id": "confident"}, {"tone_name": "Tentative", "score": 0.0, "tone_id": "tentative"}], "category_name": "Language Tone"}, {"category_id": "social_tone", "tones": [{"tone_name": "Openness", "score": 0.011774, "tone_id": "openness_big5"}, {"tone_name": "Conscientiousness", "score": 0.280887, "tone_id": "conscientiousness_big5"}, {"tone_name": "Extraversion", "score": 0.986732, "tone_id": "extraversion_big5"}, {"tone_name": "Agreeableness", "score": 0.599445, "tone_id": "agreeableness_big5"}, {"tone_name": "Emotional Range", "score": 0.301648, "tone_id": "emotional_range_big5"}], "category_name": "Social Tone"}], "input_from": 1742}, {"input_to": 1848, "text": "You know just how I made you better on your birthday, oh.", "sentence_id": 55, "tone_categories": [{"category_id": "emotion_tone", "tones": [{"tone_name": "Anger", "score": 0.022962, "tone_id": "anger"}, {"tone_name": "Disgust", "score": 0.026961, "tone_id": "disgust"}, {"tone_name": "Fear", "score": 0.041256, "tone_id": "fear"}, {"tone_name": "Joy", "score": 0.863815, "tone_id": "joy"}, {"tone_name": "Sadness", "score": 0.082085, "tone_id": "sadness"}], "category_name": "Emotion Tone"}, {"category_id": "language_tone", "tones": [{"tone_name": "Analytical", "score": 0.0, "tone_id": "analytical"}, {"tone_name": "Confident", "score": 0.0, "tone_id": "confident"}, {"tone_name": "Tentative", "score": 0.75152, "tone_id": "tentative"}], "category_name": "Language Tone"}, {"category_id": "social_tone", "tones": [{"tone_name": "Openness", "score": 0.053615, "tone_id": "openness_big5"}, {"tone_name": "Conscientiousness", "score": 0.948913, "tone_id": "conscientiousness_big5"}, {"tone_name": "Extraversion", "score": 0.93711, "tone_id": "extraversion_big5"}, {"tone_name": "Agreeableness", "score": 0.980364, "tone_id": "agreeableness_big5"}, {"tone_name": "Emotional Range", "score": 0.951614, "tone_id": "emotional_range_big5"}], "category_name": "Social Tone"}], "input_from": 1791}, {"input_to": 1898, "text": "Do he do you like this, do he woo you like this?.", "sentence_id": 56, "tone_categories": [{"category_id": "emotion_tone", "tones": [{"tone_name": "Anger", "score": 0.145208, "tone_id": "anger"}, {"tone_name": "Disgust", "score": 0.315619, "tone_id": "disgust"}, {"tone_name": "Fear", "score": 0.203986, "tone_id": "fear"}, {"tone_name": "Joy", "score": 0.295041, "tone_id": "joy"}, {"tone_name": "Sadness", "score": 0.118517, "tone_id": "sadness"}], "category_name": "Emotion Tone"}, {"category_id": "language_tone", "tones": [{"tone_name": "Analytical", "score": 0.0, "tone_id": "analytical"}, {"tone_name": "Confident", "score": 0.0, "tone_id": "confident"}, {"tone_name": "Tentative", "score": 0.75152, "tone_id": "tentative"}], "category_name": "Language Tone"}, {"category_id": "social_tone", "tones": [{"tone_name": "Openness", "score": 0.053126, "tone_id": "openness_big5"}, {"tone_name": "Conscientiousness", "score": 0.720615, "tone_id": "conscientiousness_big5"}, {"tone_name": "Extraversion", "score": 0.358315, "tone_id": "extraversion_big5"}, {"tone_name": "Agreeableness", "score": 0.682487, "tone_id": "agreeableness_big5"}, {"tone_name": "Emotional Range", "score": 0.771557, "tone_id": "emotional_range_big5"}], "category_name": "Social Tone"}], "input_from": 1849}, {"input_to": 1954, "text": "Do he lay it down for you, touch your poona like this?.", "sentence_id": 57, "tone_categories": [{"category_id": "emotion_tone", "tones": [{"tone_name": "Anger", "score": 0.061479, "tone_id": "anger"}, {"tone_name": "Disgust", "score": 0.493233, "tone_id": "disgust"}, {"tone_name": "Fear", "score": 0.051909, "tone_id": "fear"}, {"tone_name": "Joy", "score": 0.361575, "tone_id": "joy"}, {"tone_name": "Sadness", "score": 0.123895, "tone_id": "sadness"}], "category_name": "Emotion Tone"}, {"category_id": "language_tone", "tones": [{"tone_name": "Analytical", "score": 0.0, "tone_id": "analytical"}, {"tone_name": "Confident", "score": 0.0, "tone_id": "confident"}, {"tone_name": "Tentative", "score": 0.401017, "tone_id": "tentative"}], "category_name": "Language Tone"}, {"category_id": "social_tone", "tones": [{"tone_name": "Openness", "score": 0.174152, "tone_id": "openness_big5"}, {"tone_name": "Conscientiousness", "score": 0.921982, "tone_id": "conscientiousness_big5"}, {"tone_name": "Extraversion", "score": 0.616168, "tone_id": "extraversion_big5"}, {"tone_name": "Agreeableness", "score": 0.596278, "tone_id": "agreeableness_big5"}, {"tone_name": "Emotional Range", "score": 0.826883, "tone_id": "emotional_range_big5"}], "category_name": "Social Tone"}], "input_from": 1899}, {"input_to": 2002, "text": "Matter fact, never mind, we'll let the past be.", "sentence_id": 58, "tone_categories": [{"category_id": "emotion_tone", "tones": [{"tone_name": "Anger", "score": 0.082101, "tone_id": "anger"}, {"tone_name": "Disgust", "score": 0.038874, "tone_id": "disgust"}, {"tone_name": "Fear", "score": 0.327101, "tone_id": "fear"}, {"tone_name": "Joy", "score": 0.231435, "tone_id": "joy"}, {"tone_name": "Sadness", "score": 0.390496, "tone_id": "sadness"}], "category_name": "Emotion Tone"}, {"category_id": "language_tone", "tones": [{"tone_name": "Analytical", "score": 0.924064, "tone_id": "analytical"}, {"tone_name": "Confident", "score": 0.0, "tone_id": "confident"}, {"tone_name": "Tentative", "score": 0.094731, "tone_id": "tentative"}], "category_name": "Language Tone"}, {"category_id": "social_tone", "tones": [{"tone_name": "Openness", "score": 0.107258, "tone_id": "openness_big5"}, {"tone_name": "Conscientiousness", "score": 0.47367, "tone_id": "conscientiousness_big5"}, {"tone_name": "Extraversion", "score": 0.014194, "tone_id": "extraversion_big5"}, {"tone_name": "Agreeableness", "score": 0.462989, "tone_id": "agreeableness_big5"}, {"tone_name": "Emotional Range", "score": 0.380698, "tone_id": "emotional_range_big5"}], "category_name": "Social Tone"}], "input_from": 1955}, {"input_to": 2056, "text": "May be his right now, but your body's still me, woah.", "sentence_id": 59, "tone_categories": [{"category_id": "emotion_tone", "tones": [{"tone_name": "Anger", "score": 0.161899, "tone_id": "anger"}, {"tone_name": "Disgust", "score": 0.06581, "tone_id": "disgust"}, {"tone_name": "Fear", "score": 0.234383, "tone_id": "fear"}, {"tone_name": "Joy", "score": 0.12756, "tone_id": "joy"}, {"tone_name": "Sadness", "score": 0.47948, "tone_id": "sadness"}], "category_name": "Emotion Tone"}, {"category_id": "language_tone", "tones": [{"tone_name": "Analytical", "score": 0.0, "tone_id": "analytical"}, {"tone_name": "Confident", "score": 0.0, "tone_id": "confident"}, {"tone_name": "Tentative", "score": 0.786991, "tone_id": "tentative"}], "category_name": "Language Tone"}, {"category_id": "social_tone", "tones": [{"tone_name": "Openness", "score": 0.561418, "tone_id": "openness_big5"}, {"tone_name": "Conscientiousness", "score": 0.881716, "tone_id": "conscientiousness_big5"}, {"tone_name": "Extraversion", "score": 0.585395, "tone_id": "extraversion_big5"}, {"tone_name": "Agreeableness", "score": 0.979966, "tone_id": "agreeableness_big5"}, {"tone_name": "Emotional Range", "score": 0.190922, "tone_id": "emotional_range_big5"}], "category_name": "Social Tone"}], "input_from": 2003}, {"input_to": 2094, "text": "I don't wanna know, know, know, know.", "sentence_id": 60, "tone_categories": [{"category_id": "emotion_tone", "tones": [{"tone_name": "Anger", "score": 0.08893, "tone_id": "anger"}, {"tone_name": "Disgust", "score": 0.029665, "tone_id": "disgust"}, {"tone_name": "Fear", "score": 0.128077, "tone_id": "fear"}, {"tone_name": "Joy", "score": 0.122079, "tone_id": "joy"}, {"tone_name": "Sadness", "score": 0.719966, "tone_id": "sadness"}], "category_name": "Emotion Tone"}, {"category_id": "language_tone", "tones": [{"tone_name": "Analytical", "score": 0.93884, "tone_id": "analytical"}, {"tone_name": "Confident", "score": 0.0, "tone_id": "confident"}, {"tone_name": "Tentative", "score": 0.0, "tone_id": "tentative"}], "category_name": "Language Tone"}, {"category_id": "social_tone", "tones": [{"tone_name": "Openness", "score": 0.110727, "tone_id": "openness_big5"}, {"tone_name": "Conscientiousness", "score": 0.328356, "tone_id": "conscientiousness_big5"}, {"tone_name": "Extraversion", "score": 0.404247, "tone_id": "extraversion_big5"}, {"tone_name": "Agreeableness", "score": 0.568497, "tone_id": "agreeableness_big5"}, {"tone_name": "Emotional Range", "score": 0.276836, "tone_id": "emotional_range_big5"}], "category_name": "Social Tone"}], "input_from": 2057}, {"input_to": 2135, "text": "Who's taking you home, home, home, home.", "sentence_id": 61, "tone_categories": [{"category_id": "emotion_tone", "tones": [{"tone_name": "Anger", "score": 0.12746, "tone_id": "anger"}, {"tone_name": "Disgust", "score": 0.073118, "tone_id": "disgust"}, {"tone_name": "Fear", "score": 0.145777, "tone_id": "fear"}, {"tone_name": "Joy", "score": 0.680181, "tone_id": "joy"}, {"tone_name": "Sadness", "score": 0.070942, "tone_id": "sadness"}], "category_name": "Emotion Tone"}, {"category_id": "language_tone", "tones": [{"tone_name": "Analytical", "score": 0.0, "tone_id": "analytical"}, {"tone_name": "Confident", "score": 0.0, "tone_id": "confident"}, {"tone_name": "Tentative", "score": 0.0, "tone_id": "tentative"}], "category_name": "Language Tone"}, {"category_id": "social_tone", "tones": [{"tone_name": "Openness", "score": 0.00805, "tone_id": "openness_big5"}, {"tone_name": "Conscientiousness", "score": 0.286228, "tone_id": "conscientiousness_big5"}, {"tone_name": "Extraversion", "score": 0.553924, "tone_id": "extraversion_big5"}, {"tone_name": "Agreeableness", "score": 0.615368, "tone_id": "agreeableness_big5"}, {"tone_name": "Emotional Range", "score": 0.369658, "tone_id": "emotional_range_big5"}], "category_name": "Social Tone"}], "input_from": 2095}, {"input_to": 2166, "text": "And loving you so, so, so, so.", "sentence_id": 62, "tone_categories": [{"category_id": "emotion_tone", "tones": [{"tone_name": "Anger", "score": 0.044234, "tone_id": "anger"}, {"tone_name": "Disgust", "score": 0.013642, "tone_id": "disgust"}, {"tone_name": "Fear", "score": 0.025767, "tone_id": "fear"}, {"tone_name": "Joy", "score": 0.723575, "tone_id": "joy"}, {"tone_name": "Sadness", "score": 0.242875, "tone_id": "sadness"}], "category_name": "Emotion Tone"}, {"category_id": "language_tone", "tones": [{"tone_name": "Analytical", "score": 0.0, "tone_id": "analytical"}, {"tone_name": "Confident", "score": 0.0, "tone_id": "confident"}, {"tone_name": "Tentative", "score": 0.0, "tone_id": "tentative"}], "category_name": "Language Tone"}, {"category_id": "social_tone", "tones": [{"tone_name": "Openness", "score": 0.097814, "tone_id": "openness_big5"}, {"tone_name": "Conscientiousness", "score": 0.280442, "tone_id": "conscientiousness_big5"}, {"tone_name": "Extraversion", "score": 0.581671, "tone_id": "extraversion_big5"}, {"tone_name": "Agreeableness", "score": 0.634751, "tone_id": "agreeableness_big5"}, {"tone_name": "Emotional Range", "score": 0.067996, "tone_id": "emotional_range_big5"}], "category_name": "Social Tone"}], "input_from": 2136}, {"input_to": 2198, "text": "The way I used to love you, no.", "sentence_id": 63, "tone_categories": [{"category_id": "emotion_tone", "tones": [{"tone_name": "Anger", "score": 0.098945, "tone_id": "anger"}, {"tone_name": "Disgust", "score": 0.053495, "tone_id": "disgust"}, {"tone_name": "Fear", "score": 0.077129, "tone_id": "fear"}, {"tone_name": "Joy", "score": 0.097725, "tone_id": "joy"}, {"tone_name": "Sadness", "score": 0.726223, "tone_id": "sadness"}], "category_name": "Emotion Tone"}, {"category_id": "language_tone", "tones": [{"tone_name": "Analytical", "score": 0.116314, "tone_id": "analytical"}, {"tone_name": "Confident", "score": 0.0, "tone_id": "confident"}, {"tone_name": "Tentative", "score": 0.0, "tone_id": "tentative"}], "category_name": "Language Tone"}, {"category_id": "social_tone", "tones": [{"tone_name": "Openness", "score": 0.11046, "tone_id": "openness_big5"}, {"tone_name": "Conscientiousness", "score": 0.550654, "tone_id": "conscientiousness_big5"}, {"tone_name": "Extraversion", "score": 0.616951, "tone_id": "extraversion_big5"}, {"tone_name": "Agreeableness", "score": 0.74965, "tone_id": "agreeableness_big5"}, {"tone_name": "Emotional Range", "score": 0.823096, "tone_id": "emotional_range_big5"}], "category_name": "Social Tone"}], "input_from": 2167}, {"input_to": 2236, "text": "I don't wanna know, know, know, know.", "sentence_id": 64, "tone_categories": [{"category_id": "emotion_tone", "tones": [{"tone_name": "Anger", "score": 0.08893, "tone_id": "anger"}, {"tone_name": "Disgust", "score": 0.029665, "tone_id": "disgust"}, {"tone_name": "Fear", "score": 0.128077, "tone_id": "fear"}, {"tone_name": "Joy", "score": 0.122079, "tone_id": "joy"}, {"tone_name": "Sadness", "score": 0.719966, "tone_id": "sadness"}], "category_name": "Emotion Tone"}, {"category_id": "language_tone", "tones": [{"tone_name": "Analytical", "score": 0.93884, "tone_id": "analytical"}, {"tone_name": "Confident", "score": 0.0, "tone_id": "confident"}, {"tone_name": "Tentative", "score": 0.0, "tone_id": "tentative"}], "category_name": "Language Tone"}, {"category_id": "social_tone", "tones": [{"tone_name": "Openness", "score": 0.110727, "tone_id": "openness_big5"}, {"tone_name": "Conscientiousness", "score": 0.328356, "tone_id": "conscientiousness_big5"}, {"tone_name": "Extraversion", "score": 0.404247, "tone_id": "extraversion_big5"}, {"tone_name": "Agreeableness", "score": 0.568497, "tone_id": "agreeableness_big5"}, {"tone_name": "Emotional Range", "score": 0.276836, "tone_id": "emotional_range_big5"}], "category_name": "Social Tone"}], "input_from": 2199}, {"input_to": 2277, "text": "Who's taking you home, home, home, home.", "sentence_id": 65, "tone_categories": [{"category_id": "emotion_tone", "tones": [{"tone_name": "Anger", "score": 0.12746, "tone_id": "anger"}, {"tone_name": "Disgust", "score": 0.073118, "tone_id": "disgust"}, {"tone_name": "Fear", "score": 0.145777, "tone_id": "fear"}, {"tone_name": "Joy", "score": 0.680181, "tone_id": "joy"}, {"tone_name": "Sadness", "score": 0.070942, "tone_id": "sadness"}], "category_name": "Emotion Tone"}, {"category_id": "language_tone", "tones": [{"tone_name": "Analytical", "score": 0.0, "tone_id": "analytical"}, {"tone_name": "Confident", "score": 0.0, "tone_id": "confident"}, {"tone_name": "Tentative", "score": 0.0, "tone_id": "tentative"}], "category_name": "Language Tone"}, {"category_id": "social_tone", "tones": [{"tone_name": "Openness", "score": 0.00805, "tone_id": "openness_big5"}, {"tone_name": "Conscientiousness", "score": 0.286228, "tone_id": "conscientiousness_big5"}, {"tone_name": "Extraversion", "score": 0.553924, "tone_id": "extraversion_big5"}, {"tone_name": "Agreeableness", "score": 0.615368, "tone_id": "agreeableness_big5"}, {"tone_name": "Emotional Range", "score": 0.369658, "tone_id": "emotional_range_big5"}], "category_name": "Social Tone"}], "input_from": 2237}, {"input_to": 2308, "text": "And loving you so, so, so, so.", "sentence_id": 66, "tone_categories": [{"category_id": "emotion_tone", "tones": [{"tone_name": "Anger", "score": 0.044234, "tone_id": "anger"}, {"tone_name": "Disgust", "score": 0.013642, "tone_id": "disgust"}, {"tone_name": "Fear", "score": 0.025767, "tone_id": "fear"}, {"tone_name": "Joy", "score": 0.723575, "tone_id": "joy"}, {"tone_name": "Sadness", "score": 0.242875, "tone_id": "sadness"}], "category_name": "Emotion Tone"}, {"category_id": "language_tone", "tones": [{"tone_name": "Analytical", "score": 0.0, "tone_id": "analytical"}, {"tone_name": "Confident", "score": 0.0, "tone_id": "confident"}, {"tone_name": "Tentative", "score": 0.0, "tone_id": "tentative"}], "category_name": "Language Tone"}, {"category_id": "social_tone", "tones": [{"tone_name": "Openness", "score": 0.097814, "tone_id": "openness_big5"}, {"tone_name": "Conscientiousness", "score": 0.280442, "tone_id": "conscientiousness_big5"}, {"tone_name": "Extraversion", "score": 0.581671, "tone_id": "extraversion_big5"}, {"tone_name": "Agreeableness", "score": 0.634751, "tone_id": "agreeableness_big5"}, {"tone_name": "Emotional Range", "score": 0.067996, "tone_id": "emotional_range_big5"}], "category_name": "Social Tone"}], "input_from": 2278}, {"input_to": 2340, "text": "The way I used to love you, oh.", "sentence_id": 67, "tone_categories": [{"category_id": "emotion_tone", "tones": [{"tone_name": "Anger", "score": 0.090054, "tone_id": "anger"}, {"tone_name": "Disgust", "score": 0.037155, "tone_id": "disgust"}, {"tone_name": "Fear", "score": 0.079356, "tone_id": "fear"}, {"tone_name": "Joy", "score": 0.146338, "tone_id": "joy"}, {"tone_name": "Sadness", "score": 0.683564, "tone_id": "sadness"}], "category_name": "Emotion Tone"}, {"category_id": "language_tone", "tones": [{"tone_name": "Analytical", "score": 0.0, "tone_id": "analytical"}, {"tone_name": "Confident", "score": 0.0, "tone_id": "confident"}, {"tone_name": "Tentative", "score": 0.0, "tone_id": "tentative"}], "category_name": "Language Tone"}, {"category_id": "social_tone", "tones": [{"tone_name": "Openness", "score": 0.126115, "tone_id": "openness_big5"}, {"tone_name": "Conscientiousness", "score": 0.671193, "tone_id": "conscientiousness_big5"}, {"tone_name": "Extraversion", "score": 0.617389, "tone_id": "extraversion_big5"}, {"tone_name": "Agreeableness", "score": 0.947059, "tone_id": "agreeableness_big5"}, {"tone_name": "Emotional Range", "score": 0.790395, "tone_id": "emotional_range_big5"}], "category_name": "Social Tone"}], "input_from": 2309}, {"input_to": 2360, "text": "I don't wanna know.", "sentence_id": 68, "tone_categories": [{"category_id": "emotion_tone", "tones": [{"tone_name": "Anger", "score": 0.112917, "tone_id": "anger"}, {"tone_name": "Disgust", "score": 0.047376, "tone_id": "disgust"}, {"tone_name": "Fear", "score": 0.164002, "tone_id": "fear"}, {"tone_name": "Joy", "score": 0.101987, "tone_id": "joy"}, {"tone_name": "Sadness", "score": 0.662436, "tone_id": "sadness"}], "category_name": "Emotion Tone"}, {"category_id": "language_tone", "tones": [{"tone_name": "Analytical", "score": 0.0, "tone_id": "analytical"}, {"tone_name": "Confident", "score": 0.0, "tone_id": "confident"}, {"tone_name": "Tentative", "score": 0.0, "tone_id": "tentative"}], "category_name": "Language Tone"}, {"category_id": "social_tone", "tones": [{"tone_name": "Openness", "score": 0.075882, "tone_id": "openness_big5"}, {"tone_name": "Conscientiousness", "score": 0.299336, "tone_id": "conscientiousness_big5"}, {"tone_name": "Extraversion", "score": 0.37318, "tone_id": "extraversion_big5"}, {"tone_name": "Agreeableness", "score": 0.547426, "tone_id": "agreeableness_big5"}, {"tone_name": "Emotional Range", "score": 0.117378, "tone_id": "emotional_range_big5"}], "category_name": "Social Tone"}], "input_from": 2341}, {"input_to": 2398, "text": "I don't wanna know, know, know, know.", "sentence_id": 69, "tone_categories": [{"category_id": "emotion_tone", "tones": [{"tone_name": "Anger", "score": 0.08893, "tone_id": "anger"}, {"tone_name": "Disgust", "score": 0.029665, "tone_id": "disgust"}, {"tone_name": "Fear", "score": 0.128077, "tone_id": "fear"}, {"tone_name": "Joy", "score": 0.122079, "tone_id": "joy"}, {"tone_name": "Sadness", "score": 0.719966, "tone_id": "sadness"}], "category_name": "Emotion Tone"}, {"category_id": "language_tone", "tones": [{"tone_name": "Analytical", "score": 0.93884, "tone_id": "analytical"}, {"tone_name": "Confident", "score": 0.0, "tone_id": "confident"}, {"tone_name": "Tentative", "score": 0.0, "tone_id": "tentative"}], "category_name": "Language Tone"}, {"category_id": "social_tone", "tones": [{"tone_name": "Openness", "score": 0.110727, "tone_id": "openness_big5"}, {"tone_name": "Conscientiousness", "score": 0.328356, "tone_id": "conscientiousness_big5"}, {"tone_name": "Extraversion", "score": 0.404247, "tone_id": "extraversion_big5"}, {"tone_name": "Agreeableness", "score": 0.568497, "tone_id": "agreeableness_big5"}, {"tone_name": "Emotional Range", "score": 0.276836, "tone_id": "emotional_range_big5"}], "category_name": "Social Tone"}], "input_from": 2361}, {"input_to": 2439, "text": "Who's taking you home, home, home, home.", "sentence_id": 70, "tone_categories": [{"category_id": "emotion_tone", "tones": [{"tone_name": "Anger", "score": 0.12746, "tone_id": "anger"}, {"tone_name": "Disgust", "score": 0.073118, "tone_id": "disgust"}, {"tone_name": "Fear", "score": 0.145777, "tone_id": "fear"}, {"tone_name": "Joy", "score": 0.680181, "tone_id": "joy"}, {"tone_name": "Sadness", "score": 0.070942, "tone_id": "sadness"}], "category_name": "Emotion Tone"}, {"category_id": "language_tone", "tones": [{"tone_name": "Analytical", "score": 0.0, "tone_id": "analytical"}, {"tone_name": "Confident", "score": 0.0, "tone_id": "confident"}, {"tone_name": "Tentative", "score": 0.0, "tone_id": "tentative"}], "category_name": "Language Tone"}, {"category_id": "social_tone", "tones": [{"tone_name": "Openness", "score": 0.00805, "tone_id": "openness_big5"}, {"tone_name": "Conscientiousness", "score": 0.286228, "tone_id": "conscientiousness_big5"}, {"tone_name": "Extraversion", "score": 0.553924, "tone_id": "extraversion_big5"}, {"tone_name": "Agreeableness", "score": 0.615368, "tone_id": "agreeableness_big5"}, {"tone_name": "Emotional Range", "score": 0.369658, "tone_id": "emotional_range_big5"}], "category_name": "Social Tone"}], "input_from": 2399}, {"input_to": 2470, "text": "And loving you so, so, so, so.", "sentence_id": 71, "tone_categories": [{"category_id": "emotion_tone", "tones": [{"tone_name": "Anger", "score": 0.044234, "tone_id": "anger"}, {"tone_name": "Disgust", "score": 0.013642, "tone_id": "disgust"}, {"tone_name": "Fear", "score": 0.025767, "tone_id": "fear"}, {"tone_name": "Joy", "score": 0.723575, "tone_id": "joy"}, {"tone_name": "Sadness", "score": 0.242875, "tone_id": "sadness"}], "category_name": "Emotion Tone"}, {"category_id": "language_tone", "tones": [{"tone_name": "Analytical", "score": 0.0, "tone_id": "analytical"}, {"tone_name": "Confident", "score": 0.0, "tone_id": "confident"}, {"tone_name": "Tentative", "score": 0.0, "tone_id": "tentative"}], "category_name": "Language Tone"}, {"category_id": "social_tone", "tones": [{"tone_name": "Openness", "score": 0.097814, "tone_id": "openness_big5"}, {"tone_name": "Conscientiousness", "score": 0.280442, "tone_id": "conscientiousness_big5"}, {"tone_name": "Extraversion", "score": 0.581671, "tone_id": "extraversion_big5"}, {"tone_name": "Agreeableness", "score": 0.634751, "tone_id": "agreeableness_big5"}, {"tone_name": "Emotional Range", "score": 0.067996, "tone_id": "emotional_range_big5"}], "category_name": "Social Tone"}], "input_from": 2440}, {"input_to": 2502, "text": "The way I used to love you, oh.", "sentence_id": 72, "tone_categories": [{"category_id": "emotion_tone", "tones": [{"tone_name": "Anger", "score": 0.090054, "tone_id": "anger"}, {"tone_name": "Disgust", "score": 0.037155, "tone_id": "disgust"}, {"tone_name": "Fear", "score": 0.079356, "tone_id": "fear"}, {"tone_name": "Joy", "score": 0.146338, "tone_id": "joy"}, {"tone_name": "Sadness", "score": 0.683564, "tone_id": "sadness"}], "category_name": "Emotion Tone"}, {"category_id": "language_tone", "tones": [{"tone_name": "Analytical", "score": 0.0, "tone_id": "analytical"}, {"tone_name": "Confident", "score": 0.0, "tone_id": "confident"}, {"tone_name": "Tentative", "score": 0.0, "tone_id": "tentative"}], "category_name": "Language Tone"}, {"category_id": "social_tone", "tones": [{"tone_name": "Openness", "score": 0.126115, "tone_id": "openness_big5"}, {"tone_name": "Conscientiousness", "score": 0.671193, "tone_id": "conscientiousness_big5"}, {"tone_name": "Extraversion", "score": 0.617389, "tone_id": "extraversion_big5"}, {"tone_name": "Agreeableness", "score": 0.947059, "tone_id": "agreeableness_big5"}, {"tone_name": "Emotional Range", "score": 0.790395, "tone_id": "emotional_range_big5"}], "category_name": "Social Tone"}], "input_from": 2471}, {"input_to": 2522, "text": "I don't wanna know.", "sentence_id": 73, "tone_categories": [{"category_id": "emotion_tone", "tones": [{"tone_name": "Anger", "score": 0.112917, "tone_id": "anger"}, {"tone_name": "Disgust", "score": 0.047376, "tone_id": "disgust"}, {"tone_name": "Fear", "score": 0.164002, "tone_id": "fear"}, {"tone_name": "Joy", "score": 0.101987, "tone_id": "joy"}, {"tone_name": "Sadness", "score": 0.662436, "tone_id": "sadness"}], "category_name": "Emotion Tone"}, {"category_id": "language_tone", "tones": [{"tone_name": "Analytical", "score": 0.0, "tone_id": "analytical"}, {"tone_name": "Confident", "score": 0.0, "tone_id": "confident"}, {"tone_name": "Tentative", "score": 0.0, "tone_id": "tentative"}], "category_name": "Language Tone"}, {"category_id": "social_tone", "tones": [{"tone_name": "Openness", "score": 0.075882, "tone_id": "openness_big5"}, {"tone_name": "Conscientiousness", "score": 0.299336, "tone_id": "conscientiousness_big5"}, {"tone_name": "Extraversion", "score": 0.37318, "tone_id": "extraversion_big5"}, {"tone_name": "Agreeableness", "score": 0.547426, "tone_id": "agreeableness_big5"}, {"tone_name": "Emotional Range", "score": 0.117378, "tone_id": "emotional_range_big5"}], "category_name": "Social Tone"}], "input_from": 2503}, {"input_to": 2530, "text": "Oh hey.", "sentence_id": 74, "tone_categories": [], "input_from": 2523}, {"input_to": 2542, "text": "Oh, oh hey.", "sentence_id": 75, "tone_categories": [], "input_from": 2531}, {"input_to": 2558, "text": "Oh, oh, oh hey.", "sentence_id": 76, "tone_categories": [{"category_id": "emotion_tone", "tones": [{"tone_name": "Anger", "score": 0.097065, "tone_id": "anger"}, {"tone_name": "Disgust", "score": 0.041484, "tone_id": "disgust"}, {"tone_name": "Fear", "score": 0.176703, "tone_id": "fear"}, {"tone_name": "Joy", "score": 0.323319, "tone_id": "joy"}, {"tone_name": "Sadness", "score": 0.410897, "tone_id": "sadness"}], "category_name": "Emotion Tone"}, {"category_id": "language_tone", "tones": [{"tone_name": "Analytical", "score": 0.0, "tone_id": "analytical"}, {"tone_name": "Confident", "score": 0.0, "tone_id": "confident"}, {"tone_name": "Tentative", "score": 0.0, "tone_id": "tentative"}], "category_name": "Language Tone"}, {"category_id": "social_tone", "tones": [{"tone_name": "Openness", "score": 0.259574, "tone_id": "openness_big5"}, {"tone_name": "Conscientiousness", "score": 0.274457, "tone_id": "conscientiousness_big5"}, {"tone_name": "Extraversion", "score": 0.543206, "tone_id": "extraversion_big5"}, {"tone_name": "Agreeableness", "score": 0.59952, "tone_id": "agreeableness_big5"}, {"tone_name": "Emotional Range", "score": 0.299772, "tone_id": "emotional_range_big5"}], "category_name": "Social Tone"}], "input_from": 2543}, {"input_to": 2572, "text": "Uh oh, uh oh.", "sentence_id": 77, "tone_categories": [{"category_id": "emotion_tone", "tones": [{"tone_name": "Anger", "score": 0.051112, "tone_id": "anger"}, {"tone_name": "Disgust", "score": 0.035952, "tone_id": "disgust"}, {"tone_name": "Fear", "score": 0.577526, "tone_id": "fear"}, {"tone_name": "Joy", "score": 0.347636, "tone_id": "joy"}, {"tone_name": "Sadness", "score": 0.049835, "tone_id": "sadness"}], "category_name": "Emotion Tone"}, {"category_id": "language_tone", "tones": [{"tone_name": "Analytical", "score": 0.0, "tone_id": "analytical"}, {"tone_name": "Confident", "score": 0.0, "tone_id": "confident"}, {"tone_name": "Tentative", "score": 0.0, "tone_id": "tentative"}], "category_name": "Language Tone"}, {"category_id": "social_tone", "tones": [{"tone_name": "Openness", "score": 0.260223, "tone_id": "openness_big5"}, {"tone_name": "Conscientiousness", "score": 0.274457, "tone_id": "conscientiousness_big5"}, {"tone_name": "Extraversion", "score": 0.543033, "tone_id": "extraversion_big5"}, {"tone_name": "Agreeableness", "score": 0.599501, "tone_id": "agreeableness_big5"}, {"tone_name": "Emotional Range", "score": 0.294499, "tone_id": "emotional_range_big5"}], "category_name": "Social Tone"}], "input_from": 2559}]}